Workbook

Sheet Plant, Month & PO Defect Analys
B1: ERC Inspection Details
A2: Firm Name | B2: Month | C2: PO Number /Date | D2: Zonal Railway (Purchaser) | E2: Consignee Details | F2: Inspected (Nos.) | G2: Acceptance (Nos.) | H2: % Acceptance | I2: Rejection (Nos.) | J2: % Rejection | K2: Visual (Sheared Edges, Surface Defects) | L2: ="%"&K2 -> %Visual (Sheared Edges, Surface Defects) | M2: Dimensional | N2: ="%"&M2 -> %Dimensional | O2: Cut bar length | P2: ="%"&O2 -> %Cut bar length | Q2: Cut Bar diameter | R2: ="%"&Q2 -> %Cut Bar diameter | S2: Turning length | T2: ="%"&S2 -> %Turning length | U2: Turning Bar Diameter | V2: ="%"&U2 -> %Turning Bar Diameter | W2: Flat Bearing Area | X2: ="%"&W2 -> %Flat Bearing Area | Y2: Application & Deflection test | Z2: ="%"&Y2 -> %Application & Deflection test | AA2: Chemical Composition | AB2: ="%"&AA2 -> %Chemical Composition | AC2: Toe load | AD2: ="%"&AC2 -> %Toe load | AE2: Hardness | AF2: ="%"&AE2 -> %Hardness | AG2: Microstructure | AH2: ="%"&AG2 -> %Microstructure | AI2: Grain size | AJ2: ="%"&AI2 -> %Grain size | AK2: Depth of Decarburization | AL2: ="%"&AK2 -> %Depth of Decarburization | AM2: Inclusion rating | AN2: ="%"&AM2 -> %Inclusion rating | AO2: MPI | AP2: ="%"&AO2 -> %MPI | AQ2: Forging defect | AR2: ="%"&AQ2 -> %Forging defect | AS2: Marking | AT2: ="%"&AS2 -> %Marking | AU2: Embossing Die Impression / Failure | AV2: ="%"&AU2 -> %Embossing Die Impression / Failure | AW2: Other (less weight) | AX2: ="%"&AW2 -> %Other (less weight)
A3: ERIO AMBE FASTNERS PVT.LTD. Patna Bihar | B3: December 2025 | C3: NO PRODUCTION | H3: =G3/F3 -> #DIV/0! | J3: =I3/F3 -> #DIV/0! | L3: =K3/F3 -> #DIV/0! | N3: =M3/F3 -> #DIV/0! | P3: =O3/F3 -> #DIV/0! | R3: =Q3/F3 -> #DIV/0! | T3: =S3/F3 -> #DIV/0! | V3: =U3/F3 -> #DIV/0! | X3: =W3/F3 -> #DIV/0! | Z3: =Y3/F3 -> #DIV/0! | AB3: =AA3/F3 -> #DIV/0! | AD3: =AC3/F3 -> #DIV/0! | AF3: =AE3/F3 -> #DIV/0! | AH3: =AG3/F3 -> #DIV/0! | AJ3: =AI3/F3 -> #DIV/0! | AL3: =AK3/F3 -> #DIV/0! | AN3: =AM3/F3 -> #DIV/0! | AP3: =AO3/F3 -> #DIV/0! | AR3: =AQ3/F3 -> #DIV/0! | AT3: =AS3/F3 -> #DIV/0! | AV3: =AU3/F3 -> #DIV/0! | AX3: =AW3/F3 -> #DIV/0!
A4: ERIO AMBE FASTNERS PVT.LTD. Patna Bihar | B4: Jan 2026 | C4: NO PRODUCTION | H4: =G4/F4 -> #DIV/0! | J4: =I4/F4 -> #DIV/0! | L4: =K4/F4 -> #DIV/0! | N4: =M4/F4 -> #DIV/0! | P4: =O4/F4 -> #DIV/0! | R4: =Q4/F4 -> #DIV/0! | T4: =S4/F4 -> #DIV/0! | V4: =U4/F4 -> #DIV/0! | X4: =W4/F4 -> #DIV/0! | Z4: =Y4/F4 -> #DIV/0! | AB4: =AA4/F4 -> #DIV/0! | AD4: =AC4/F4 -> #DIV/0! | AF4: =AE4/F4 -> #DIV/0! | AH4: =AG4/F4 -> #DIV/0! | AJ4: =AI4/F4 -> #DIV/0! | AL4: =AK4/F4 -> #DIV/0! | AN4: =AM4/F4 -> #DIV/0! | AP4: =AO4/F4 -> #DIV/0! | AR4: =AQ4/F4 -> #DIV/0! | AT4: =AS4/F4 -> #DIV/0! | AV4: =AU4/F4 -> #DIV/0! | AX4: =AW4/F4 -> #DIV/0! | AZ4: =AY4-I4 -> 0
A5: ERIO CALCUTTA SPRINGS LTD. Howrah West Bengal | B5: December 2025 | C5: 07254988202255 Dt. 14.06.2025 | D5: East Central | E5: ECR | F5: 57229 | G5: 56431 | H5: =G5/F5 -> 0.98605602 | I5: 798 | J5: =I5/F5 -> 0.013943979 | K5: 0 | L5: =K5/F5 -> 0 | M5: 80 | N5: =M5/F5 -> 0.0013978927 | O5: 101 | P5: =O5/F5 -> 0.0017648395 | R5: =Q5/F5 -> 0 | S5: 54 | T5: =S5/F5 -> 0.00094357756 | U5: 36 | V5: =U5/F5 -> 0.0006290517 | W5: 2 | X5: =W5/F5 -> 3.4947317e-05 | Z5: =Y5/F5 -> 0 | AB5: =AA5/F5 -> 0 | AC5: 36 | AD5: =AC5/F5 -> 0.0006290517 | AE5: 23 | AF5: =AE5/F5 -> 0.00040189414 | AH5: =AG5/F5 -> 0 | AJ5: =AI5/F5 -> 0 | AL5: =AK5/F5 -> 0 | AN5: =AM5/F5 -> 0 | AO5: 13 | AP5: =AO5/F5 -> 0.00022715756 | AQ5: 180 | AR5: =AQ5/F5 -> 0.0031452585 | AT5: =AS5/F5 -> 0 | AU5: 220 | AV5: =AU5/F5 -> 0.0038442049 | AW5: 53 | AX5: =AW5/F5 -> 0.0009261039
A6: ERIO CALCUTTA SPRINGS LTD. Howrah West Bengal | B6: December 2025 | C6: 61245413103216 dated 24.06.2025 | D6: North East Frontier | E6: NFR | F6: 113857 | G6: 113598 | H6: =G6/F6 -> 0.99772522 | I6: 259 | J6: =I6/F6 -> 0.0022747833 | K6: 0 | L6: =K6/F6 -> 0 | M6: 8 | N6: =M6/F6 -> 7.0263576e-05 | O6: 55 | P6: =O6/F6 -> 0.00048306209 | R6: =Q6/F6 -> 0 | S6: 28 | T6: =S6/F6 -> 0.00024592252 | U6: 0 | V6: =U6/F6 -> 0 | W6: 0 | X6: =W6/F6 -> 0 | Z6: =Y6/F6 -> 0 | AB6: =AA6/F6 -> 0 | AC6: 21 | AD6: =AC6/F6 -> 0.00018444189 | AE6: 19 | AF6: =AE6/F6 -> 0.00016687599 | AH6: =AG6/F6 -> 0 | AJ6: =AI6/F6 -> 0 | AL6: =AK6/F6 -> 0 | AN6: =AM6/F6 -> 0 | AO6: 10 | AP6: =AO6/F6 -> 8.782947e-05 | AQ6: 43 | AR6: =AQ6/F6 -> 0.00037766672 | AT6: =AS6/F6 -> 0 | AU6: 51 | AV6: =AU6/F6 -> 0.0004479303 | AW6: 24 | AX6: =AW6/F6 -> 0.00021079073
A7: ERIO CALCUTTA SPRINGS LTD. Howrah West Bengal | B7: December 2025 | C7: 06255112102398 dated 06.08.2025 | D7: East Coast | E7: ECoR | F7: 146606 | G7: 145018 | H7: =G7/F7 -> 0.98916825 | I7: 1588 | J7: =I7/F7 -> 0.010831753 | K7: 0 | L7: =K7/F7 -> 0 | M7: 240 | N7: =M7/F7 -> 0.0016370408 | O7: 267 | P7: =O7/F7 -> 0.0018212079 | R7: =Q7/F7 -> 0 | S7: 150 | T7: =S7/F7 -> 0.0010231505 | U7: 13 | V7: =U7/F7 -> 8.8673042e-05 | W7: 0 | X7: =W7/F7 -> 0 | Z7: =Y7/F7 -> 0 | AB7: =AA7/F7 -> 0 | AC7: 34 | AD7: =AC7/F7 -> 0.00023191411 | AE7: 55 | AF7: =AE7/F7 -> 0.00037515518 | AH7: =AG7/F7 -> 0 | AJ7: =AI7/F7 -> 0 | AL7: =AK7/F7 -> 0 | AN7: =AM7/F7 -> 0 | AO7: 26 | AP7: =AO7/F7 -> 0.00017734608 | AQ7: 261 | AR7: =AQ7/F7 -> 0.0017802818 | AT7: =AS7/F7 -> 0 | AU7: 376 | AV7: =AU7/F7 -> 0.0025646972 | AW7: 166 | AX7: =AW7/F7 -> 0.0011322865
A8: ERIO CALCUTTA SPRINGS LTD. Howrah West Bengal | B8: December 2025 | C8: 61255131105052 Dt. 19.09.2025 | D8: North East Frontier | E8: NFR | F8: 57357 | G8: 57029 | H8: =G8/F8 -> 0.99428143 | I8: 328 | J8: =I8/F8 -> 0.0057185697 | K8: 10 | L8: =K8/F8 -> 0.00017434664 | M8: 66 | N8: =M8/F8 -> 0.0011506878 | O8: 35 | P8: =O8/F8 -> 0.00061021323 | R8: =Q8/F8 -> 0 | S8: 30 | T8: =S8/F8 -> 0.00052303991 | U8: 0 | V8: =U8/F8 -> 0 | W8: 0 | X8: =W8/F8 -> 0 | Z8: =Y8/F8 -> 0 | AB8: =AA8/F8 -> 0 | AC8: 14 | AD8: =AC8/F8 -> 0.00024408529 | AE8: 21 | AF8: =AE8/F8 -> 0.00036612794 | AH8: =AG8/F8 -> 0 | AJ8: =AI8/F8 -> 0 | AL8: =AK8/F8 -> 0 | AN8: =AM8/F8 -> 0 | AO8: 7 | AP8: =AO8/F8 -> 0.00012204265 | AQ8: 51 | AR8: =AQ8/F8 -> 0.00088916784 | AT8: =AS8/F8 -> 0 | AU8: 58 | AV8: =AU8/F8 -> 0.0010112105 | AW8: 36 | AX8: =AW8/F8 -> 0.00062764789
A9: ERIO CALCUTTA SPRINGS LTD. Howrah West Bengal | B9: Jan 2026 | C9: 07254988202255 DT. 14.06.2025 | D9: East Central | E9: ECR | F9: 64844 | G9: 64466 | H9: =G9/F9 -> 0.99417062 | I9: 378 | J9: =I9/F9 -> 0.0058293751 | K9: 4 | L9: =K9/F9 -> 6.1686509e-05 | M9: 50 | N9: =M9/F9 -> 0.00077108136 | O9: 42 | P9: =O9/F9 -> 0.00064770835 | R9: =Q9/F9 -> 0 | S9: 9 | T9: =S9/F9 -> 0.00013879465 | U9: 25 | V9: =U9/F9 -> 0.00038554068 | W9: 7 | X9: =W9/F9 -> 0.00010795139 | Z9: =Y9/F9 -> 0 | AB9: =AA9/F9 -> 0 | AC9: 26 | AD9: =AC9/F9 -> 0.00040096231 | AE9: 24 | AF9: =AE9/F9 -> 0.00037011905 | AH9: =AG9/F9 -> 0 | AJ9: =AI9/F9 -> 0 | AL9: =AK9/F9 -> 0 | AN9: =AM9/F9 -> 0 | AO9: 13 | AP9: =AO9/F9 -> 0.00020048115 | AQ9: 64 | AR9: =AQ9/F9 -> 0.00098698415 | AS9: 0 | AT9: =AS9/F9 -> 0 | AU9: 73 | AV9: =AU9/F9 -> 0.0011257788 | AX9: =AW9/F9 -> 0 | AY9: =SUM(K9:AX9) -> 337.0052 | AZ9: =AY9-I9 -> -40.994803
A10: ERIO CALCUTTA SPRINGS LTD. Howrah West Bengal | B10: Jan 2026 | C10: 61255131105052 Dt. 19.09.2025 | D10: North East Frontier | E10: NFR | F10: 237717 | G10: 235955 | H10: =G10/F10 -> 0.99258783 | I10: 1762 | J10: =I10/F10 -> 0.007412175 | K10: 160 | L10: =K10/F10 -> 0.00067306924 | M10: 204 | N10: =M10/F10 -> 0.00085816328 | O10: 126 | P10: =O10/F10 -> 0.00053004202 | R10: =Q10/F10 -> 0 | S10: 107 | T10: =S10/F10 -> 0.00045011505 | U10: 109 | V10: =U10/F10 -> 0.00045852842 | W10: 22 | X10: =W10/F10 -> 9.254702e-05 | Z10: =Y10/F10 -> 0 | AB10: =AA10/F10 -> 0 | AC10: 42 | AD10: =AC10/F10 -> 0.00017668067 | AE10: 55 | AF10: =AE10/F10 -> 0.00023136755 | AH10: =AG10/F10 -> 0 | AJ10: =AI10/F10 -> 0 | AL10: =AK10/F10 -> 0 | AN10: =AM10/F10 -> 0 | AO10: 31 | AP10: =AO10/F10 -> 0.00013040716 | AQ10: 407 | AR10: =AQ10/F10 -> 0.0017121199 | AS10: 41 | AT10: =AS10/F10 -> 0.00017247399 | AU10: 345 | AV10: =AU10/F10 -> 0.0014513055 | AX10: =AW10/F10 -> 0 | AY10: =SUM(K10:AX10) -> 1649.0069 | AZ10: =AY10-I10 -> -112.99306
A11: ERIO KALIMATA ISPAT (Unit-1) Howrah West Bengal | B11: December 2025 | C11: PO-60250003104659 DTD. 09.10.2025 | D11: South Eastern | E11: SER | F11: 195702 | G11: 192449 | H11: =G11/F11 -> 0.98337779 | I11: 3253 | J11: =I11/F11 -> 0.016622211 | K11: 145 | L11: =K11/F11 -> 0.00074092242 | M11: 728 | N11: =M11/F11 -> 0.0037199415 | O11: 77 | P11: =O11/F11 -> 0.00039345536 | Q11: 25 | R11: =Q11/F11 -> 0.00012774525 | S11: 51 | T11: =S11/F11 -> 0.0002606003 | U11: 755 | V11: =U11/F11 -> 0.0038579064 | W11: 0 | X11: =W11/F11 -> 0 | Z11: =Y11/F11 -> 0 | AB11: =AA11/F11 -> 0 | AD11: =AC11/F11 -> 0 | AE11: 0 | AF11: =AE11/F11 -> 0 | AH11: =AG11/F11 -> 0 | AJ11: =AI11/F11 -> 0 | AL11: =AK11/F11 -> 0 | AN11: =AM11/F11 -> 0 | AP11: =AO11/F11 -> 0 | AQ11: 722 | AR11: =AQ11/F11 -> 0.0036892827 | AT11: =AS11/F11 -> 0 | AU11: =285+405 -> 690 | AV11: =AU11/F11 -> 0.0035257688 | AW11: 60 | AX11: =AW11/F11 -> 0.00030658859
A12: ERIO KALIMATA ISPAT (Unit-1) Howrah West Bengal | B12: Jan 2026 | C12: 60250003104659 & DTD. 09.10.2025 | D12: South Eastern | E12: SER | F12: 112197 | G12: 110809 | H12: =G12/F12 -> 0.9876289 | I12: 1388 | J12: =I12/F12 -> 0.012371097 | K12: 33 | L12: =K12/F12 -> 0.00029412551 | M12: 80 | N12: =M12/F12 -> 0.00071303154 | O12: 46 | P12: =O12/F12 -> 0.00040999314 | Q12: 0 | R12: =Q12/F12 -> 0 | S12: 49 | T12: =S12/F12 -> 0.00043673182 | U12: 235 | V12: =U12/F12 -> 0.0020945302 | W12: 0 | X12: =W12/F12 -> 0 | Z12: =Y12/F12 -> 0 | AB12: =AA12/F12 -> 0 | AD12: =AC12/F12 -> 0 | AF12: =AE12/F12 -> 0 | AH12: =AG12/F12 -> 0 | AJ12: =AI12/F12 -> 0 | AL12: =AK12/F12 -> 0 | AN12: =AM12/F12 -> 0 | AP12: =AO12/F12 -> 0 | AQ12: 582 | AR12: =AQ12/F12 -> 0.0051873045 | AT12: =AS12/F12 -> 0 | AU12: 246 | AV12: =AU12/F12 -> 0.002192572 | AW12: 117 | AX12: =AW12/F12 -> 0.0010428086 | AY12: =SUM(K12:AX12) -> 1388.0124 | AZ12: =AY12-I12 -> 0.012371097
A13: ERIO KALIMATA ISPAT (Unit-1) Howrah West Bengal | B13: Jan 2026 | C13: 6325559204678 & DTD. 29.10.2025 | D13: North Western | E13: NWR | F13: 9979 | G13: 9920 | H13: =G13/F13 -> 0.99408758 | I13: 59 | J13: =I13/F13 -> 0.0059124161 | K13: 0 | L13: =K13/F13 -> 0 | M13: 6 | N13: =M13/F13 -> 0.00060126265 | O13: 0 | P13: =O13/F13 -> 0 | Q13: 0 | R13: =Q13/F13 -> 0 | S13: 0 | T13: =S13/F13 -> 0 | U13: 0 | V13: =U13/F13 -> 0 | W13: 0 | X13: =W13/F13 -> 0 | Z13: =Y13/F13 -> 0 | AB13: =AA13/F13 -> 0 | AD13: =AC13/F13 -> 0 | AF13: =AE13/F13 -> 0 | AH13: =AG13/F13 -> 0 | AJ13: =AI13/F13 -> 0 | AL13: =AK13/F13 -> 0 | AN13: =AM13/F13 -> 0 | AP13: =AO13/F13 -> 0 | AQ13: 42 | AR13: =AQ13/F13 -> 0.0042088386 | AT13: =AS13/F13 -> 0 | AU13: 0 | AV13: =AU13/F13 -> 0 | AW13: 11 | AX13: =AW13/F13 -> 0.0011023149 | AY13: =SUM(K13:AX13) -> 59.005912 | AZ13: =AY13-I13 -> 0.0059124161
A14: ERIO KALIMATA ISPAT (Unit-1) Howrah West Bengal | B14: Jan 2026 | C14: 60256836107122 & DTD. 08.12.2025 | D14: South Central | E14: SCR | F14: 155104 | G14: 153656 | H14: =G14/F14 -> 0.99066433 | I14: 1448 | J14: =I14/F14 -> 0.0093356715 | K14: 0 | L14: =K14/F14 -> 0 | M14: 265 | N14: =M14/F14 -> 0.0017085311 | O14: 175 | P14: =O14/F14 -> 0.0011282752 | Q14: 25 | R14: =Q14/F14 -> 0.00016118217 | S14: 47 | T14: =S14/F14 -> 0.00030302249 | U14: 207 | V14: =U14/F14 -> 0.0013345884 | W14: 10 | X14: =W14/F14 -> 6.447287e-05 | Z14: =Y14/F14 -> 0 | AB14: =AA14/F14 -> 0 | AD14: =AC14/F14 -> 0 | AF14: =AE14/F14 -> 0 | AH14: =AG14/F14 -> 0 | AJ14: =AI14/F14 -> 0 | AL14: =AK14/F14 -> 0 | AN14: =AM14/F14 -> 0 | AP14: =AO14/F14 -> 0 | AQ14: 358 | AR14: =AQ14/F14 -> 0.0023081287 | AT14: =AS14/F14 -> 0 | AU14: 7 | AV14: =AU14/F14 -> 4.5131009e-05 | AW14: 354 | AX14: =AW14/F14 -> 0.0022823396 | AY14: =SUM(K14:AX14) -> 1448.0093 | AZ14: =AY14-I14 -> 0.0093356715
A15: ERIO KALIMATA ISPAT (Unit-II) Durgapur West Bengal | B15: December 2025 | C15: 26245012101170 dated 16.05.2025 | D15: North Eastern | E15: NER | F15: 34416 | G15: 34011 | H15: =G15/F15 -> 0.98823222 | I15: 405 | J15: =I15/F15 -> 0.011767782 | L15: =K15/F15 -> 0 | M15: 0 | N15: =M15/F15 -> 0 | O15: 30 | P15: =O15/F15 -> 0.00087168759 | R15: =Q15/F15 -> 0 | S15: 138 | T15: =S15/F15 -> 0.0040097629 | U15: 198 | V15: =U15/F15 -> 0.0057531381 | X15: =W15/F15 -> 0 | Z15: =Y15/F15 -> 0 | AB15: =AA15/F15 -> 0 | AD15: =AC15/F15 -> 0 | AE15: 7 | AF15: =AE15/F15 -> 0.00020339377 | AH15: =AG15/F15 -> 0 | AJ15: =AI15/F15 -> 0 | AL15: =AK15/F15 -> 0 | AN15: =AM15/F15 -> 0 | AO15: 0 | AP15: =AO15/F15 -> 0 | AQ15: 31 | AR15: =AQ15/F15 -> 0.00090074384 | AT15: =AS15/F15 -> 0 | AV15: =AU15/F15 -> 0 | AW15: 1 | AX15: =AW15/F15 -> 2.9056253e-05
A16: ERIO KALIMATA ISPAT (Unit-II) Durgapur West Bengal | B16: December 2025 | C16: 61255204105004 dated 16.09.2025 | D16: North East Frontier | E16: NFR | F16: 17655 | G16: 17531 | H16: =G16/F16 -> 0.99297649 | I16: 124 | J16: =I16/F16 -> 0.0070235061 | L16: =K16/F16 -> 0 | M16: 0 | N16: =M16/F16 -> 0 | O16: 2 | P16: =O16/F16 -> 0.00011328236 | R16: =Q16/F16 -> 0 | S16: 53 | T16: =S16/F16 -> 0.0030019824 | U16: 52 | V16: =U16/F16 -> 0.0029453413 | X16: =W16/F16 -> 0 | Z16: =Y16/F16 -> 0 | AB16: =AA16/F16 -> 0 | AD16: =AC16/F16 -> 0 | AE16: 3 | AF16: =AE16/F16 -> 0.00016992353 | AH16: =AG16/F16 -> 0 | AJ16: =AI16/F16 -> 0 | AL16: =AK16/F16 -> 0 | AN16: =AM16/F16 -> 0 | AO16: 0 | AP16: =AO16/F16 -> 0 | AQ16: 14 | AR16: =AQ16/F16 -> 0.00079297649 | AT16: =AS16/F16 -> 0 | AV16: =AU16/F16 -> 0 | AW16: 0 | AX16: =AW16/F16 -> 0
A17: ERIO KALIMATA ISPAT (Unit-II) Durgapur West Bengal | B17: December 2025 | C17: 63255579204678 dated 29.10.2025 | D17: North Western | E17: NWR | F17: 109205 | G17: 108418 | H17: =G17/F17 -> 0.99279337 | I17: 787 | J17: =I17/F17 -> 0.0072066297 | L17: =K17/F17 -> 0 | M17: 12 | N17: =M17/F17 -> 0.00010988508 | O17: 89 | P17: =O17/F17 -> 0.000814981 | R17: =Q17/F17 -> 0 | S17: 296 | T17: =S17/F17 -> 0.0027104986 | U17: 337 | V17: =U17/F17 -> 0.0030859393 | X17: =W17/F17 -> 0 | Z17: =Y17/F17 -> 0 | AB17: =AA17/F17 -> 0 | AD17: =AC17/F17 -> 0 | AE17: 1 | AF17: =AE17/F17 -> 9.1570899e-06 | AH17: =AG17/F17 -> 0 | AJ17: =AI17/F17 -> 0 | AL17: =AK17/F17 -> 0 | AN17: =AM17/F17 -> 0 | AO17: 0 | AP17: =AO17/F17 -> 0 | AQ17: 52 | AR17: =AQ17/F17 -> 0.00047616867 | AT17: =AS17/F17 -> 0 | AV17: =AU17/F17 -> 0 | AW17: 0 | AX17: =AW17/F17 -> 0
A18: ERIO KALIMATA ISPAT (Unit-II) Durgapur West Bengal | B18: December 2025 | C18: 6255178103406 dated 03.11.2025 | D18: East Coast | E18: ECOR | F18: 262479 | G18: 260243 | H18: =G18/F18 -> 0.99148122 | I18: 2236 | J18: =I18/F18 -> 0.0085187767 | L18: =K18/F18 -> 0 | M18: 32 | N18: =M18/F18 -> 0.00012191452 | O18: 279 | P18: =O18/F18 -> 0.0010629422 | R18: =Q18/F18 -> 0 | S18: 933 | T18: =S18/F18 -> 0.0035545701 | U18: 788 | V18: =U18/F18 -> 0.0030021449 | X18: =W18/F18 -> 0 | Z18: =Y18/F18 -> 0 | AB18: =AA18/F18 -> 0 | AD18: =AC18/F18 -> 0 | AE18: 11 | AF18: =AE18/F18 -> 4.1908115e-05 | AH18: =AG18/F18 -> 0 | AJ18: =AI18/F18 -> 0 | AL18: =AK18/F18 -> 0 | AN18: =AM18/F18 -> 0 | AO18: 3 | AP18: =AO18/F18 -> 1.1429486e-05 | AQ18: 161 | AR18: =AQ18/F18 -> 0.0006133824 | AT18: =AS18/F18 -> 0 | AV18: =AU18/F18 -> 0 | AW18: 29 | AX18: =AW18/F18 -> 0.00011048503
A19: ERIO KALIMATA ISPAT (Unit-II) Durgapur West Bengal | B19: Jan 2026 | C19: 26245012101170 & 16.05.2025 | D19: North Eastern | E19: NER | F19: 121363 | G19: 120592 | H19: =G19/F19 -> 0.99364716 | I19: 771 | J19: =I19/F19 -> 0.0063528423 | K19: 0 | L19: =K19/F19 -> 0 | M19: 28 | N19: =M19/F19 -> 0.00023071282 | O19: 94 | P19: =O19/F19 -> 0.0007745359 | R19: =Q19/F19 -> 0 | S19: 229 | T19: =S19/F19 -> 0.0018869013 | U19: 345 | V19: =U19/F19 -> 0.0028427115 | X19: =W19/F19 -> 0 | Z19: =Y19/F19 -> 0 | AB19: =AA19/F19 -> 0 | AC19: 0 | AD19: =AC19/F19 -> 0 | AE19: 0 | AF19: =AE19/F19 -> 0 | AH19: =AG19/F19 -> 0 | AJ19: =AI19/F19 -> 0 | AL19: =AK19/F19 -> 0 | AN19: =AM19/F19 -> 0 | AO19: 14 | AP19: =AO19/F19 -> 0.00011535641 | AQ19: 60 | AR19: =AQ19/F19 -> 0.00049438461 | AT19: =AS19/F19 -> 0 | AU19: 0 | AV19: =AU19/F19 -> 0 | AW19: 1 | AX19: =AW19/F19 -> 8.2397436e-06 | AY19: =SUM(K19:AX19) -> 771.00635 | AZ19: =AY19-I19 -> 0.0063528423
A20: ERIO KALIMATA ISPAT (Unit-II) Durgapur West Bengal | B20: Jan 2026 | C20: 63255579204678 & 29.10.2025 | D20: North Western | E20: NWR | F20: 79919 | G20: 79448 | H20: =G20/F20 -> 0.99410653 | I20: 471 | J20: =I20/F20 -> 0.0058934671 | K20: 1 | L20: =K20/F20 -> 1.2512669e-05 | M20: 15 | N20: =M20/F20 -> 0.00018769004 | O20: 55 | P20: =O20/F20 -> 0.0006881968 | R20: =Q20/F20 -> 0 | S20: 146 | T20: =S20/F20 -> 0.0018268497 | U20: 146 | V20: =U20/F20 -> 0.0018268497 | X20: =W20/F20 -> 0 | Z20: =Y20/F20 -> 0 | AB20: =AA20/F20 -> 0 | AC20: 1 | AD20: =AC20/F20 -> 1.2512669e-05 | AE20: 0 | AF20: =AE20/F20 -> 0 | AH20: =AG20/F20 -> 0 | AJ20: =AI20/F20 -> 0 | AL20: =AK20/F20 -> 0 | AN20: =AM20/F20 -> 0 | AO20: 8 | AP20: =AO20/F20 -> 0.00010010135 | AQ20: 99 | AR20: =AQ20/F20 -> 0.0012387542 | AT20: =AS20/F20 -> 0 | AU20: 0 | AV20: =AU20/F20 -> 0 | AW20: 0 | AX20: =AW20/F20 -> 0 | AY20: =SUM(K20:AX20) -> 471.00589 | AZ20: =AY20-I20 -> 0.0058934671
A21: ERIO KALIMATA ISPAT (Unit-II) Durgapur West Bengal | B21: Jan 2026 | C21: 03255541205744 & 22.11.2025 | D21: Southern | E21: SR | F21: 186716 | G21: 185510 | H21: =G21/F21 -> 0.99354099 | I21: 1206 | J21: =I21/F21 -> 0.0064590073 | K21: 0 | L21: =K21/F21 -> 0 | M21: 42 | N21: =M21/F21 -> 0.00022494055 | O21: 168 | P21: =O21/F21 -> 0.00089976221 | R21: =Q21/F21 -> 0 | S21: 323 | T21: =S21/F21 -> 0.0017299 | U21: 498 | V21: =U21/F21 -> 0.0026671523 | X21: =W21/F21 -> 0 | Z21: =Y21/F21 -> 0 | AB21: =AA21/F21 -> 0 | AC21: 0 | AD21: =AC21/F21 -> 0 | AE21: 0 | AF21: =AE21/F21 -> 0 | AH21: =AG21/F21 -> 0 | AJ21: =AI21/F21 -> 0 | AL21: =AK21/F21 -> 0 | AN21: =AM21/F21 -> 0 | AO21: 7 | AP21: =AO21/F21 -> 3.7490092e-05 | AQ21: 150 | AR21: =AQ21/F21 -> 0.00080335911 | AT21: =AS21/F21 -> 0 | AU21: 12 | AV21: =AU21/F21 -> 6.4268729e-05 | AW21: 6 | AX21: =AW21/F21 -> 3.2134364e-05 | AY21: =SUM(K21:AX21) -> 1206.0065 | AZ21: =AY21-I21 -> 0.0064590073
A22: ERIO KALIMATA ISPAT (Unit-II) Durgapur West Bengal | B22: Jan 2026 | C22: 60256836107122 & 08.12.2025 | D22: South Central | E22: SCR | F22: 65523 | G22: 65211 | H22: =G22/F22 -> 0.99523831 | I22: 312 | J22: =I22/F22 -> 0.0047616867 | K22: 2 | L22: =K22/F22 -> 3.0523633e-05 | M22: 97 | N22: =M22/F22 -> 0.0014803962 | O22: 69 | P22: =O22/F22 -> 0.0010530653 | R22: =Q22/F22 -> 0 | S22: 0 | T22: =S22/F22 -> 0 | U22: 0 | V22: =U22/F22 -> 0 | X22: =W22/F22 -> 0 | Z22: =Y22/F22 -> 0 | AB22: =AA22/F22 -> 0 | AC22: 0 | AD22: =AC22/F22 -> 0 | AE22: 2 | AF22: =AE22/F22 -> 3.0523633e-05 | AH22: =AG22/F22 -> 0 | AJ22: =AI22/F22 -> 0 | AL22: =AK22/F22 -> 0 | AN22: =AM22/F22 -> 0 | AO22: 14 | AP22: =AO22/F22 -> 0.00021366543 | AQ22: 111 | AR22: =AQ22/F22 -> 0.0016940616 | AT22: =AS22/F22 -> 0 | AU22: 2 | AV22: =AU22/F22 -> 3.0523633e-05 | AW22: 15 | AX22: =AW22/F22 -> 0.00022892725 | AY22: =SUM(K22:AX22) -> 312.00476 | AZ22: =AY22-I22 -> 0.0047616867
A23: ERIO KALIMATA VYAPAAR (Unit-II) Durgapur West Bengal | B23: December 2025 | C23: 60257500205477 dated 10.09.2025 | D23: South Central | E23: SCR | F23: 43707 | G23: 43179 | H23: =G23/F23 -> 0.98791956 | I23: 528 | J23: =I23/F23 -> 0.012080445 | L23: =K23/F23 -> 0 | M23: 6 | N23: =M23/F23 -> 0.00013727778 | O23: 124 | P23: =O23/F23 -> 0.0028370742 | R23: =Q23/F23 -> 0 | S23: 150 | T23: =S23/F23 -> 0.0034319445 | U23: 166 | V23: =U23/F23 -> 0.0037980186 | X23: =W23/F23 -> 0 | Z23: =Y23/F23 -> 0 | AB23: =AA23/F23 -> 0 | AD23: =AC23/F23 -> 0 | AE23: 0 | AF23: =AE23/F23 -> 0 | AH23: =AG23/F23 -> 0 | AJ23: =AI23/F23 -> 0 | AL23: =AK23/F23 -> 0 | AN23: =AM23/F23 -> 0 | AP23: =AO23/F23 -> 0 | AQ23: 82 | AR23: =AQ23/F23 -> 0.0018761297 | AS23: 0 | AT23: =AS23/F23 -> 0 | AV23: =AU23/F23 -> 0 | AW23: 0 | AX23: =AW23/F23 -> 0
A24: ERIO KALIMATA VYAPAAR (Unit-II) Durgapur West Bengal | B24: December 2025 | C24: 03255362204668 dated 12.09.2025 | D24: Southern | E24: SR | F24: 178635 | G24: 176175 | H24: =G24/F24 -> 0.9862289 | I24: 2460 | J24: =I24/F24 -> 0.013771097 | L24: =K24/F24 -> 0 | M24: 1 | N24: =M24/F24 -> 5.5980071e-06 | O24: 159 | P24: =O24/F24 -> 0.00089008313 | R24: =Q24/F24 -> 0 | S24: 927 | T24: =S24/F24 -> 0.0051893526 | U24: 832 | V24: =U24/F24 -> 0.0046575419 | X24: =W24/F24 -> 0 | Z24: =Y24/F24 -> 0 | AB24: =AA24/F24 -> 0 | AD24: =AC24/F24 -> 0 | AE24: 21 | AF24: =AE24/F24 -> 0.00011755815 | AH24: =AG24/F24 -> 0 | AJ24: =AI24/F24 -> 0 | AL24: =AK24/F24 -> 0 | AN24: =AM24/F24 -> 0 | AP24: =AO24/F24 -> 0 | AQ24: 516 | AR24: =AQ24/F24 -> 0.0028885717 | AS24: 0 | AT24: =AS24/F24 -> 0 | AV24: =AU24/F24 -> 0 | AW24: 4 | AX24: =AW24/F24 -> 2.2392028e-05
A25: ERIO KALIMATA VYAPAAR (Unit-II) Durgapur West Bengal | B25: December 2025 | C25: 60250003104658 dated 09.10.2025 | D25: South Eastern | E25: SER | F25: 195626 | G25: 192833 | H25: =G25/F25 -> 0.98572276 | I25: 2793 | J25: =I25/F25 -> 0.014277243 | L25: =K25/F25 -> 0 | M25: 203 | N25: =M25/F25 -> 0.0010376944 | O25: 394 | P25: =O25/F25 -> 0.0020140472 | R25: =Q25/F25 -> 0 | S25: 883 | T25: =S25/F25 -> 0.0045137149 | U25: 812 | V25: =U25/F25 -> 0.0041507775 | X25: =W25/F25 -> 0 | Z25: =Y25/F25 -> 0 | AB25: =AA25/F25 -> 0 | AD25: =AC25/F25 -> 0 | AE25: 23 | AF25: =AE25/F25 -> 0.00011757128 | AH25: =AG25/F25 -> 0 | AJ25: =AI25/F25 -> 0 | AL25: =AK25/F25 -> 0 | AN25: =AM25/F25 -> 0 | AP25: =AO25/F25 -> 0 | AQ25: 474 | AR25: =AQ25/F25 -> 0.0024229908 | AS25: 0 | AT25: =AS25/F25 -> 0 | AV25: =AU25/F25 -> 0 | AW25: 4 | AX25: =AW25/F25 -> 2.044718e-05
A26: ERIO KALIMATA VYAPAAR (Unit-II) Durgapur West Bengal | B26: December 2025 | C26: 63255579204677 dated 29.10.2025 | D26: North Western | E26: NWR | F26: 16555 | G26: 16299 | H26: =G26/F26 -> 0.98453639 | I26: 256 | J26: =I26/F26 -> 0.015463606 | L26: =K26/F26 -> 0 | M26: 0 | N26: =M26/F26 -> 0 | O26: 70 | P26: =O26/F26 -> 0.0042283298 | R26: =Q26/F26 -> 0 | S26: 70 | T26: =S26/F26 -> 0.0042283298 | U26: 67 | V26: =U26/F26 -> 0.0040471157 | X26: =W26/F26 -> 0 | Z26: =Y26/F26 -> 0 | AB26: =AA26/F26 -> 0 | AD26: =AC26/F26 -> 0 | AE26: 0 | AF26: =AE26/F26 -> 0 | AH26: =AG26/F26 -> 0 | AJ26: =AI26/F26 -> 0 | AL26: =AK26/F26 -> 0 | AN26: =AM26/F26 -> 0 | AP26: =AO26/F26 -> 0 | AQ26: 48 | AR26: =AQ26/F26 -> 0.0028994262 | AS26: 0 | AT26: =AS26/F26 -> 0 | AV26: =AU26/F26 -> 0 | AW26: 1 | AX26: =AW26/F26 -> 6.0404712e-05
A27: ERIO KALIMATA VYAPAAR (Unit-II) Durgapur West Bengal | B27: December 2025 | C27: 06255399103608 dated 21.11.2025 | D27: East Coast | E27: ECOR | F27: 67325 | G27: 66662 | H27: =G27/F27 -> 0.99015225 | I27: 663 | J27: =I27/F27 -> 0.0098477534 | L27: =K27/F27 -> 0 | M27: 134 | N27: =M27/F27 -> 0.0019903453 | O27: 186 | P27: =O27/F27 -> 0.0027627182 | R27: =Q27/F27 -> 0 | S27: 0 | T27: =S27/F27 -> 0 | U27: 0 | V27: =U27/F27 -> 0 | X27: =W27/F27 -> 0 | Z27: =Y27/F27 -> 0 | AB27: =AA27/F27 -> 0 | AD27: =AC27/F27 -> 0 | AE27: 5 | AF27: =AE27/F27 -> 7.4266617e-05 | AH27: =AG27/F27 -> 0 | AJ27: =AI27/F27 -> 0 | AL27: =AK27/F27 -> 0 | AN27: =AM27/F27 -> 0 | AP27: =AO27/F27 -> 0 | AQ27: 227 | AR27: =AQ27/F27 -> 0.0033717044 | AS27: 55 | AT27: =AS27/F27 -> 0.00081693279 | AV27: =AU27/F27 -> 0 | AW27: 56 | AX27: =AW27/F27 -> 0.00083178611
A28: ERIO KALIMATA VYAPAAR (Unit-II) Durgapur West Bengal | B28: Jan 2026 | C28: 63255579204677 & 29.10.2025 | D28: North Western | E28: NWR | F28: 404458 | G28: 397681 | H28: =G28/F28 -> 0.98324424 | I28: 6777 | J28: =I28/F28 -> 0.016755757 | L28: =K28/F28 -> 0 | M28: 107 | N28: =M28/F28 -> 0.00026455157 | O28: 1599 | P28: =O28/F28 -> 0.0039534389 | R28: =Q28/F28 -> 0 | S28: 1581 | T28: =S28/F28 -> 0.0039089349 | U28: 1638 | V28: =U28/F28 -> 0.0040498643 | X28: =W28/F28 -> 0 | Z28: =Y28/F28 -> 0 | AB28: =AA28/F28 -> 0 | AD28: =AC28/F28 -> 0 | AE28: 12 | AF28: =AE28/F28 -> 2.9669335e-05 | AH28: =AG28/F28 -> 0 | AJ28: =AI28/F28 -> 0 | AL28: =AK28/F28 -> 0 | AN28: =AM28/F28 -> 0 | AP28: =AO28/F28 -> 0 | AQ28: 1069 | AR28: =AQ28/F28 -> 0.0026430433 | AT28: =AS28/F28 -> 0 | AV28: =AU28/F28 -> 0 | AW28: 771 | AX28: =AW28/F28 -> 0.0019062548 | AY28: =SUM(K28:AX28) -> 6777.0168 | AZ28: =AY28-I28 -> 0.016755757
A29: ERIO KALIMATA VYAPAAR (Unit-II) Durgapur West Bengal | B29: Jan 2026 | C29: 06255399103608 & 21.11.2025 | D29: East Coast | E29: ECOR | F29: 284 | G29: 264 | H29: =G29/F29 -> 0.92957746 | I29: 20 | J29: =I29/F29 -> 0.070422535 | L29: =K29/F29 -> 0 | M29: 0 | N29: =M29/F29 -> 0 | O29: 14 | P29: =O29/F29 -> 0.049295775 | R29: =Q29/F29 -> 0 | S29: 0 | T29: =S29/F29 -> 0 | U29: 0 | V29: =U29/F29 -> 0 | X29: =W29/F29 -> 0 | Z29: =Y29/F29 -> 0 | AB29: =AA29/F29 -> 0 | AD29: =AC29/F29 -> 0 | AE29: 0 | AF29: =AE29/F29 -> 0 | AH29: =AG29/F29 -> 0 | AJ29: =AI29/F29 -> 0 | AL29: =AK29/F29 -> 0 | AN29: =AM29/F29 -> 0 | AP29: =AO29/F29 -> 0 | AQ29: 6 | AR29: =AQ29/F29 -> 0.021126761 | AT29: =AS29/F29 -> 0 | AV29: =AU29/F29 -> 0 | AW29: 0 | AX29: =AW29/F29 -> 0 | AY29: =SUM(K29:AX29) -> 20.070423 | AZ29: =AY29-I29 -> 0.070422535
A30: ERIO KALIMATA VYAPAAR (Unit-II) Durgapur West Bengal | B30: Jan 2026 | C30: 03255541205771 & 24.11.2025 | D30: Southern | E30: SR | F30: 121602 | G30: 119728 | H30: =G30/F30 -> 0.98458907 | I30: 1874 | J30: =I30/F30 -> 0.015410931 | L30: =K30/F30 -> 0 | M30: 5 | N30: =M30/F30 -> 4.1117745e-05 | O30: 488 | P30: =O30/F30 -> 0.0040130919 | R30: =Q30/F30 -> 0 | S30: 514 | T30: =S30/F30 -> 0.0042269042 | U30: 564 | V30: =U30/F30 -> 0.0046380816 | X30: =W30/F30 -> 0 | Z30: =Y30/F30 -> 0 | AB30: =AA30/F30 -> 0 | AD30: =AC30/F30 -> 0 | AE30: 0 | AF30: =AE30/F30 -> 0 | AH30: =AG30/F30 -> 0 | AJ30: =AI30/F30 -> 0 | AL30: =AK30/F30 -> 0 | AN30: =AM30/F30 -> 0 | AP30: =AO30/F30 -> 0 | AQ30: 287 | AR30: =AQ30/F30 -> 0.0023601586 | AT30: =AS30/F30 -> 0 | AV30: =AU30/F30 -> 0 | AW30: 16 | AX30: =AW30/F30 -> 0.00013157678 | AY30: =SUM(K30:AX30) -> 1874.0154 | AZ30: =AY30-I30 -> 0.015410931
A31: ERIO KDS ENGG. PVT. LTD. Howrah West Bengal | B31: December 2025 | C31: NO PRODUCTION | F31: 0 | G31: 0 | H31: =G31/F31 -> #DIV/0! | I31: 0 | J31: =I31/F31 -> #DIV/0! | L31: =K31/F31 -> #DIV/0! | N31: =M31/F31 -> #DIV/0! | P31: =O31/F31 -> #DIV/0! | R31: =Q31/F31 -> #DIV/0! | T31: =S31/F31 -> #DIV/0! | V31: =U31/F31 -> #DIV/0! | X31: =W31/F31 -> #DIV/0! | Z31: =Y31/F31 -> #DIV/0! | AB31: =AA31/F31 -> #DIV/0! | AD31: =AC31/F31 -> #DIV/0! | AF31: =AE31/F31 -> #DIV/0! | AH31: =AG31/F31 -> #DIV/0! | AJ31: =AI31/F31 -> #DIV/0! | AL31: =AK31/F31 -> #DIV/0! | AN31: =AM31/F31 -> #DIV/0! | AP31: =AO31/F31 -> #DIV/0! | AR31: =AQ31/F31 -> #DIV/0! | AT31: =AS31/F31 -> #DIV/0! | AV31: =AU31/F31 -> #DIV/0! | AX31: =AW31/F31 -> #DIV/0!
A32: ERIO KDS ENGG. PVT. LTD. Howrah West Bengal | B32: Jan 2026 | C32: 26255279200322 DT-13.01.2026 | D32: Western | E32: WR | F32: 39589 | G32: 39266 | H32: =G32/F32 -> 0.99184117 | I32: 323 | J32: =I32/F32 -> 0.008158832 | L32: =K32/F32 -> 0 | M32: 125 | N32: =M32/F32 -> 0.0031574427 | P32: =O32/F32 -> 0 | R32: =Q32/F32 -> 0 | S32: 41 | T32: =S32/F32 -> 0.0010356412 | U32: 71 | V32: =U32/F32 -> 0.0017934275 | W32: 10 | X32: =W32/F32 -> 0.00025259542 | Z32: =Y32/F32 -> 0 | AB32: =AA32/F32 -> 0 | AC32: 4 | AD32: =AC32/F32 -> 0.00010103817 | AF32: =AE32/F32 -> 0 | AH32: =AG32/F32 -> 0 | AJ32: =AI32/F32 -> 0 | AL32: =AK32/F32 -> 0 | AN32: =AM32/F32 -> 0 | AP32: =AO32/F32 -> 0 | AQ32: 46 | AR32: =AQ32/F32 -> 0.0011619389 | AS32: 20 | AT32: =AS32/F32 -> 0.00050519084 | AU32: 6 | AV32: =AU32/F32 -> 0.00015155725 | AX32: =AW32/F32 -> 0 | AY32: =SUM(K32:AX32) -> 323.00816 | AZ32: =AY32-I32 -> 0.008158832
A33: ERIO KRISHNA INFRATECH Jharsuguda Odisha | B33: December 2025 | C33: 77255086207682 DT 15.10.2025 | D33: Northern | E33: NR | F33: =G33+I33 -> 50926 | G33: 50410 | H33: =G33/F33 -> 0.98986765 | I33: 516 | J33: =I33/F33 -> 0.010132349 | L33: =K33/F33 -> 0 | M33: 246 | N33: =M33/F33 -> 0.0048305384 | O33: 103 | P33: =O33/F33 -> 0.0020225425 | R33: =Q33/F33 -> 0 | T33: =S33/F33 -> 0 | U33: 105 | V33: =U33/F33 -> 0.0020618152 | X33: =W33/F33 -> 0 | Z33: =Y33/F33 -> 0 | AB33: =AA33/F33 -> 0 | AD33: =AC33/F33 -> 0 | AF33: =AE33/F33 -> 0 | AH33: =AG33/F33 -> 0 | AJ33: =AI33/F33 -> 0 | AL33: =AK33/F33 -> 0 | AN33: =AM33/F33 -> 0 | AO33: 12 | AP33: =AO33/F33 -> 0.00023563602 | AQ33: 50 | AR33: =AQ33/F33 -> 0.00098181675 | AT33: =AS33/F33 -> 0 | AV33: =AU33/F33 -> 0 | AX33: =AW33/F33 -> 0
A34: ERIO KRISHNA INFRATECH Jharsuguda Odisha | B34: December 2025 | C34: 77255086207682 DT 15.10.2026 | D34: Northern | E34: NR | F34: =G34+I34 -> 8267 | G34: 8190 | H34: =G34/F34 -> 0.99068586 | I34: 77 | J34: =I34/F34 -> 0.0093141406 | L34: =K34/F34 -> 0 | M34: 43 | N34: =M34/F34 -> 0.0052014032 | O34: 22 | P34: =O34/F34 -> 0.002661183 | R34: =Q34/F34 -> 0 | T34: =S34/F34 -> 0 | U34: 0 | V34: =U34/F34 -> 0 | X34: =W34/F34 -> 0 | Z34: =Y34/F34 -> 0 | AB34: =AA34/F34 -> 0 | AD34: =AC34/F34 -> 0 | AF34: =AE34/F34 -> 0 | AH34: =AG34/F34 -> 0 | AJ34: =AI34/F34 -> 0 | AL34: =AK34/F34 -> 0 | AN34: =AM34/F34 -> 0 | AO34: 5 | AP34: =AO34/F34 -> 0.00060481432 | AQ34: 7 | AR34: =AQ34/F34 -> 0.00084674005 | AT34: =AS34/F34 -> 0 | AV34: =AU34/F34 -> 0 | AX34: =AW34/F34 -> 0
A35: ERIO KRISHNA INFRATECH Jharsuguda Odisha | B35: December 2025 | C35: 06255178103407 DT 03.11.2025 | D35: East Coast | E35: ECoR | F35: =G35+I35 -> 169531 | G35: 167810 | H35: =G35/F35 -> 0.98984846 | I35: 1721 | J35: =I35/F35 -> 0.010151536 | L35: =K35/F35 -> 0 | M35: 792 | N35: =M35/F35 -> 0.004671712 | O35: 341 | P35: =O35/F35 -> 0.0020114315 | R35: =Q35/F35 -> 0 | T35: =S35/F35 -> 0 | U35: 326 | V35: =U35/F35 -> 0.0019229521 | X35: =W35/F35 -> 0 | Z35: =Y35/F35 -> 0 | AB35: =AA35/F35 -> 0 | AD35: =AC35/F35 -> 0 | AF35: =AE35/F35 -> 0 | AH35: =AG35/F35 -> 0 | AJ35: =AI35/F35 -> 0 | AL35: =AK35/F35 -> 0 | AN35: =AM35/F35 -> 0 | AO35: 41 | AP35: =AO35/F35 -> 0.00024184367 | AQ35: 179 | AR35: =AQ35/F35 -> 0.0010558541 | AT35: =AS35/F35 -> 0 | AV35: =AU35/F35 -> 0 | AX35: =AW35/F35 -> 0
A36: ERIO KRISHNA INFRATECH Jharsuguda Odisha | B36: Jan 2026 | C36: 06255178103407 DT 03.11.2025 | D36: East Coast | E36: ECoR | F36: 131959 | G36: 130800 | H36: =G36/F36 -> 0.99121697 | I36: 1159 | J36: =I36/F36 -> 0.0087830311 | L36: =K36/F36 -> 0 | M36: 452 | N36: =M36/F36 -> 0.0034253063 | O36: 389 | P36: =O36/F36 -> 0.0029478853 | R36: =Q36/F36 -> 0 | T36: =S36/F36 -> 0 | U36: 146 | V36: =U36/F36 -> 0.0011064043 | X36: =W36/F36 -> 0 | Z36: =Y36/F36 -> 0 | AB36: =AA36/F36 -> 0 | AD36: =AC36/F36 -> 0 | AF36: =AE36/F36 -> 0 | AH36: =AG36/F36 -> 0 | AJ36: =AI36/F36 -> 0 | AL36: =AK36/F36 -> 0 | AN36: =AM36/F36 -> 0 | AO36: 21 | AP36: =AO36/F36 -> 0.00015914034 | AQ36: 151 | AR36: =AQ36/F36 -> 0.0011442948 | AT36: =AS36/F36 -> 0 | AV36: =AU36/F36 -> 0 | AX36: =AW36/F36 -> 0 | AY36: =SUM(K36:AX36) -> 1159.0088 | AZ36: =AY36-I36 -> 0.0087830311
A37: ERIO KSE ELECTRICALS PVT LTD Howrah West Bengal | B37: December 2025 | C37: 77235519205935 DT 29- JULY-2024 | D37: Northern | E37: NR | F37: =G37+I37 -> 118730 | G37: 117600 | H37: =G37/F37 -> 0.99048261 | I37: 1130 | J37: =I37/F37 -> 0.0095173924 | K37: 78 | L37: =K37/F37 -> 0.00065695275 | M37: 118 | N37: =M37/F37 -> 0.0009938516 | O37: 0 | P37: =O37/F37 -> 0 | R37: =Q37/F37 -> 0 | S37: 167 | T37: =S37/F37 -> 0.0014065527 | U37: 287 | V37: =U37/F37 -> 0.0024172492 | W37: 40 | X37: =W37/F37 -> 0.00033689885 | Z37: =Y37/F37 -> 0 | AB37: =AA37/F37 -> 0 | AC37: 68 | AD37: =AC37/F37 -> 0.00057272804 | AF37: =AE37/F37 -> 0 | AH37: =AG37/F37 -> 0 | AJ37: =AI37/F37 -> 0 | AL37: =AK37/F37 -> 0 | AN37: =AM37/F37 -> 0 | AO37: 3 | AP37: =AO37/F37 -> 2.5267413e-05 | AQ37: 116 | AR37: =AQ37/F37 -> 0.00097700665 | AS37: 110 | AT37: =AS37/F37 -> 0.00092647183 | AU37: 143 | AV37: =AU37/F37 -> 0.0012044134 | AX37: =AW37/F37 -> 0
A38: ERIO KSE ELECTRICALS PVT LTD Howrah West Bengal | B38: December 2025 | C38: 63255372202186 DT 10- JUN-2025 | D38: North Western | E38: NWR | F38: =G38+I38 -> 110579 | G38: 109480 | H38: =G38/F38 -> 0.9900614 | I38: 1099 | J38: =I38/F38 -> 0.0099385959 | K38: 39 | L38: =K38/F38 -> 0.00035268903 | M38: 157 | N38: =M38/F38 -> 0.0014197994 | O38: 0 | P38: =O38/F38 -> 0 | R38: =Q38/F38 -> 0 | S38: 144 | T38: =S38/F38 -> 0.0013022364 | U38: 334 | V38: =U38/F38 -> 0.003020465 | W38: 62 | X38: =W38/F38 -> 0.00056068512 | Z38: =Y38/F38 -> 0 | AB38: =AA38/F38 -> 0 | AC38: 83 | AD38: =AC38/F38 -> 0.0007505946 | AF38: =AE38/F38 -> 0 | AH38: =AG38/F38 -> 0 | AJ38: =AI38/F38 -> 0 | AL38: =AK38/F38 -> 0 | AN38: =AM38/F38 -> 0 | AO38: 0 | AP38: =AO38/F38 -> 0 | AQ38: 98 | AR38: =AQ38/F38 -> 0.00088624422 | AS38: 31 | AT38: =AS38/F38 -> 0.00028034256 | AU38: 151 | AV38: =AU38/F38 -> 0.0013655396 | AX38: =AW38/F38 -> 0
A39: ERIO KSE ELECTRICALS PVT LTD Howrah West Bengal | B39: December 2025 | C39: 01245150200865 DT 27- JUN-2025 | D39: North East Frontier | E39: NFR | F39: =G39+I39 -> 206706 | G39: 204700 | H39: =G39/F39 -> 0.9902954 | I39: 2006 | J39: =I39/F39 -> 0.0097046046 | K39: 169 | L39: =K39/F39 -> 0.00081758633 | M39: 200 | N39: =M39/F39 -> 0.00096755779 | O39: 0 | P39: =O39/F39 -> 0 | R39: =Q39/F39 -> 0 | S39: 205 | T39: =S39/F39 -> 0.00099174673 | U39: 505 | V39: =U39/F39 -> 0.0024430834 | W39: 197 | X39: =W39/F39 -> 0.00095304442 | Z39: =Y39/F39 -> 0 | AB39: =AA39/F39 -> 0 | AC39: 148 | AD39: =AC39/F39 -> 0.00071599276 | AF39: =AE39/F39 -> 0 | AH39: =AG39/F39 -> 0 | AJ39: =AI39/F39 -> 0 | AL39: =AK39/F39 -> 0 | AN39: =AM39/F39 -> 0 | AO39: 0 | AP39: =AO39/F39 -> 0 | AQ39: 168 | AR39: =AQ39/F39 -> 0.00081274854 | AS39: 144 | AT39: =AS39/F39 -> 0.00069664161 | AU39: 270 | AV39: =AU39/F39 -> 0.001306203 | AX39: =AW39/F39 -> 0
A40: ERIO KSE ELECTRICALS PVT LTD Howrah West Bengal | B40: December 2025 | C40: 81255001102836 DT 21- JULY-2025 | D40: West Central | E40: WCR | F40: =G40+I40 -> 115270 | G40: 114400 | H40: =G40/F40 -> 0.9924525 | I40: 870 | J40: =I40/F40 -> 0.0075474972 | K40: 39 | L40: =K40/F40 -> 0.00033833608 | M40: 133 | N40: =M40/F40 -> 0.0011538128 | O40: 0 | P40: =O40/F40 -> 0 | R40: =Q40/F40 -> 0 | S40: 114 | T40: =S40/F40 -> 0.00098898239 | U40: 260 | V40: =U40/F40 -> 0.0022555739 | W40: 14 | X40: =W40/F40 -> 0.00012145398 | Z40: =Y40/F40 -> 0 | AB40: =AA40/F40 -> 0 | AC40: 36 | AD40: =AC40/F40 -> 0.00031231023 | AF40: =AE40/F40 -> 0 | AH40: =AG40/F40 -> 0 | AJ40: =AI40/F40 -> 0 | AL40: =AK40/F40 -> 0 | AN40: =AM40/F40 -> 0 | AO40: 0 | AP40: =AO40/F40 -> 0 | AQ40: 115 | AR40: =AQ40/F40 -> 0.00099765767 | AS40: 28 | AT40: =AS40/F40 -> 0.00024290796 | AU40: 131 | AV40: =AU40/F40 -> 0.0011364622 | AX40: =AW40/F40 -> 0
A41: ERIO KSE ELECTRICALS PVT LTD Howrah West Bengal | B41: December 2025 | C41: 60257500205472 DT 10-SEP-2025 | D41: Southern | E41: SR | F41: =G41+I41 -> 90211 | G41: 89450 | H41: =G41/F41 -> 0.99156422 | I41: 761 | J41: =I41/F41 -> 0.0084357783 | K41: 52 | L41: =K41/F41 -> 0.00057642638 | M41: 63 | N41: =M41/F41 -> 0.00069836273 | O41: 5 | P41: =O41/F41 -> 5.5425613e-05 | R41: =Q41/F41 -> 0 | S41: 102 | T41: =S41/F41 -> 0.0011306825 | U41: 180 | V41: =U41/F41 -> 0.0019953221 | W41: 66 | X41: =W41/F41 -> 0.0007316181 | Z41: =Y41/F41 -> 0 | AB41: =AA41/F41 -> 0 | AC41: 39 | AD41: =AC41/F41 -> 0.00043231978 | AF41: =AE41/F41 -> 0 | AH41: =AG41/F41 -> 0 | AJ41: =AI41/F41 -> 0 | AL41: =AK41/F41 -> 0 | AN41: =AM41/F41 -> 0 | AO41: 8 | AP41: =AO41/F41 -> 8.8680981e-05 | AQ41: 71 | AR41: =AQ41/F41 -> 0.00078704371 | AS41: 80 | AT41: =AS41/F41 -> 0.00088680981 | AU41: 95 | AV41: =AU41/F41 -> 0.0010530867 | AX41: =AW41/F41 -> 0
A42: ERIO KSE ELECTRICALS PVT LTD Howrah West Bengal | B42: Jan 2026 | C42: 3255403204450 DT 29-AUG-2025 | D42: Southern | E42: SR | F42: 61129 | G42: 60219 | H42: =G42/F42 -> 0.98511345 | I42: 910 | J42: =I42/F42 -> 0.014886551 | K42: 0 | L42: =K42/F42 -> 0 | M42: 291 | N42: =M42/F42 -> 0.0047604247 | O42: 28 | P42: =O42/F42 -> 0.00045804774 | R42: =Q42/F42 -> 0 | S42: 0 | T42: =S42/F42 -> 0 | U42: 0 | V42: =U42/F42 -> 0 | W42: 123 | X42: =W42/F42 -> 0.0020121383 | Z42: =Y42/F42 -> 0 | AB42: =AA42/F42 -> 0 | AC42: 120 | AD42: =AC42/F42 -> 0.0019630617 | AF42: =AE42/F42 -> 0 | AH42: =AG42/F42 -> 0 | AJ42: =AI42/F42 -> 0 | AL42: =AK42/F42 -> 0 | AN42: =AM42/F42 -> 0 | AO42: 0 | AP42: =AO42/F42 -> 0 | AQ42: 242 | AR42: =AQ42/F42 -> 0.0039588411 | AS42: 34 | AT42: =AS42/F42 -> 0.00055620082 | AU42: 69 | AV42: =AU42/F42 -> 0.0011287605 | AW42: 3 | AX42: =AW42/F42 -> 4.9076543e-05 | AY42: =SUM(K42:AX42) -> 910.01489 | AZ42: =AY42-I42 -> 0.014886551
A43: ERIO KSE ELECTRICALS PVT LTD Howrah West Bengal | B43: Jan 2026 | C43: 03255362204669 DT 12-SEP-2025 | D43: Southern | E43: SR | F43: 231905 | G43: 229770 | H43: =G43/F43 -> 0.99079364 | I43: 2135 | J43: =I43/F43 -> 0.0092063561 | K43: 0 | L43: =K43/F43 -> 0 | M43: 290 | N43: =M43/F43 -> 0.0012505121 | O43: 12 | P43: =O43/F43 -> 5.1745327e-05 | R43: =Q43/F43 -> 0 | S43: 328 | T43: =S43/F43 -> 0.0014143723 | U43: 461 | V43: =U43/F43 -> 0.001987883 | W43: 241 | X43: =W43/F43 -> 0.0010392186 | Z43: =Y43/F43 -> 0 | AB43: =AA43/F43 -> 0 | AC43: 125 | AD43: =AC43/F43 -> 0.00053901382 | AF43: =AE43/F43 -> 0 | AH43: =AG43/F43 -> 0 | AJ43: =AI43/F43 -> 0 | AL43: =AK43/F43 -> 0 | AN43: =AM43/F43 -> 0 | AO43: 2 | AP43: =AO43/F43 -> 8.6242211e-06 | AQ43: 412 | AR43: =AQ43/F43 -> 0.0017765896 | AS43: 42 | AT43: =AS43/F43 -> 0.00018110864 | AU43: 222 | AV43: =AU43/F43 -> 0.00095728854 | AW43: 0 | AX43: =AW43/F43 -> 0 | AY43: =SUM(K43:AX43) -> 2135.0092 | AZ43: =AY43-I43 -> 0.0092063561
A44: ERIO KSE ELECTRICALS PVT LTD Howrah West Bengal | B44: Jan 2026 | C44: 61255131105050 DT 19-SEP-2025 | D44: North East Frontier | E44: NFR | F44: 267529 | G44: 265032 | H44: =G44/F44 -> 0.99066643 | I44: 2497 | J44: =I44/F44 -> 0.0093335676 | K44: 55 | L44: =K44/F44 -> 0.00020558519 | M44: 227 | N44: =M44/F44 -> 0.00084850614 | O44: 0 | P44: =O44/F44 -> 0 | R44: =Q44/F44 -> 0 | S44: 395 | T44: =S44/F44 -> 0.0014764754 | U44: 585 | V44: =U44/F44 -> 0.0021866788 | W44: 197 | X44: =W44/F44 -> 0.00073636877 | Z44: =Y44/F44 -> 0 | AB44: =AA44/F44 -> 0 | AC44: 136 | AD44: =AC44/F44 -> 0.0005083561 | AF44: =AE44/F44 -> 0 | AH44: =AG44/F44 -> 0 | AJ44: =AI44/F44 -> 0 | AL44: =AK44/F44 -> 0 | AN44: =AM44/F44 -> 0 | AO44: 14 | AP44: =AO44/F44 -> 5.2330775e-05 | AQ44: 449 | AR44: =AQ44/F44 -> 0.0016783227 | AS44: 168 | AT44: =AS44/F44 -> 0.0006279693 | AU44: 271 | AV44: =AU44/F44 -> 0.0010129743 | AW44: 0 | AX44: =AW44/F44 -> 0 | AY44: =SUM(K44:AX44) -> 2497.0093 | AZ44: =AY44-I44 -> 0.0093335676
A45: ERIO KSE ELECTRICALS PVT LTD Howrah West Bengal | B45: Jan 2026 | C45: 60257500205472 DT 10-SEP-2025 | D45: Southern | E45: SR | F45: 10449 | G45: 10350 | H45: =G45/F45 -> 0.99052541 | I45: 99 | J45: =I45/F45 -> 0.0094745909 | K45: 0 | L45: =K45/F45 -> 0 | M45: 7 | N45: =M45/F45 -> 0.00066992057 | O45: 0 | P45: =O45/F45 -> 0 | R45: =Q45/F45 -> 0 | S45: 19 | T45: =S45/F45 -> 0.0018183558 | U45: 32 | V45: =U45/F45 -> 0.003062494 | W45: 11 | X45: =W45/F45 -> 0.0010527323 | Z45: =Y45/F45 -> 0 | AB45: =AA45/F45 -> 0 | AC45: 0 | AD45: =AC45/F45 -> 0 | AF45: =AE45/F45 -> 0 | AH45: =AG45/F45 -> 0 | AJ45: =AI45/F45 -> 0 | AL45: =AK45/F45 -> 0 | AN45: =AM45/F45 -> 0 | AO45: 0 | AP45: =AO45/F45 -> 0 | AQ45: 8 | AR45: =AQ45/F45 -> 0.0007656235 | AS45: 5 | AT45: =AS45/F45 -> 0.00047851469 | AU45: 17 | AV45: =AU45/F45 -> 0.0016269499 | AW45: 0 | AX45: =AW45/F45 -> 0 | AY45: =SUM(K45:AX45) -> 99.009475 | AZ45: =AY45-I45 -> 0.0094745909
A46: ERIO LNVS INFRA PVT. LTD Tatanagar Jharkhand | B46: December 2025 | C46: 12235234204746 dated 11/07/2025 | D46: Eastern | E46: ER | F46: 140773 | G46: 137864 | H46: =G46/F46 -> 0.97933553 | I46: 2909 | J46: =I46/F46 -> 0.020664474 | K46: 657 | L46: =K46/F46 -> 0.0046670881 | M46: 842 | N46: =M46/F46 -> 0.0059812606 | O46: 61 | P46: =O46/F46 -> 0.00043332173 | R46: =Q46/F46 -> 0 | S46: 305 | T46: =S46/F46 -> 0.0021666087 | U46: 19 | V46: =U46/F46 -> 0.00013496906 | W46: 10 | X46: =W46/F46 -> 7.1036349e-05 | Z46: =Y46/F46 -> 0 | AB46: =AA46/F46 -> 0 | AD46: =AC46/F46 -> 0 | AE46: 765 | AF46: =AE46/F46 -> 0.0054342807 | AH46: =AG46/F46 -> 0 | AJ46: =AI46/F46 -> 0 | AL46: =AK46/F46 -> 0 | AN46: =AM46/F46 -> 0 | AP46: =AO46/F46 -> 0 | AQ46: 250 | AR46: =AQ46/F46 -> 0.0017759087 | AT46: =AS46/F46 -> 0 | AV46: =AU46/F46 -> 0 | AX46: =AW46/F46 -> 0
A47: ERIO LNVS INFRA PVT. LTD Tatanagar Jharkhand | B47: Jan 2026 | C47: 77246507101249 & 01/03/2025 | D47: Northern | E47: NR | F47: 43282 | G47: 42800 | H47: =G47/F47 -> 0.98886373 | I47: 482 | J47: =I47/F47 -> 0.011136269 | K47: 373 | L47: =K47/F47 -> 0.0086179012 | M47: 61 | N47: =M47/F47 -> 0.0014093619 | P47: =O47/F47 -> 0 | R47: =Q47/F47 -> 0 | S47: 48 | T47: =S47/F47 -> 0.0011090061 | U47: 0 | V47: =U47/F47 -> 0 | X47: =W47/F47 -> 0 | Z47: =Y47/F47 -> 0 | AB47: =AA47/F47 -> 0 | AD47: =AC47/F47 -> 0 | AF47: =AE47/F47 -> 0 | AH47: =AG47/F47 -> 0 | AJ47: =AI47/F47 -> 0 | AL47: =AK47/F47 -> 0 | AN47: =AM47/F47 -> 0 | AP47: =AO47/F47 -> 0 | AR47: =AQ47/F47 -> 0 | AT47: =AS47/F47 -> 0 | AU47: 0 | AV47: =AU47/F47 -> 0 | AX47: =AW47/F47 -> 0 | AY47: =SUM(K47:AX47) -> 482.01114 | AZ47: =AY47-I47 -> 0.011136269
A48: ERIO LNVS INFRA PVT. LTD Tatanagar Jharkhand | B48: Jan 2026 | C48: 12235234204746 &11/07/2025 | D48: Eastern | E48: ER | F48: 30662 | G48: 30550 | H48: =G48/F48 -> 0.99634727 | I48: 112 | J48: =I48/F48 -> 0.0036527298 | K48: 70 | L48: =K48/F48 -> 0.0022829561 | M48: 28 | N48: =M48/F48 -> 0.00091318244 | P48: =O48/F48 -> 0 | R48: =Q48/F48 -> 0 | S48: 2 | T48: =S48/F48 -> 6.5227317e-05 | U48: 4 | V48: =U48/F48 -> 0.00013045463 | X48: =W48/F48 -> 0 | Z48: =Y48/F48 -> 0 | AB48: =AA48/F48 -> 0 | AD48: =AC48/F48 -> 0 | AF48: =AE48/F48 -> 0 | AH48: =AG48/F48 -> 0 | AJ48: =AI48/F48 -> 0 | AL48: =AK48/F48 -> 0 | AN48: =AM48/F48 -> 0 | AP48: =AO48/F48 -> 0 | AR48: =AQ48/F48 -> 0 | AT48: =AS48/F48 -> 0 | AU48: 8 | AV48: =AU48/F48 -> 0.00026090927 | AX48: =AW48/F48 -> 0 | AY48: =SUM(K48:AX48) -> 112.00365 | AZ48: =AY48-I48 -> 0.0036527298
A49: ERIO Surya Alloys Industries Limited Durgapur West Bengal | B49: December 2025 | C49: 07244988203129 DATED-14.10.2024 | D49: East Central | E49: ECR | F49: 270752 | G49: 266450 | H49: =G49/F49 -> 0.98411092 | I49: 4302 | J49: =I49/F49 -> 0.015889079 | K49: 44 | L49: =K49/F49 -> 0.00016251034 | M49: 130 | N49: =M49/F49 -> 0.00048014419 | O49: 289 | P49: =O49/F49 -> 0.0010673975 | Q49: 0 | R49: =Q49/F49 -> 0 | S49: 507 | T49: =S49/F49 -> 0.0018725623 | U49: 1148 | V49: =U49/F49 -> 0.0042400425 | X49: =W49/F49 -> 0 | Z49: =Y49/F49 -> 0 | AB49: =AA49/F49 -> 0 | AD49: =AC49/F49 -> 0 | AE49: 501 | AF49: =AE49/F49 -> 0.0018504018 | AH49: =AG49/F49 -> 0 | AJ49: =AI49/F49 -> 0 | AL49: =AK49/F49 -> 0 | AN49: =AM49/F49 -> 0 | AO49: 231 | AP49: =AO49/F49 -> 0.00085317929 | AQ49: 1424 | AR49: =AQ49/F49 -> 0.0052594256 | AT49: =AS49/F49 -> 0 | AU49: 28 | AV49: =AU49/F49 -> 0.00010341567 | AX49: =AW49/F49 -> 0
A50: ERIO Surya Alloys Industries Limited Durgapur West Bengal | B50: December 2025 | C50: 12245535205529 DATED-18.10.2024 | D50: Eastern | E50: ER | F50: 170552 | G50: 168150 | H50: =G50/F50 -> 0.98591632 | I50: 2402 | J50: =I50/F50 -> 0.014083681 | K50: 25 | L50: =K50/F50 -> 0.00014658286 | M50: 24 | N50: =M50/F50 -> 0.00014071955 | O50: 173 | P50: =O50/F50 -> 0.0010143534 | Q50: 0 | R50: =Q50/F50 -> 0 | S50: 398 | T50: =S50/F50 -> 0.0023335991 | U50: 699 | V50: =U50/F50 -> 0.0040984568 | X50: =W50/F50 -> 0 | Z50: =Y50/F50 -> 0 | AB50: =AA50/F50 -> 0 | AD50: =AC50/F50 -> 0 | AE50: 3 | AF50: =AE50/F50 -> 1.7589943e-05 | AH50: =AG50/F50 -> 0 | AJ50: =AI50/F50 -> 0 | AL50: =AK50/F50 -> 0 | AN50: =AM50/F50 -> 0 | AO50: 124 | AP50: =AO50/F50 -> 0.00072705099 | AQ50: 926 | AR50: =AQ50/F50 -> 0.0054294291 | AT50: =AS50/F50 -> 0 | AU50: 30 | AV50: =AU50/F50 -> 0.00017589943 | AX50: =AW50/F50 -> 0
A51: ERIO Surya Alloys Industries Limited Durgapur West Bengal | B51: December 2025 | C51: 07254988202252 DATED-14.06.2025 | D51: East Central | E51: ECR | F51: 498891 | G51: 491560 | H51: =G51/F51 -> 0.98530541 | I51: 7331 | J51: =I51/F51 -> 0.014694593 | K51: 218 | L51: =K51/F51 -> 0.0004369692 | M51: 267 | N51: =M51/F51 -> 0.00053518704 | O51: 705 | P51: =O51/F51 -> 0.0014131343 | Q51: 0 | R51: =Q51/F51 -> 0 | S51: 1253 | T51: =S51/F51 -> 0.0025115707 | U51: 1929 | V51: =U51/F51 -> 0.0038665761 | X51: =W51/F51 -> 0 | Z51: =Y51/F51 -> 0 | AB51: =AA51/F51 -> 0 | AD51: =AC51/F51 -> 0 | AE51: 1 | AF51: =AE51/F51 -> 2.0044459e-06 | AH51: =AG51/F51 -> 0 | AJ51: =AI51/F51 -> 0 | AL51: =AK51/F51 -> 0 | AN51: =AM51/F51 -> 0 | AO51: 366 | AP51: =AO51/F51 -> 0.00073362719 | AQ51: 2440 | AR51: =AQ51/F51 -> 0.0048908479 | AT51: =AS51/F51 -> 0 | AU51: 152 | AV51: =AU51/F51 -> 0.00030467577 | AX51: =AW51/F51 -> 0
A52: ERIO Surya Alloys Industries Limited Durgapur West Bengal | B52: December 2025 | C52: 60257500205474 DATED-10.09.2025 | D52: South Central | E52: SCR | F52: 494960 | G52: 486850 | H52: =G52/F52 -> 0.98361484 | I52: 8110 | J52: =I52/F52 -> 0.016385162 | K52: 75 | L52: =K52/F52 -> 0.0001515274 | M52: 451 | N52: =M52/F52 -> 0.00091118474 | O52: 508 | P52: =O52/F52 -> 0.0010263456 | Q52: 0 | R52: =Q52/F52 -> 0 | S52: 1581 | T52: =S52/F52 -> 0.0031941975 | U52: 2118 | V52: =U52/F52 -> 0.0042791337 | X52: =W52/F52 -> 0 | Z52: =Y52/F52 -> 0 | AB52: =AA52/F52 -> 0 | AD52: =AC52/F52 -> 0 | AE52: 25 | AF52: =AE52/F52 -> 5.0509132e-05 | AH52: =AG52/F52 -> 0 | AJ52: =AI52/F52 -> 0 | AL52: =AK52/F52 -> 0 | AN52: =AM52/F52 -> 0 | AO52: 386 | AP52: =AO52/F52 -> 0.000779861 | AQ52: 2936 | AR52: =AQ52/F52 -> 0.0059317925 | AT52: =AS52/F52 -> 0 | AU52: 30 | AV52: =AU52/F52 -> 6.0610958e-05 | AX52: =AW52/F52 -> 0
A53: ERIO Surya Alloys Industries Limited Durgapur West Bengal | B53: December 2025 | C53: 61255204105005 DATED-16.09.2025 | D53: North East Frontier | E53: NFR | F53: 283328 | G53: 276539 | H53: =G53/F53 -> 0.97603837 | I53: 6789 | J53: =I53/F53 -> 0.023961628 | K53: 48 | L53: =K53/F53 -> 0.00016941495 | M53: 1293 | N53: =M53/F53 -> 0.0045636153 | O53: 589 | P53: =O53/F53 -> 0.0020788627 | Q53: 0 | R53: =Q53/F53 -> 0 | S53: 999 | T53: =S53/F53 -> 0.0035259487 | U53: 1610 | V53: =U53/F53 -> 0.0056824599 | X53: =W53/F53 -> 0 | Z53: =Y53/F53 -> 0 | AB53: =AA53/F53 -> 0 | AD53: =AC53/F53 -> 0 | AE53: 33 | AF53: =AE53/F53 -> 0.00011647278 | AH53: =AG53/F53 -> 0 | AJ53: =AI53/F53 -> 0 | AL53: =AK53/F53 -> 0 | AN53: =AM53/F53 -> 0 | AO53: 227 | AP53: =AO53/F53 -> 0.00080119155 | AQ53: 1973 | AR53: =AQ53/F53 -> 0.0069636605 | AT53: =AS53/F53 -> 0 | AU53: 17 | AV53: =AU53/F53 -> 6.0001129e-05 | AX53: =AW53/F53 -> 0
A54: ERIO Surya Alloys Industries Limited Durgapur West Bengal | B54: December 2025 | C54: 07254988203753 DATED-07.10.2025 | D54: East Central | E54: ECR | F54: 149455 | G54: 147050 | H54: =G54/F54 -> 0.9839082 | I54: 2405 | J54: =I54/F54 -> 0.0160918 | K54: 7 | L54: =K54/F54 -> 4.6836841e-05 | M54: 46 | N54: =M54/F54 -> 0.00030778495 | O54: 203 | P54: =O54/F54 -> 0.0013582684 | Q54: 0 | R54: =Q54/F54 -> 0 | S54: 395 | T54: =S54/F54 -> 0.002642936 | U54: 747 | V54: =U54/F54 -> 0.00499816 | X54: =W54/F54 -> 0 | Z54: =Y54/F54 -> 0 | AB54: =AA54/F54 -> 0 | AD54: =AC54/F54 -> 0 | AE54: 8 | AF54: =AE54/F54 -> 5.3527818e-05 | AH54: =AG54/F54 -> 0 | AJ54: =AI54/F54 -> 0 | AL54: =AK54/F54 -> 0 | AN54: =AM54/F54 -> 0 | AO54: 123 | AP54: =AO54/F54 -> 0.0008229902 | AQ54: 846 | AR54: =AQ54/F54 -> 0.0056605667 | AT54: =AS54/F54 -> 0 | AU54: 30 | AV54: =AU54/F54 -> 0.00020072932 | AX54: =AW54/F54 -> 0
A55: ERIO Surya Alloys Industries Limited Durgapur West Bengal | B55: Jan 2026 | C55: 07244988203129 DATED-14.10.2024 | D55: East Central | E55: ECR | F55: 276610 | G55: 272600 | H55: =G55/F55 -> 0.98550305 | I55: 4010 | J55: =I55/F55 -> 0.014496945 | K55: 0 | L55: =K55/F55 -> 0 | M55: 424 | N55: =M55/F55 -> 0.0015328441 | O55: 276 | P55: =O55/F55 -> 0.00099779473 | Q55: 0 | R55: =Q55/F55 -> 0 | S55: 767 | T55: =S55/F55 -> 0.0027728571 | U55: 980 | V55: =U55/F55 -> 0.0035428943 | X55: =W55/F55 -> 0 | Z55: =Y55/F55 -> 0 | AB55: =AA55/F55 -> 0 | AD55: =AC55/F55 -> 0 | AE55: 50 | AF55: =AE55/F55 -> 0.00018075991 | AH55: =AG55/F55 -> 0 | AJ55: =AI55/F55 -> 0 | AL55: =AK55/F55 -> 0 | AN55: =AM55/F55 -> 0 | AO55: 167 | AP55: =AO55/F55 -> 0.00060373812 | AQ55: 1346 | AR55: =AQ55/F55 -> 0.0048660569 | AS55: 0 | AT55: =AS55/F55 -> 0 | AU55: 0 | AV55: =AU55/F55 -> 0 | AW55: 0 | AX55: =AW55/F55 -> 0 | AY55: =SUM(K55:AX55) -> 4010.0145 | AZ55: =AY55-I55 -> 0.014496945
A56: ERIO Surya Alloys Industries Limited Durgapur West Bengal | B56: Jan 2026 | C56: 12245535205529 DATED-18.10.2024 | D56: Eastern | E56: ER | F56: 595855 | G56: 585550 | H56: =G56/F56 -> 0.98270552 | I56: 10305 | J56: =I56/F56 -> 0.017294476 | K56: 662 | L56: =K56/F56 -> 0.0011110086 | M56: 102 | N56: =M56/F56 -> 0.00017118259 | O56: 742 | P56: =O56/F56 -> 0.0012452694 | Q56: 29 | R56: =Q56/F56 -> 4.8669559e-05 | S56: 1827 | T56: =S56/F56 -> 0.0030661822 | U56: 2854 | V56: =U56/F56 -> 0.0047897559 | X56: =W56/F56 -> 0 | Z56: =Y56/F56 -> 0 | AB56: =AA56/F56 -> 0 | AD56: =AC56/F56 -> 0 | AE56: 0 | AF56: =AE56/F56 -> 0 | AH56: =AG56/F56 -> 0 | AJ56: =AI56/F56 -> 0 | AL56: =AK56/F56 -> 0 | AN56: =AM56/F56 -> 0 | AO56: 415 | AP56: =AO56/F56 -> 0.00069647817 | AQ56: 3608 | AR56: =AQ56/F56 -> 0.0060551644 | AS56: 0 | AT56: =AS56/F56 -> 0 | AU56: 66 | AV56: =AU56/F56 -> 0.0001107652 | AW56: 0 | AX56: =AW56/F56 -> 0 | AY56: =SUM(K56:AX56) -> 10305.017 | AZ56: =AY56-I56 -> 0.017294476
A57: ERIO Surya Alloys Industries Limited Durgapur West Bengal | B57: Jan 2026 | C57: 12255464203830 DATED-05.06.2025 | D57: Eastern | E57: ER | F57: 173379 | G57: 170517 | H57: =G57/F57 -> 0.98349281 | I57: 2862 | J57: =I57/F57 -> 0.016507189 | K57: 0 | L57: =K57/F57 -> 0 | M57: 200 | N57: =M57/F57 -> 0.0011535422 | O57: 181 | P57: =O57/F57 -> 0.0010439557 | Q57: 0 | R57: =Q57/F57 -> 0 | S57: 535 | T57: =S57/F57 -> 0.0030857255 | U57: 801 | V57: =U57/F57 -> 0.0046199367 | X57: =W57/F57 -> 0 | Z57: =Y57/F57 -> 0 | AB57: =AA57/F57 -> 0 | AD57: =AC57/F57 -> 0 | AE57: 0 | AF57: =AE57/F57 -> 0 | AH57: =AG57/F57 -> 0 | AJ57: =AI57/F57 -> 0 | AL57: =AK57/F57 -> 0 | AN57: =AM57/F57 -> 0 | AO57: 120 | AP57: =AO57/F57 -> 0.00069212534 | AQ57: 1025 | AR57: =AQ57/F57 -> 0.005911904 | AS57: 0 | AT57: =AS57/F57 -> 0 | AU57: 0 | AV57: =AU57/F57 -> 0 | AW57: 0 | AX57: =AW57/F57 -> 0 | AY57: =SUM(K57:AX57) -> 2862.0165 | AZ57: =AY57-I57 -> 0.016507189
A58: ERIO Surya Alloys Industries Limited Durgapur West Bengal | B58: Jan 2026 | C58: 60257500205474 DATED-10.09.2025 | D58: South Central | E58: SCR | F58: 244250 | G58: 241270 | H58: =G58/F58 -> 0.98779939 | I58: 2980 | J58: =I58/F58 -> 0.012200614 | K58: 104 | L58: =K58/F58 -> 0.00042579324 | M58: 66 | N58: =M58/F58 -> 0.00027021494 | O58: 197 | P58: =O58/F58 -> 0.00080655067 | Q58: 10 | R58: =Q58/F58 -> 4.0941658e-05 | S58: 627 | T58: =S58/F58 -> 0.002567042 | U58: 849 | V58: =U58/F58 -> 0.0034759468 | X58: =W58/F58 -> 0 | Z58: =Y58/F58 -> 0 | AB58: =AA58/F58 -> 0 | AD58: =AC58/F58 -> 0 | AE58: 0 | AF58: =AE58/F58 -> 0 | AH58: =AG58/F58 -> 0 | AJ58: =AI58/F58 -> 0 | AL58: =AK58/F58 -> 0 | AN58: =AM58/F58 -> 0 | AO58: 102 | AP58: =AO58/F58 -> 0.00041760491 | AQ58: 1010 | AR58: =AQ58/F58 -> 0.0041351075 | AS58: 0 | AT58: =AS58/F58 -> 0 | AU58: 14 | AV58: =AU58/F58 -> 5.7318321e-05 | AW58: 1 | AX58: =AW58/F58 -> 4.0941658e-06 | AY58: =SUM(K58:AX58) -> 2980.0122 | AZ58: =AY58-I58 -> 0.012200614
A59: ERIO Surya Alloys Industries Limited Durgapur West Bengal | B59: Jan 2026 | C59: 01245250101413 DATED-19.11.2025 | D59: North East Frontier | E59: NFR | F59: 158106 | G59: 155750 | H59: =G59/F59 -> 0.9850986 | I59: 2356 | J59: =I59/F59 -> 0.014901395 | K59: 182 | L59: =K59/F59 -> 0.0011511265 | M59: 128 | N59: =M59/F59 -> 0.00080958344 | O59: 202 | P59: =O59/F59 -> 0.0012776239 | Q59: 0 | R59: =Q59/F59 -> 0 | S59: 424 | T59: =S59/F59 -> 0.0026817452 | U59: 600 | V59: =U59/F59 -> 0.0037949224 | X59: =W59/F59 -> 0 | Z59: =Y59/F59 -> 0 | AB59: =AA59/F59 -> 0 | AD59: =AC59/F59 -> 0 | AE59: 0 | AF59: =AE59/F59 -> 0 | AH59: =AG59/F59 -> 0 | AJ59: =AI59/F59 -> 0 | AL59: =AK59/F59 -> 0 | AN59: =AM59/F59 -> 0 | AO59: 79 | AP59: =AO59/F59 -> 0.00049966478 | AQ59: 721 | AR59: =AQ59/F59 -> 0.0045602317 | AS59: 0 | AT59: =AS59/F59 -> 0 | AU59: 20 | AV59: =AU59/F59 -> 0.00012649741 | AW59: 0 | AX59: =AW59/F59 -> 0 | AY59: =SUM(K59:AX59) -> 2356.0149 | AZ59: =AY59-I59 -> 0.014901395
A60: ERIO Surya Alloys Industries Limited Durgapur West Bengal | B60: Jan 2026 | C60: 81255499104487 DATED-19.11.2025 | D60: West Central | E60: WCR | F60: 425080 | G60: 416750 | H60: =G60/F60 -> 0.98040369 | I60: 8330 | J60: =I60/F60 -> 0.019596311 | K60: 347 | L60: =K60/F60 -> 0.00081631693 | M60: 956 | N60: =M60/F60 -> 0.0022489884 | O60: 586 | P60: =O60/F60 -> 0.001378564 | Q60: 2 | R60: =Q60/F60 -> 4.7049967e-06 | S60: 1293 | T60: =S60/F60 -> 0.0030417804 | U60: 2059 | V60: =U60/F60 -> 0.0048437941 | X60: =W60/F60 -> 0 | Z60: =Y60/F60 -> 0 | AB60: =AA60/F60 -> 0 | AD60: =AC60/F60 -> 0 | AE60: 0 | AF60: =AE60/F60 -> 0 | AH60: =AG60/F60 -> 0 | AJ60: =AI60/F60 -> 0 | AL60: =AK60/F60 -> 0 | AN60: =AM60/F60 -> 0 | AO60: 273 | AP60: =AO60/F60 -> 0.00064223205 | AQ60: 2762 | AR60: =AQ60/F60 -> 0.0064976005 | AS60: 5 | AT60: =AS60/F60 -> 1.1762492e-05 | AU60: 47 | AV60: =AU60/F60 -> 0.00011056742 | AW60: 0 | AX60: =AW60/F60 -> 0 | AY60: =SUM(K60:AX60) -> 8330.0196 | AZ60: =AY60-I60 -> 0.019596311
A61: ERIO TECHMA ENGG. Howrah West Bengal | B61: December 2025 | C61: NO PRODUCTION | F61: 0 | G61: 0 | H61: =G61/F61 -> #DIV/0! | I61: 0 | J61: =I61/F61 -> #DIV/0! | L61: =K61/F61 -> #DIV/0! | N61: =M61/F61 -> #DIV/0! | P61: =O61/F61 -> #DIV/0! | R61: =Q61/F61 -> #DIV/0! | T61: =S61/F61 -> #DIV/0! | V61: =U61/F61 -> #DIV/0! | X61: =W61/F61 -> #DIV/0! | Z61: =Y61/F61 -> #DIV/0! | AB61: =AA61/F61 -> #DIV/0! | AD61: =AC61/F61 -> #DIV/0! | AF61: =AE61/F61 -> #DIV/0! | AH61: =AG61/F61 -> #DIV/0! | AJ61: =AI61/F61 -> #DIV/0! | AL61: =AK61/F61 -> #DIV/0! | AN61: =AM61/F61 -> #DIV/0! | AP61: =AO61/F61 -> #DIV/0! | AR61: =AQ61/F61 -> #DIV/0! | AT61: =AS61/F61 -> #DIV/0! | AV61: =AU61/F61 -> #DIV/0! | AX61: =AW61/F61 -> #DIV/0!
A62: ERIO TECHMA ENGG. Howrah West Bengal | B62: Jan 2026 | C62: NO PRODUCTION | H62: =G62/F62 -> #DIV/0! | J62: =I62/F62 -> #DIV/0! | L62: =K62/F62 -> #DIV/0! | N62: =M62/F62 -> #DIV/0! | P62: =O62/F62 -> #DIV/0! | R62: =Q62/F62 -> #DIV/0! | T62: =S62/F62 -> #DIV/0! | V62: =U62/F62 -> #DIV/0! | X62: =W62/F62 -> #DIV/0! | Z62: =Y62/F62 -> #DIV/0! | AB62: =AA62/F62 -> #DIV/0! | AD62: =AC62/F62 -> #DIV/0! | AF62: =AE62/F62 -> #DIV/0! | AH62: =AG62/F62 -> #DIV/0! | AJ62: =AI62/F62 -> #DIV/0! | AL62: =AK62/F62 -> #DIV/0! | AN62: =AM62/F62 -> #DIV/0! | AP62: =AO62/F62 -> #DIV/0! | AR62: =AQ62/F62 -> #DIV/0! | AT62: =AS62/F62 -> #DIV/0! | AV62: =AU62/F62 -> #DIV/0! | AX62: =AW62/F62 -> #DIV/0! | AZ62: =AY62-I62 -> 0
A63: ERIO UTKARSH INDIA LIMITED Howrah West Bengal | B63: December 2025 | C63: NO PRODUCTION | F63: 0 | G63: 0 | H63: =G63/F63 -> #DIV/0! | J63: =I63/F63 -> #DIV/0! | L63: =K63/F63 -> #DIV/0! | N63: =M63/F63 -> #DIV/0! | P63: =O63/F63 -> #DIV/0! | R63: =Q63/F63 -> #DIV/0! | T63: =S63/F63 -> #DIV/0! | V63: =U63/F63 -> #DIV/0! | X63: =W63/F63 -> #DIV/0! | Z63: =Y63/F63 -> #DIV/0! | AB63: =AA63/F63 -> #DIV/0! | AD63: =AC63/F63 -> #DIV/0! | AF63: =AE63/F63 -> #DIV/0! | AH63: =AG63/F63 -> #DIV/0! | AJ63: =AI63/F63 -> #DIV/0! | AL63: =AK63/F63 -> #DIV/0! | AN63: =AM63/F63 -> #DIV/0! | AP63: =AO63/F63 -> #DIV/0! | AR63: =AQ63/F63 -> #DIV/0! | AT63: =AS63/F63 -> #DIV/0! | AV63: =AU63/F63 -> #DIV/0! | AX63: =AW63/F63 -> #DIV/0!
A64: ERIO UTKARSH INDIA LIMITED Howrah West Bengal | B64: Jan 2026 | C64: 60250003103021 DT 23.06.2025 | D64: South Eastern | E64: SER | F64: 68103 | G64: 67265 | H64: =G64/F64 -> 0.98769511 | I64: 838 | J64: =I64/F64 -> 0.012304891 | K64: 26 | L64: =K64/F64 -> 0.00038177466 | M64: 186 | N64: =M64/F64 -> 0.0027311572 | P64: =O64/F64 -> 0 | R64: =Q64/F64 -> 0 | S64: 0 | T64: =S64/F64 -> 0 | U64: 0 | V64: =U64/F64 -> 0 | W64: 81 | X64: =W64/F64 -> 0.0011893749 | Z64: =Y64/F64 -> 0 | AB64: =AA64/F64 -> 0 | AC64: 151 | AD64: =AC64/F64 -> 0.0022172298 | AE64: 0 | AF64: =AE64/F64 -> 0 | AH64: =AG64/F64 -> 0 | AJ64: =AI64/F64 -> 0 | AL64: =AK64/F64 -> 0 | AN64: =AM64/F64 -> 0 | AP64: =AO64/F64 -> 0 | AQ64: 145 | AR64: =AQ64/F64 -> 0.0021291279 | AS64: 75 | AT64: =AS64/F64 -> 0.0011012731 | AU64: 174 | AV64: =AU64/F64 -> 0.0025549535 | AX64: =AW64/F64 -> 0 | AY64: =SUM(K64:AX64) -> 838.0123 | AZ64: =AY64-I64 -> 0.012304891
A65: ERIO UTKARSH INDIA LIMITED Howrah West Bengal | B65: Jan 2026 | C65: 63245440202944 DT.18-JULY-2025 | D65: North Central | E65: NCR | F65: 59557 | G65: 58822 | H65: =G65/F65 -> 0.98765888 | I65: 735 | J65: =I65/F65 -> 0.012341119 | K65: 0 | L65: =K65/F65 -> 0 | M65: 138 | N65: =M65/F65 -> 0.002317108 | P65: =O65/F65 -> 0 | R65: =Q65/F65 -> 0 | S65: 42 | T65: =S65/F65 -> 0.00070520678 | U65: 103 | V65: =U65/F65 -> 0.0017294357 | W65: 0 | X65: =W65/F65 -> 0 | Z65: =Y65/F65 -> 0 | AB65: =AA65/F65 -> 0 | AC65: 77 | AD65: =AC65/F65 -> 0.0012928791 | AE65: 156 | AF65: =AE65/F65 -> 0.0026193395 | AH65: =AG65/F65 -> 0 | AJ65: =AI65/F65 -> 0 | AL65: =AK65/F65 -> 0 | AN65: =AM65/F65 -> 0 | AP65: =AO65/F65 -> 0 | AQ65: 86 | AR65: =AQ65/F65 -> 0.0014439948 | AS65: 74 | AT65: =AS65/F65 -> 0.0012425072 | AU65: 59 | AV65: =AU65/F65 -> 0.00099064761 | AX65: =AW65/F65 -> 0 | AY65: =SUM(K65:AX65) -> 735.01234 | AZ65: =AY65-I65 -> 0.012341119
A66: NRIO Adinath Industries Bhiwadi Haryana | B66: July 2025 | C66: 63245440202943 | D66: North Central | F66: =G66+I66 -> 216362 | G66: 215134 | H66: =G66/F66 -> 0.99432433 | I66: 1228 | J66: =I66/F66 -> 0.0056756732 | L66: =K66/F66 -> 0 | N66: =M66/F66 -> 0 | P66: =O66/F66 -> 0 | R66: =Q66/F66 -> 0 | T66: =S66/F66 -> 0 | V66: =U66/F66 -> 0 | X66: =W66/F66 -> 0 | Z66: =Y66/F66 -> 0 | AB66: =AA66/F66 -> 0 | AD66: =AC66/F66 -> 0 | AF66: =AE66/F66 -> 0 | AH66: =AG66/F66 -> 0 | AJ66: =AI66/F66 -> 0 | AL66: =AK66/F66 -> 0 | AN66: =AM66/F66 -> 0 | AP66: =AO66/F66 -> 0 | AR66: =AQ66/F66 -> 0 | AT66: =AS66/F66 -> 0 | AV66: =AU66/F66 -> 0 | AX66: =AW66/F66 -> 0 | AY66: =SUM(K66:AX66) -> 0 | AZ66: =AY66-I66 -> -1228
A67: NRIO Adinath Industries Bhiwadi Haryana | B67: April 2025 | C67: 63255058201323 | D67: North Western | F67: =G67+I67 -> 504585 | G67: 502843 | H67: =G67/F67 -> 0.99654766 | I67: 1742 | J67: =I67/F67 -> 0.003452342 | L67: =K67/F67 -> 0 | N67: =M67/F67 -> 0 | P67: =O67/F67 -> 0 | R67: =Q67/F67 -> 0 | T67: =S67/F67 -> 0 | V67: =U67/F67 -> 0 | X67: =W67/F67 -> 0 | Z67: =Y67/F67 -> 0 | AB67: =AA67/F67 -> 0 | AD67: =AC67/F67 -> 0 | AF67: =AE67/F67 -> 0 | AH67: =AG67/F67 -> 0 | AJ67: =AI67/F67 -> 0 | AL67: =AK67/F67 -> 0 | AN67: =AM67/F67 -> 0 | AP67: =AO67/F67 -> 0 | AR67: =AQ67/F67 -> 0 | AT67: =AS67/F67 -> 0 | AV67: =AU67/F67 -> 0 | AX67: =AW67/F67 -> 0 | AY67: =SUM(K67:AX67) -> 0 | AZ67: =AY67-I67 -> -1742
A68: NRIO Adinath Industries Bhiwadi Haryana | B68: June 2025 | C68: 63255372202188 | D68: North Western | F68: =G68+I68 -> 54200 | G68: 53783 | H68: =G68/F68 -> 0.99230627 | I68: 417 | J68: =I68/F68 -> 0.0076937269 | L68: =K68/F68 -> 0 | N68: =M68/F68 -> 0 | P68: =O68/F68 -> 0 | R68: =Q68/F68 -> 0 | T68: =S68/F68 -> 0 | V68: =U68/F68 -> 0 | X68: =W68/F68 -> 0 | Z68: =Y68/F68 -> 0 | AB68: =AA68/F68 -> 0 | AD68: =AC68/F68 -> 0 | AF68: =AE68/F68 -> 0 | AH68: =AG68/F68 -> 0 | AJ68: =AI68/F68 -> 0 | AL68: =AK68/F68 -> 0 | AN68: =AM68/F68 -> 0 | AP68: =AO68/F68 -> 0 | AR68: =AQ68/F68 -> 0 | AT68: =AS68/F68 -> 0 | AV68: =AU68/F68 -> 0 | AX68: =AW68/F68 -> 0 | AY68: =SUM(K68:AX68) -> 0 | AZ68: =AY68-I68 -> -417
A69: NRIO Adinath Industries Bhiwadi Haryana | B69: December 2025 | C69: 63245440202943 | D69: North Central | F69: 61300 | G69: =F69-I69 -> 60847 | H69: =G69/F69 -> 0.99261011 | I69: 453 | J69: =I69/F69 -> 0.0073898858 | K69: 0 | L69: =K69/F69 -> 0 | M69: 59 | N69: =M69/F69 -> 0.00096247961 | O69: 54 | P69: =O69/F69 -> 0.00088091354 | Q69: 0 | R69: =Q69/F69 -> 0 | S69: 49 | T69: =S69/F69 -> 0.00079934747 | V69: =U69/F69 -> 0 | W69: 68 | X69: =W69/F69 -> 0.0011092985 | Z69: =Y69/F69 -> 0 | AB69: =AA69/F69 -> 0 | AD69: =AC69/F69 -> 0 | AE69: 44 | AF69: =AE69/F69 -> 0.0007177814 | AH69: =AG69/F69 -> 0 | AJ69: =AI69/F69 -> 0 | AL69: =AK69/F69 -> 0 | AN69: =AM69/F69 -> 0 | AO69: 0 | AP69: =AO69/F69 -> 0 | AR69: =AQ69/F69 -> 0 | AT69: =AS69/F69 -> 0 | AU69: 179 | AV69: =AU69/F69 -> 0.0029200653 | AW69: 0 | AX69: =AW69/F69 -> 0
A70: NRIO Adinath Industries Bhiwadi Haryana | B70: December 2025 | C70: 63255372202188 | D70: North Western | F70: 223258 | G70: =F70-I70 -> 221479 | H70: =G70/F70 -> 0.99203164 | I70: 1779 | J70: =I70/F70 -> 0.0079683595 | K70: 0 | L70: =K70/F70 -> 0 | M70: 222 | N70: =M70/F70 -> 0.00099436526 | O70: 214 | P70: =O70/F70 -> 0.00095853228 | Q70: 0 | R70: =Q70/F70 -> 0 | S70: 201 | T70: =S70/F70 -> 0.00090030368 | V70: =U70/F70 -> 0 | W70: 202 | X70: =W70/F70 -> 0.00090478281 | Z70: =Y70/F70 -> 0 | AB70: =AA70/F70 -> 0 | AD70: =AC70/F70 -> 0 | AE70: 189 | AF70: =AE70/F70 -> 0.00084655421 | AH70: =AG70/F70 -> 0 | AJ70: =AI70/F70 -> 0 | AL70: =AK70/F70 -> 0 | AN70: =AM70/F70 -> 0 | AO70: 0 | AP70: =AO70/F70 -> 0 | AR70: =AQ70/F70 -> 0 | AT70: =AS70/F70 -> 0 | AU70: 751 | AV70: =AU70/F70 -> 0.0033638212 | AW70: 0 | AX70: =AW70/F70 -> 0
A71: NRIO Adinath Industries Bhiwadi Haryana | B71: Jan 2026 | C71: 63255372202188 | D71: North Western | F71: 203101 | G71: 201486 | H71: =G71/F71 -> 0.99204829 | I71: 1615 | J71: =I71/F71 -> 0.0079517088 | L71: =K71/F71 -> 0 | M71: 178 | N71: =M71/F71 -> 0.00087641124 | O71: 136 | P71: =O71/F71 -> 0.00066961758 | R71: =Q71/F71 -> 0 | S71: 163 | T71: =S71/F71 -> 0.00080255636 | V71: =U71/F71 -> 0 | W71: 338 | X71: =W71/F71 -> 0.0016641966 | Z71: =Y71/F71 -> 0 | AB71: =AA71/F71 -> 0 | AD71: =AC71/F71 -> 0 | AE71: 137 | AF71: =AE71/F71 -> 0.00067454124 | AH71: =AG71/F71 -> 0 | AJ71: =AI71/F71 -> 0 | AL71: =AK71/F71 -> 0 | AN71: =AM71/F71 -> 0 | AP71: =AO71/F71 -> 0 | AR71: =AQ71/F71 -> 0 | AS71: 158 | AT71: =AS71/F71 -> 0.00077793807 | AU71: 505 | AV71: =AU71/F71 -> 0.0024864476 | AX71: =AW71/F71 -> 0 | AZ71: =AY71-I71 -> -1615
A72: NRIO Adinath Industries INC Bhiwadi Haryana | B72: June 2025 | C72: 63255372202187 | D72: North Western | F72: =G72+I72 -> 604701 | G72: 601199 | H72: =G72/F72 -> 0.99420871 | I72: 3502 | J72: =I72/F72 -> 0.0057912919 | L72: =K72/F72 -> 0 | N72: =M72/F72 -> 0 | P72: =O72/F72 -> 0 | R72: =Q72/F72 -> 0 | T72: =S72/F72 -> 0 | V72: =U72/F72 -> 0 | X72: =W72/F72 -> 0 | Z72: =Y72/F72 -> 0 | AB72: =AA72/F72 -> 0 | AD72: =AC72/F72 -> 0 | AF72: =AE72/F72 -> 0 | AH72: =AG72/F72 -> 0 | AJ72: =AI72/F72 -> 0 | AL72: =AK72/F72 -> 0 | AN72: =AM72/F72 -> 0 | AP72: =AO72/F72 -> 0 | AR72: =AQ72/F72 -> 0 | AT72: =AS72/F72 -> 0 | AV72: =AU72/F72 -> 0 | AX72: =AW72/F72 -> 0
A73: NRIO Adinath Industries INC Bhiwadi Haryana | B73: April 2025 | C73: 63255058201325 | D73: North Western | F73: =G73+I73 -> 503620 | G73: 502094 | H73: =G73/F73 -> 0.99696994 | I73: 1526 | J73: =I73/F73 -> 0.0030300623 | L73: =K73/F73 -> 0 | N73: =M73/F73 -> 0 | P73: =O73/F73 -> 0 | R73: =Q73/F73 -> 0 | T73: =S73/F73 -> 0 | V73: =U73/F73 -> 0 | X73: =W73/F73 -> 0 | Z73: =Y73/F73 -> 0 | AB73: =AA73/F73 -> 0 | AD73: =AC73/F73 -> 0 | AF73: =AE73/F73 -> 0 | AH73: =AG73/F73 -> 0 | AJ73: =AI73/F73 -> 0 | AL73: =AK73/F73 -> 0 | AN73: =AM73/F73 -> 0 | AP73: =AO73/F73 -> 0 | AR73: =AQ73/F73 -> 0 | AT73: =AS73/F73 -> 0 | AV73: =AU73/F73 -> 0 | AX73: =AW73/F73 -> 0
A74: NRIO Adinath Industries INC Bhiwadi Haryana | B74: Jan 2025 | C74: 81245851100262 | D74: West Central | F74: =G74+I74 -> 43443 | G74: 43258 | H74: =G74/F74 -> 0.99574155 | I74: 185 | J74: =I74/F74 -> 0.0042584536 | L74: =K74/F74 -> 0 | N74: =M74/F74 -> 0 | P74: =O74/F74 -> 0 | R74: =Q74/F74 -> 0 | T74: =S74/F74 -> 0 | V74: =U74/F74 -> 0 | X74: =W74/F74 -> 0 | Z74: =Y74/F74 -> 0 | AB74: =AA74/F74 -> 0 | AD74: =AC74/F74 -> 0 | AF74: =AE74/F74 -> 0 | AH74: =AG74/F74 -> 0 | AJ74: =AI74/F74 -> 0 | AL74: =AK74/F74 -> 0 | AN74: =AM74/F74 -> 0 | AP74: =AO74/F74 -> 0 | AR74: =AQ74/F74 -> 0 | AT74: =AS74/F74 -> 0 | AV74: =AU74/F74 -> 0 | AX74: =AW74/F74 -> 0
A75: NRIO Adinath Industries INC Bhiwadi Haryana | B75: June 2025 | C75: 63255372202187 | D75: North Western | F75: =G75+I75 -> 337341 | G75: 335383 | H75: =G75/F75 -> 0.99419578 | I75: 1958 | J75: =I75/F75 -> 0.0058042159 | L75: =K75/F75 -> 0 | N75: =M75/F75 -> 0 | P75: =O75/F75 -> 0 | R75: =Q75/F75 -> 0 | T75: =S75/F75 -> 0 | V75: =U75/F75 -> 0 | X75: =W75/F75 -> 0 | Z75: =Y75/F75 -> 0 | AB75: =AA75/F75 -> 0 | AD75: =AC75/F75 -> 0 | AF75: =AE75/F75 -> 0 | AH75: =AG75/F75 -> 0 | AJ75: =AI75/F75 -> 0 | AL75: =AK75/F75 -> 0 | AN75: =AM75/F75 -> 0 | AP75: =AO75/F75 -> 0 | AR75: =AQ75/F75 -> 0 | AT75: =AS75/F75 -> 0 | AV75: =AU75/F75 -> 0 | AX75: =AW75/F75 -> 0
A76: NRIO Adinath Industries INC Bhiwadi Haryana | B76: December 2025 | C76: 63255372202187 | D76: North Western | F76: 304516 | G76: =F76-I76 -> 302789 | H76: =G76/F76 -> 0.99432871 | I76: 1727 | J76: =I76/F76 -> 0.0056712948 | K76: 0 | L76: =K76/F76 -> 0 | M76: 213 | N76: =M76/F76 -> 0.00069947064 | O76: 197 | P76: =O76/F76 -> 0.00064692824 | Q76: 0 | R76: =Q76/F76 -> 0 | S76: 151 | T76: =S76/F76 -> 0.00049586885 | U76: 67 | V76: =U76/F76 -> 0.00022002128 | X76: =W76/F76 -> 0 | Z76: =Y76/F76 -> 0 | AB76: =AA76/F76 -> 0 | AD76: =AC76/F76 -> 0 | AE76: 198 | AF76: =AE76/F76 -> 0.00065021214 | AH76: =AG76/F76 -> 0 | AJ76: =AI76/F76 -> 0 | AL76: =AK76/F76 -> 0 | AN76: =AM76/F76 -> 0 | AO76: 0 | AP76: =AO76/F76 -> 0 | AR76: =AQ76/F76 -> 0 | AT76: =AS76/F76 -> 0 | AU76: 901 | AV76: =AU76/F76 -> 0.0029587936 | AW76: 0 | AX76: =AW76/F76 -> 0
A77: NRIO Adinath Industries INC Bhiwadi Haryana | B77: Jan 2026 | C77: 63255372202187 | D77: North Western | F77: 438233 | G77: 435655 | H77: =G77/F77 -> 0.99411728 | I77: 2578 | J77: =I77/F77 -> 0.0058827154 | K77: 0 | L77: =K77/F77 -> 0 | M77: 324 | N77: =M77/F77 -> 0.00073933273 | O77: 313 | P77: =O77/F77 -> 0.00071423193 | Q77: 0 | R77: =Q77/F77 -> 0 | S77: 206 | T77: =S77/F77 -> 0.00047006957 | U77: 93 | V77: =U77/F77 -> 0.00021221588 | X77: =W77/F77 -> 0 | Z77: =Y77/F77 -> 0 | AB77: =AA77/F77 -> 0 | AD77: =AC77/F77 -> 0 | AE77: 284 | AF77: =AE77/F77 -> 0.00064805708 | AH77: =AG77/F77 -> 0 | AJ77: =AI77/F77 -> 0 | AL77: =AK77/F77 -> 0 | AN77: =AM77/F77 -> 0 | AO77: 0 | AP77: =AO77/F77 -> 0 | AR77: =AQ77/F77 -> 0 | AS77: 516 | AT77: =AS77/F77 -> 0.0011774558 | AU77: 842 | AV77: =AU77/F77 -> 0.0019213523 | AW77: 0 | AX77: =AW77/F77 -> 0 | AZ77: =AY77-I77 -> -2578
A78: NRIO Avdesh Tracks(P) Ltd. Mohali Punjab | B78: June 2025 | C78: 7254988202253 | D78: East Central | F78: =G78+I78 -> 294263 | G78: 292687 | H78: =G78/F78 -> 0.99464425 | I78: 1576 | J78: =I78/F78 -> 0.0053557532 | L78: =K78/F78 -> 0 | N78: =M78/F78 -> 0 | P78: =O78/F78 -> 0 | R78: =Q78/F78 -> 0 | T78: =S78/F78 -> 0 | V78: =U78/F78 -> 0 | X78: =W78/F78 -> 0 | Z78: =Y78/F78 -> 0 | AB78: =AA78/F78 -> 0 | AD78: =AC78/F78 -> 0 | AF78: =AE78/F78 -> 0 | AH78: =AG78/F78 -> 0 | AJ78: =AI78/F78 -> 0 | AL78: =AK78/F78 -> 0 | AN78: =AM78/F78 -> 0 | AP78: =AO78/F78 -> 0 | AR78: =AQ78/F78 -> 0 | AT78: =AS78/F78 -> 0 | AV78: =AU78/F78 -> 0 | AX78: =AW78/F78 -> 0
A79: NRIO Avdesh Tracks(P) Ltd. Mohali Punjab | B79: May 2025 | C79: 26245114101043 | D79: North Eastern | F79: =G79+I79 -> 344605 | G79: 343245 | H79: =G79/F79 -> 0.99605345 | I79: 1360 | J79: =I79/F79 -> 0.0039465475 | L79: =K79/F79 -> 0 | N79: =M79/F79 -> 0 | P79: =O79/F79 -> 0 | R79: =Q79/F79 -> 0 | T79: =S79/F79 -> 0 | V79: =U79/F79 -> 0 | X79: =W79/F79 -> 0 | Z79: =Y79/F79 -> 0 | AB79: =AA79/F79 -> 0 | AD79: =AC79/F79 -> 0 | AF79: =AE79/F79 -> 0 | AH79: =AG79/F79 -> 0 | AJ79: =AI79/F79 -> 0 | AL79: =AK79/F79 -> 0 | AN79: =AM79/F79 -> 0 | AP79: =AO79/F79 -> 0 | AR79: =AQ79/F79 -> 0 | AT79: =AS79/F79 -> 0 | AV79: =AU79/F79 -> 0 | AX79: =AW79/F79 -> 0
A80: NRIO Avdesh Tracks(P) Ltd. Mohali Punjab | B80: May 2025 | C80: 81246420101886 | D80: West Central | F80: =G80+I80 -> 94227 | G80: 93924 | H80: =G80/F80 -> 0.99678436 | I80: 303 | J80: =I80/F80 -> 0.0032156388 | L80: =K80/F80 -> 0 | N80: =M80/F80 -> 0 | P80: =O80/F80 -> 0 | R80: =Q80/F80 -> 0 | T80: =S80/F80 -> 0 | V80: =U80/F80 -> 0 | X80: =W80/F80 -> 0 | Z80: =Y80/F80 -> 0 | AB80: =AA80/F80 -> 0 | AD80: =AC80/F80 -> 0 | AF80: =AE80/F80 -> 0 | AH80: =AG80/F80 -> 0 | AJ80: =AI80/F80 -> 0 | AL80: =AK80/F80 -> 0 | AN80: =AM80/F80 -> 0 | AP80: =AO80/F80 -> 0 | AR80: =AQ80/F80 -> 0 | AT80: =AS80/F80 -> 0 | AV80: =AU80/F80 -> 0 | AX80: =AW80/F80 -> 0
A81: NRIO Avdesh Tracks(P) Ltd. Mohali Punjab | B81: December 2025 | C81: 7254988202253 | D81: East Central | F81: 172153 | G81: =F81-I81 -> 171235 | H81: =G81/F81 -> 0.99466753 | I81: 918 | J81: =I81/F81 -> 0.0053324659 | K81: 0 | L81: =K81/F81 -> 0 | M81: 151 | N81: =M81/F81 -> 0.00087712674 | O81: 155 | P81: =O81/F81 -> 0.00090036189 | Q81: 0 | R81: =Q81/F81 -> 0 | S81: 113 | T81: =S81/F81 -> 0.00065639286 | U81: 53 | V81: =U81/F81 -> 0.00030786568 | X81: =W81/F81 -> 0 | Z81: =Y81/F81 -> 0 | AB81: =AA81/F81 -> 0 | AD81: =AC81/F81 -> 0 | AE81: 114 | AF81: =AE81/F81 -> 0.00066220165 | AH81: =AG81/F81 -> 0 | AJ81: =AI81/F81 -> 0 | AL81: =AK81/F81 -> 0 | AN81: =AM81/F81 -> 0 | AO81: 0 | AP81: =AO81/F81 -> 0 | AR81: =AQ81/F81 -> 0 | AT81: =AS81/F81 -> 0 | AU81: 332 | AV81: =AU81/F81 -> 0.0019285171 | AW81: 0 | AX81: =AW81/F81 -> 0
A82: NRIO Avdesh Tracks(P) Ltd. Mohali Punjab | B82: December 2025 | C82: 81246420101886 | D82: West Central | F82: 5600 | G82: =F82-I82 -> 5569 | H82: =G82/F82 -> 0.99446429 | I82: 31 | J82: =I82/F82 -> 0.0055357143 | K82: 0 | L82: =K82/F82 -> 0 | M82: 6 | N82: =M82/F82 -> 0.0010714286 | O82: 5 | P82: =O82/F82 -> 0.00089285714 | Q82: 0 | R82: =Q82/F82 -> 0 | T82: =S82/F82 -> 0 | V82: =U82/F82 -> 0 | X82: =W82/F82 -> 0 | Z82: =Y82/F82 -> 0 | AB82: =AA82/F82 -> 0 | AD82: =AC82/F82 -> 0 | AE82: 5 | AF82: =AE82/F82 -> 0.00089285714 | AH82: =AG82/F82 -> 0 | AJ82: =AI82/F82 -> 0 | AL82: =AK82/F82 -> 0 | AN82: =AM82/F82 -> 0 | AO82: 0 | AP82: =AO82/F82 -> 0 | AR82: =AQ82/F82 -> 0 | AT82: =AS82/F82 -> 0 | AU82: 15 | AV82: =AU82/F82 -> 0.0026785714 | AW82: 0 | AX82: =AW82/F82 -> 0
A83: NRIO Avdesh Tracks(P) Ltd. Mohali Punjab | B83: Jan 2026 | C83: 7254988202253 | D83: East Central | F83: 156828 | G83: 155854 | H83: =G83/F83 -> 0.99378937 | I83: 974 | J83: =I83/F83 -> 0.0062106257 | L83: =K83/F83 -> 0 | M83: 137 | N83: =M83/F83 -> 0.0008735685 | O83: 144 | P83: =O83/F83 -> 0.00091820338 | R83: =Q83/F83 -> 0 | S83: 166 | T83: =S83/F83 -> 0.0010584845 | U83: 0 | V83: =U83/F83 -> 0 | X83: =W83/F83 -> 0 | Z83: =Y83/F83 -> 0 | AB83: =AA83/F83 -> 0 | AD83: =AC83/F83 -> 0 | AE83: 102 | AF83: =AE83/F83 -> 0.00065039406 | AH83: =AG83/F83 -> 0 | AJ83: =AI83/F83 -> 0 | AL83: =AK83/F83 -> 0 | AN83: =AM83/F83 -> 0 | AP83: =AO83/F83 -> 0 | AR83: =AQ83/F83 -> 0 | AT83: =AS83/F83 -> 0 | AU83: 425 | AV83: =AU83/F83 -> 0.0027099753 | AX83: =AW83/F83 -> 0 | AZ83: =AY83-I83 -> -974
A84: NRIO Avdesh Tracks(P) Ltd. Mohali Punjab | B84: Jan 2026 | C84: 81246420101886 | D84: West Central | F84: 41780 | G84: 41535 | H84: =G84/F84 -> 0.99413595 | I84: 245 | J84: =I84/F84 -> 0.0058640498 | L84: =K84/F84 -> 0 | M84: 40 | N84: =M84/F84 -> 0.00095739588 | O84: 40 | P84: =O84/F84 -> 0.00095739588 | R84: =Q84/F84 -> 0 | S84: 0 | T84: =S84/F84 -> 0 | U84: 0 | V84: =U84/F84 -> 0 | X84: =W84/F84 -> 0 | Z84: =Y84/F84 -> 0 | AB84: =AA84/F84 -> 0 | AD84: =AC84/F84 -> 0 | AE84: 27 | AF84: =AE84/F84 -> 0.00064624222 | AH84: =AG84/F84 -> 0 | AJ84: =AI84/F84 -> 0 | AL84: =AK84/F84 -> 0 | AN84: =AM84/F84 -> 0 | AP84: =AO84/F84 -> 0 | AR84: =AQ84/F84 -> 0 | AT84: =AS84/F84 -> 0 | AU84: 138 | AV84: =AU84/F84 -> 0.0033030158 | AX84: =AW84/F84 -> 0 | AZ84: =AY84-I84 -> -245
A85: NRIO Bimla Rail Fasteners Karnal Haryana | B85: June 2025 | C85: 61245413103217 | D85: North East Frontier | F85: =G85+I85 -> 181603 | G85: 181027 | H85: =G85/F85 -> 0.99682825 | I85: 576 | J85: =I85/F85 -> 0.0031717538 | L85: =K85/F85 -> 0 | N85: =M85/F85 -> 0 | P85: =O85/F85 -> 0 | R85: =Q85/F85 -> 0 | T85: =S85/F85 -> 0 | V85: =U85/F85 -> 0 | X85: =W85/F85 -> 0 | Z85: =Y85/F85 -> 0 | AB85: =AA85/F85 -> 0 | AD85: =AC85/F85 -> 0 | AF85: =AE85/F85 -> 0 | AH85: =AG85/F85 -> 0 | AJ85: =AI85/F85 -> 0 | AL85: =AK85/F85 -> 0 | AN85: =AM85/F85 -> 0 | AP85: =AO85/F85 -> 0 | AR85: =AQ85/F85 -> 0 | AT85: =AS85/F85 -> 0 | AV85: =AU85/F85 -> 0 | AX85: =AW85/F85 -> 0
A86: NRIO Bimla Rail Fasteners Karnal Haryana | B86: October 2025 | C86: 77255086207678 | D86: Northern | F86: =G86+I86 -> 14800 | G86: 14732 | H86: =G86/F86 -> 0.99540541 | I86: 68 | J86: =I86/F86 -> 0.0045945946 | L86: =K86/F86 -> 0 | N86: =M86/F86 -> 0 | P86: =O86/F86 -> 0 | R86: =Q86/F86 -> 0 | T86: =S86/F86 -> 0 | V86: =U86/F86 -> 0 | X86: =W86/F86 -> 0 | Z86: =Y86/F86 -> 0 | AB86: =AA86/F86 -> 0 | AD86: =AC86/F86 -> 0 | AF86: =AE86/F86 -> 0 | AH86: =AG86/F86 -> 0 | AJ86: =AI86/F86 -> 0 | AL86: =AK86/F86 -> 0 | AN86: =AM86/F86 -> 0 | AP86: =AO86/F86 -> 0 | AR86: =AQ86/F86 -> 0 | AT86: =AS86/F86 -> 0 | AV86: =AU86/F86 -> 0 | AX86: =AW86/F86 -> 0
A87: NRIO Bimla Rail Fasteners Karnal Haryana | B87: December 2025 | C87: 77255086207679 | D87: Northern | F87: 36436 | G87: 36270 | H87: =G87/F87 -> 0.99544407 | I87: 166 | J87: =I87/F87 -> 0.0045559337 | L87: =K87/F87 -> 0 | N87: =M87/F87 -> 0 | P87: =O87/F87 -> 0 | R87: =Q87/F87 -> 0 | T87: =S87/F87 -> 0 | V87: =U87/F87 -> 0 | X87: =W87/F87 -> 0 | Z87: =Y87/F87 -> 0 | AB87: =AA87/F87 -> 0 | AD87: =AC87/F87 -> 0 | AF87: =AE87/F87 -> 0 | AH87: =AG87/F87 -> 0 | AJ87: =AI87/F87 -> 0 | AL87: =AK87/F87 -> 0 | AN87: =AM87/F87 -> 0 | AP87: =AO87/F87 -> 0 | AR87: =AQ87/F87 -> 0 | AT87: =AS87/F87 -> 0 | AV87: =AU87/F87 -> 0 | AX87: =AW87/F87 -> 0
A88: NRIO Bimla Rail Fasteners Karnal Haryana | B88: October 2025 | C88: 77255086207680 | D88: Northern | F88: =G88+I88 -> 29365 | G88: 29237 | H88: =G88/F88 -> 0.99564107 | I88: 128 | J88: =I88/F88 -> 0.0043589307 | L88: =K88/F88 -> 0 | N88: =M88/F88 -> 0 | P88: =O88/F88 -> 0 | R88: =Q88/F88 -> 0 | T88: =S88/F88 -> 0 | V88: =U88/F88 -> 0 | X88: =W88/F88 -> 0 | Z88: =Y88/F88 -> 0 | AB88: =AA88/F88 -> 0 | AD88: =AC88/F88 -> 0 | AF88: =AE88/F88 -> 0 | AH88: =AG88/F88 -> 0 | AJ88: =AI88/F88 -> 0 | AL88: =AK88/F88 -> 0 | AN88: =AM88/F88 -> 0 | AP88: =AO88/F88 -> 0 | AR88: =AQ88/F88 -> 0 | AT88: =AS88/F88 -> 0 | AV88: =AU88/F88 -> 0 | AX88: =AW88/F88 -> 0
A89: NRIO Bimla Rail Fasteners Karnal Haryana | B89: Novemeber 2025 | C89: 51245078105860 | D89: West Central | F89: =G89+I89 -> 1910407 | G89: 1890874 | H89: =G89/F89 -> 0.98977548 | I89: 19533 | J89: =I89/F89 -> 0.010224523 | L89: =K89/F89 -> 0 | N89: =M89/F89 -> 0 | P89: =O89/F89 -> 0 | R89: =Q89/F89 -> 0 | T89: =S89/F89 -> 0 | V89: =U89/F89 -> 0 | X89: =W89/F89 -> 0 | Z89: =Y89/F89 -> 0 | AB89: =AA89/F89 -> 0 | AD89: =AC89/F89 -> 0 | AF89: =AE89/F89 -> 0 | AH89: =AG89/F89 -> 0 | AJ89: =AI89/F89 -> 0 | AL89: =AK89/F89 -> 0 | AN89: =AM89/F89 -> 0 | AP89: =AO89/F89 -> 0 | AR89: =AQ89/F89 -> 0 | AT89: =AS89/F89 -> 0 | AV89: =AU89/F89 -> 0 | AX89: =AW89/F89 -> 0
A90: NRIO Bimla Rail Fasteners Karnal Haryana | B90: December 2025 | C90: 77255086207678 | D90: Northern | F90: 45220 | G90: =F90-I90 -> 45040 | H90: =G90/F90 -> 0.99601946 | I90: 180 | J90: =I90/F90 -> 0.0039805396 | K90: 0 | L90: =K90/F90 -> 0 | M90: 26 | N90: =M90/F90 -> 0.00057496683 | O90: 40 | P90: =O90/F90 -> 0.00088456435 | Q90: 0 | R90: =Q90/F90 -> 0 | S90: 23 | T90: =S90/F90 -> 0.0005086245 | U90: 8 | V90: =U90/F90 -> 0.00017691287 | X90: =W90/F90 -> 0 | Z90: =Y90/F90 -> 0 | AB90: =AA90/F90 -> 0 | AD90: =AC90/F90 -> 0 | AE90: 27 | AF90: =AE90/F90 -> 0.00059708094 | AH90: =AG90/F90 -> 0 | AJ90: =AI90/F90 -> 0 | AL90: =AK90/F90 -> 0 | AN90: =AM90/F90 -> 0 | AO90: 0 | AP90: =AO90/F90 -> 0 | AR90: =AQ90/F90 -> 0 | AT90: =AS90/F90 -> 0 | AU90: 56 | AV90: =AU90/F90 -> 0.0012383901 | AW90: 0 | AX90: =AW90/F90 -> 0
A91: NRIO Bimla Rail Fasteners Karnal Haryana | B91: December 2025 | C91: 77255086207679 | D91: Northern | F91: 36436 | G91: =F91-I91 -> 36270 | H91: =G91/F91 -> 0.99544407 | I91: 166 | J91: =I91/F91 -> 0.0045559337 | K91: 0 | L91: =K91/F91 -> 0 | M91: 23 | N91: =M91/F91 -> 0.00063124382 | O91: 35 | P91: =O91/F91 -> 0.00096058843 | Q91: 0 | R91: =Q91/F91 -> 0 | S91: 28 | T91: =S91/F91 -> 0.00076847074 | V91: =U91/F91 -> 0 | X91: =W91/F91 -> 0 | Z91: =Y91/F91 -> 0 | AB91: =AA91/F91 -> 0 | AD91: =AC91/F91 -> 0 | AE91: 20 | AF91: =AE91/F91 -> 0.00054890767 | AH91: =AG91/F91 -> 0 | AJ91: =AI91/F91 -> 0 | AL91: =AK91/F91 -> 0 | AN91: =AM91/F91 -> 0 | AO91: 0 | AP91: =AO91/F91 -> 0 | AR91: =AQ91/F91 -> 0 | AT91: =AS91/F91 -> 0 | AU91: 60 | AV91: =AU91/F91 -> 0.001646723 | AW91: 0 | AX91: =AW91/F91 -> 0
A92: NRIO Bimla Rail Fasteners Karnal Haryana | B92: December 2025 | C92: 77255086207680 | D92: Northern | F92: 29237 | G92: =F92-I92 -> 29109 | H92: =G92/F92 -> 0.99562199 | I92: 128 | J92: =I92/F92 -> 0.0043780142 | K92: 0 | L92: =K92/F92 -> 0 | M92: 15 | N92: =M92/F92 -> 0.00051304853 | O92: 27 | P92: =O92/F92 -> 0.00092348736 | Q92: 0 | R92: =Q92/F92 -> 0 | S92: 20 | T92: =S92/F92 -> 0.00068406471 | V92: =U92/F92 -> 0 | X92: =W92/F92 -> 0 | Z92: =Y92/F92 -> 0 | AB92: =AA92/F92 -> 0 | AD92: =AC92/F92 -> 0 | AE92: 15 | AF92: =AE92/F92 -> 0.00051304853 | AH92: =AG92/F92 -> 0 | AJ92: =AI92/F92 -> 0 | AL92: =AK92/F92 -> 0 | AN92: =AM92/F92 -> 0 | AO92: 0 | AP92: =AO92/F92 -> 0 | AR92: =AQ92/F92 -> 0 | AT92: =AS92/F92 -> 0 | AU92: 51 | AV92: =AU92/F92 -> 0.001744365 | AW92: 0 | AX92: =AW92/F92 -> 0
A93: NRIO Bimla Rail Fasteners Karnal Haryana | B93: Jan 2026 | C93: 76255086207678 | D93: Northern | F93: 9035 | G93: 8997 | H93: =G93/F93 -> 0.99579413 | I93: 38 | J93: =I93/F93 -> 0.0042058661 | L93: =K93/F93 -> 0 | M93: 4 | N93: =M93/F93 -> 0.00044272274 | O93: 7 | P93: =O93/F93 -> 0.0007747648 | R93: =Q93/F93 -> 0 | S93: 7 | T93: =S93/F93 -> 0.0007747648 | U93: 0 | V93: =U93/F93 -> 0 | X93: =W93/F93 -> 0 | Z93: =Y93/F93 -> 0 | AB93: =AA93/F93 -> 0 | AD93: =AC93/F93 -> 0 | AE93: 4 | AF93: =AE93/F93 -> 0.00044272274 | AH93: =AG93/F93 -> 0 | AJ93: =AI93/F93 -> 0 | AL93: =AK93/F93 -> 0 | AN93: =AM93/F93 -> 0 | AP93: =AO93/F93 -> 0 | AR93: =AQ93/F93 -> 0 | AT93: =AS93/F93 -> 0 | AU93: 15 | AV93: =AU93/F93 -> 0.0016602103 | AX93: =AW93/F93 -> 0
A94: NRIO Bimla Rail Fasteners Karnal Haryana | B94: Jan 2026 | C94: 81255001102838 | D94: West Central | F94: 195505 | G94: 194138 | H94: =G94/F94 -> 0.99300785 | I94: 1367 | J94: =I94/F94 -> 0.0069921485 | L94: =K94/F94 -> 0 | M94: 164 | N94: =M94/F94 -> 0.00083885323 | O94: 211 | P94: =O94/F94 -> 0.0010792563 | R94: =Q94/F94 -> 0 | S94: 188 | T94: =S94/F94 -> 0.00096161223 | U94: 49 | V94: =U94/F94 -> 0.00025063298 | X94: =W94/F94 -> 0 | Z94: =Y94/F94 -> 0 | AB94: =AA94/F94 -> 0 | AD94: =AC94/F94 -> 0 | AE94: 154 | AF94: =AE94/F94 -> 0.00078770364 | AH94: =AG94/F94 -> 0 | AJ94: =AI94/F94 -> 0 | AL94: =AK94/F94 -> 0 | AN94: =AM94/F94 -> 0 | AP94: =AO94/F94 -> 0 | AR94: =AQ94/F94 -> 0 | AS94: 189 | AT94: =AS94/F94 -> 0.00096672719 | AU94: 412 | AV94: =AU94/F94 -> 0.002107363 | AX94: =AW94/F94 -> 0 | AZ94: =AY94-I94 -> -1367
A95: NRIO Cemcon Railway Industries Gohana Haryana | B95: Novemeber 2025 | C95: 7244989203195 | D95: East Central | F95: 202049 | G95: 200572 | H95: =G95/F95 -> 0.99268989 | I95: 1477 | J95: =I95/F95 -> 0.0073101079 | K95: 0 | L95: =K95/F95 -> 0 | M95: 428 | N95: =M95/F95 -> 0.002118298 | O95: 410 | P95: =O95/F95 -> 0.0020292107 | Q95: 0 | R95: =Q95/F95 -> 0 | S95: 0 | T95: =S95/F95 -> 0 | U95: 0 | V95: =U95/F95 -> 0 | X95: =W95/F95 -> 0 | Z95: =Y95/F95 -> 0 | AB95: =AA95/F95 -> 0 | AD95: =AC95/F95 -> 0 | AE95: 458 | AF95: =AE95/F95 -> 0.0022667769 | AH95: =AG95/F95 -> 0 | AJ95: =AI95/F95 -> 0 | AL95: =AK95/F95 -> 0 | AN95: =AM95/F95 -> 0 | AO95: 0 | AP95: =AO95/F95 -> 0 | AR95: =AQ95/F95 -> 0 | AS95: 181 | AT95: =AS95/F95 -> 0.0008958223 | AU95: 0 | AV95: =AU95/F95 -> 0 | AW95: 0 | AX95: =AW95/F95 -> 0
A96: NRIO Cemcon Railway Industries Gohana Haryana | B96: Jan 2026 | C96: 51245078105859 | D96: Central | F96: 23431 | G96: 23083 | H96: =G96/F96 -> 0.98514788 | I96: 348 | J96: =I96/F96 -> 0.014852119 | K96: 0 | L96: =K96/F96 -> 0 | M96: 25 | N96: =M96/F96 -> 0.0010669626 | O96: 232 | P96: =O96/F96 -> 0.0099014127 | R96: =Q96/F96 -> 0 | S96: 51 | T96: =S96/F96 -> 0.0021766036 | V96: =U96/F96 -> 0 | X96: =W96/F96 -> 0 | Z96: =Y96/F96 -> 0 | AB96: =AA96/F96 -> 0 | AD96: =AC96/F96 -> 0 | AE96: 27 | AF96: =AE96/F96 -> 0.0011523196 | AH96: =AG96/F96 -> 0 | AJ96: =AI96/F96 -> 0 | AL96: =AK96/F96 -> 0 | AN96: =AM96/F96 -> 0 | AO96: 0 | AP96: =AO96/F96 -> 0 | AR96: =AQ96/F96 -> 0 | AS96: 13 | AT96: =AS96/F96 -> 0.00055482054 | AU96: 0 | AV96: =AU96/F96 -> 0 | AW96: 0 | AX96: =AW96/F96 -> 0 | AZ96: =AY96-I96 -> -348
A97: NRIO Fateh Chand Jain Faridabad Haryana | B97: October 2025 | C97: 63245100104526 | D97: North Central | F97: 100424 | G97: =F97-I97 -> 100176 | H97: =G97/F97 -> 0.99753047 | I97: 248 | J97: =I97/F97 -> 0.0024695292 | K97: 0 | L97: =K97/F97 -> 0 | M97: 77 | N97: =M97/F97 -> 0.00076674898 | O97: 22 | P97: =O97/F97 -> 0.00021907114 | Q97: 0 | R97: =Q97/F97 -> 0 | S97: 12 | T97: =S97/F97 -> 0.00011949335 | U97: 0 | V97: =U97/F97 -> 0 | W97: 0 | X97: =W97/F97 -> 0 | Y97: 0 | Z97: =Y97/F97 -> 0 | AA97: 0 | AB97: =AA97/F97 -> 0 | AC97: 0 | AD97: =AC97/F97 -> 0 | AE97: 76 | AF97: =AE97/F97 -> 0.00075679121 | AG97: 0 | AH97: =AG97/F97 -> 0 | AI97: 0 | AJ97: =AI97/F97 -> 0 | AK97: 0 | AL97: =AK97/F97 -> 0 | AM97: 0 | AN97: =AM97/F97 -> 0 | AO97: 0 | AP97: =AO97/F97 -> 0 | AQ97: 0 | AR97: =AQ97/F97 -> 0 | AS97: 61 | AT97: =AS97/F97 -> 0.00060742452 | AU97: 0 | AV97: =AU97/F97 -> 0 | AW97: 0 | AX97: =AW97/F97 -> 0
A98: NRIO Fateh Chand Jain Faridabad Haryana | B98: Novemeber 2025 | C98: 81245608103747 | D98: West Central | F98: =G98+I98 -> 73820 | G98: 73718 | H98: =G98/F98 -> 0.99861826 | I98: 102 | J98: =I98/F98 -> 0.0013817394 | L98: =K98/F98 -> 0 | N98: =M98/F98 -> 0 | P98: =O98/F98 -> 0 | R98: =Q98/F98 -> 0 | T98: =S98/F98 -> 0 | V98: =U98/F98 -> 0 | X98: =W98/F98 -> 0 | Z98: =Y98/F98 -> 0 | AB98: =AA98/F98 -> 0 | AD98: =AC98/F98 -> 0 | AF98: =AE98/F98 -> 0 | AH98: =AG98/F98 -> 0 | AJ98: =AI98/F98 -> 0 | AL98: =AK98/F98 -> 0 | AN98: =AM98/F98 -> 0 | AP98: =AO98/F98 -> 0 | AR98: =AQ98/F98 -> 0 | AT98: =AS98/F98 -> 0 | AV98: =AU98/F98 -> 0 | AX98: =AW98/F98 -> 0
A99: NRIO Fateh Chand Jain Faridabad Haryana | B99: May 2025 | C99: 26245012101169 | D99: North Eastern | F99: =G99+I99 -> 72604 | G99: 72353 | H99: =G99/F99 -> 0.99654289 | I99: 251 | J99: =I99/F99 -> 0.0034571098 | L99: =K99/F99 -> 0 | N99: =M99/F99 -> 0 | P99: =O99/F99 -> 0 | R99: =Q99/F99 -> 0 | T99: =S99/F99 -> 0 | V99: =U99/F99 -> 0 | X99: =W99/F99 -> 0 | Z99: =Y99/F99 -> 0 | AB99: =AA99/F99 -> 0 | AD99: =AC99/F99 -> 0 | AF99: =AE99/F99 -> 0 | AH99: =AG99/F99 -> 0 | AJ99: =AI99/F99 -> 0 | AL99: =AK99/F99 -> 0 | AN99: =AM99/F99 -> 0 | AP99: =AO99/F99 -> 0 | AR99: =AQ99/F99 -> 0 | AT99: =AS99/F99 -> 0 | AV99: =AU99/F99 -> 0 | AX99: =AW99/F99 -> 0
A100: NRIO Fateh Chand Jain Faridabad Haryana | B100: August 2025 | C100: 51245071203888 | D100: Central | F100: =G100+I100 -> 142205 | G100: 141087 | H100: =G100/F100 -> 0.99213811 | I100: 1118 | J100: =I100/F100 -> 0.0078618895 | L100: =K100/F100 -> 0 | N100: =M100/F100 -> 0 | P100: =O100/F100 -> 0 | R100: =Q100/F100 -> 0 | T100: =S100/F100 -> 0 | V100: =U100/F100 -> 0 | X100: =W100/F100 -> 0 | Z100: =Y100/F100 -> 0 | AB100: =AA100/F100 -> 0 | AD100: =AC100/F100 -> 0 | AF100: =AE100/F100 -> 0 | AH100: =AG100/F100 -> 0 | AJ100: =AI100/F100 -> 0 | AL100: =AK100/F100 -> 0 | AN100: =AM100/F100 -> 0 | AP100: =AO100/F100 -> 0 | AR100: =AQ100/F100 -> 0 | AT100: =AS100/F100 -> 0 | AV100: =AU100/F100 -> 0 | AX100: =AW100/F100 -> 0
...

Sheet Copy of Final Month Wise Defect
A2: Firm Name | B2: Month | C2: Inspected (Nos.) | D2: Acceptance (Nos.) | E2: % Acceptance | F2: Rejection (Nos.) | G2: % Rejection | H2: Visual (Sheared Edges, Surface Defects) | I2: ="%"&H2 -> %Visual (Sheared Edges, Surface Defects) | J2: Dimensional | K2: ="%"&J2 -> %Dimensional | L2: Cut bar length | M2: ="%"&L2 -> %Cut bar length | N2: Cut Bar diameter | O2: ="%"&N2 -> %Cut Bar diameter | P2: Turning length | Q2: ="%"&P2 -> %Turning length | R2: Turning Bar Diameter | S2: ="%"&R2 -> %Turning Bar Diameter | T2: Flat Bearing Area | U2: ="%"&T2 -> %Flat Bearing Area | V2: Application & Deflection test | W2: ="%"&V2 -> %Application & Deflection test | X2: Chemical Composition | Y2: ="%"&X2 -> %Chemical Composition | Z2: Toe load | AA2: ="%"&Z2 -> %Toe load | AB2: Hardness | AC2: ="%"&AB2 -> %Hardness | AD2: Microstructure | AE2: ="%"&AD2 -> %Microstructure | AF2: Grain size | AG2: ="%"&AF2 -> %Grain size | AH2: Depth of Decarburization | AI2: ="%"&AH2 -> %Depth of Decarburization | AJ2: Inclusion rating | AK2: ="%"&AJ2 -> %Inclusion rating | AL2: MPI | AM2: ="%"&AL2 -> %MPI | AN2: Forging defect | AO2: ="%"&AN2 -> %Forging defect | AP2: Marking | AQ2: ="%"&AP2 -> %Marking | AR2: Embossing Die Impression / Failure | AS2: ="%"&AR2 -> %Embossing Die Impression / Failure | AT2: Other (less weight) | AU2: ="%"&AT2 -> %Other (less weight)
A3: ERIO AMBE FASTNERS PVT.LTD. Patna Bihar | B3: May 2025 | C3: =D3+F3 -> 34664 | D3: 34447 | E3: =D3/C3 -> 0.9937399 | F3: 217 | G3: =F3/$C3 -> 0.0062600969 | H3: 5 | I3: =H3/$C3 -> 0.00014424186 | J3: 26 | K3: =J3/$C3 -> 0.0007500577 | L3: 102 | M3: =L3/$C3 -> 0.002942534 | N3: 0 | O3: =N3/$C3 -> 0 | P3: 26 | Q3: =P3/$C3 -> 0.0007500577 | R3: 0 | S3: =R3/$C3 -> 0 | T3: 0 | U3: =T3/$C3 -> 0 | W3: =V3/$C3 -> 0 | Y3: =X3/$C3 -> 0 | Z3: 55 | AA3: =Z3/$C3 -> 0.0015866605 | AB3: 0 | AC3: =AB3/$C3 -> 0 | AE3: =AD3/$C3 -> 0 | AG3: =AF3/$C3 -> 0 | AI3: =AH3/$C$3 -> 0 | AK3: =AJ3/$C3 -> 0 | AL3: 0 | AM3: =AL3/$C3 -> 0 | AN3: 0 | AO3: =AN3/$C3 -> 0 | AP3: 0 | AQ3: =AP3/$C3 -> 0 | AR3: 3 | AS3: =AR3/$C3 -> 8.6545119e-05 | AU3: =AT3/$C3 -> 0
A4: ERIO AMBE FASTNERS PVT.LTD. Patna Bihar | B4: June 2025 | C4: =D4+F4 -> 40443 | D4: 40119 | E4: =D4/C4 -> 0.99198872 | F4: 324 | G4: =F4/$C4 -> 0.0080112751 | H4: 0 | I4: =H4/$C4 -> 0 | J4: 43 | K4: =J4/$C4 -> 0.0010632248 | L4: 145 | M4: =L4/$C4 -> 0.0035852929 | N4: 0 | O4: =N4/$C4 -> 0 | P4: 48 | Q4: =P4/$C4 -> 0.0011868556 | R4: 0 | S4: =R4/$C4 -> 0 | T4: 0 | U4: =T4/$C4 -> 0 | W4: =V4/$C4 -> 0 | Y4: =X4/$C4 -> 0 | Z4: 49 | AA4: =Z4/$C4 -> 0.0012115817 | AB4: 0 | AC4: =AB4/$C4 -> 0 | AE4: =AD4/$C4 -> 0 | AG4: =AF4/$C4 -> 0 | AI4: =AH4/$C$3 -> 0 | AK4: =AJ4/$C4 -> 0 | AL4: 0 | AM4: =AL4/$C4 -> 0 | AN4: 30 | AO4: =AN4/$C4 -> 0.00074178473 | AP4: 0 | AQ4: =AP4/$C4 -> 0 | AR4: 9 | AS4: =AR4/$C4 -> 0.00022253542 | AU4: =AT4/$C4 -> 0
A5: ERIO AMBE FASTNERS PVT.LTD. Patna Bihar | B5: July 2025 | C5: =D5+F5 -> 64388 | D5: 63682 | E5: =D5/C5 -> 0.98903522 | F5: 706 | G5: =F5/$C5 -> 0.010964776 | H5: 0 | I5: =H5/$C5 -> 0 | J5: 208 | K5: =J5/$C5 -> 0.0032304156 | L5: 198 | M5: =L5/$C5 -> 0.0030751072 | N5: 0 | O5: =N5/$C5 -> 0 | P5: 38 | Q5: =P5/$C5 -> 0.00059017208 | R5: 0 | S5: =R5/$C5 -> 0 | T5: 0 | U5: =T5/$C5 -> 0 | W5: =V5/$C5 -> 0 | Y5: =X5/$C5 -> 0 | Z5: 117 | AA5: =Z5/$C5 -> 0.0018171088 | AB5: 0 | AC5: =AB5/$C5 -> 0 | AE5: =AD5/$C5 -> 0 | AG5: =AF5/$C5 -> 0 | AI5: =AH5/$C$3 -> 0 | AK5: =AJ5/$C5 -> 0 | AL5: 0 | AM5: =AL5/$C5 -> 0 | AN5: 99 | AO5: =AN5/$C5 -> 0.0015375536 | AP5: 0 | AQ5: =AP5/$C5 -> 0 | AR5: 46 | AS5: =AR5/$C5 -> 0.00071441884 | AU5: =AT5/$C5 -> 0
A6: ERIO AMBE FASTNERS PVT.LTD. Patna Bihar | B6: August 2025 | C6: =D6+F6 -> 54536 | D6: 53885 | E6: =D6/C6 -> 0.98806293 | F6: 651 | G6: =F6/$C6 -> 0.011937069 | H6: 0 | I6: =H6/$C6 -> 0 | J6: 120 | K6: =J6/$C6 -> 0.0022003814 | L6: 277 | M6: =L6/$C6 -> 0.0050792137 | N6: 0 | O6: =N6/$C6 -> 0 | P6: 29 | Q6: =P6/$C6 -> 0.00053175884 | R6: 0 | S6: =R6/$C6 -> 0 | T6: 0 | U6: =T6/$C6 -> 0 | W6: =V6/$C6 -> 0 | Y6: =X6/$C6 -> 0 | Z6: 86 | AA6: =Z6/$C6 -> 0.00157694 | AB6: 0 | AC6: =AB6/$C6 -> 0 | AE6: =AD6/$C6 -> 0 | AG6: =AF6/$C6 -> 0 | AI6: =AH6/$C$3 -> 0 | AK6: =AJ6/$C6 -> 0 | AL6: 0 | AM6: =AL6/$C6 -> 0 | AN6: 117 | AO6: =AN6/$C6 -> 0.0021453719 | AP6: 0 | AQ6: =AP6/$C6 -> 0 | AR6: 22 | AS6: =AR6/$C6 -> 0.00040340326 | AU6: =AT6/$C6 -> 0
A7: ERIO AMBE FASTNERS PVT.LTD. Patna Bihar | B7: September 2025 | C7: =D7+F7 -> 13699 | D7: 13660 | E7: =D7/C7 -> 0.99715308 | F7: 39 | G7: =F7/$C7 -> 0.0028469231 | H7: 0 | I7: =H7/$C7 -> 0 | J7: 10 | K7: =J7/$C7 -> 0.00072998029 | L7: 0 | M7: =L7/$C7 -> 0 | N7: 0 | O7: =N7/$C7 -> 0 | P7: 0 | Q7: =P7/$C7 -> 0 | R7: 0 | S7: =R7/$C7 -> 0 | T7: 0 | U7: =T7/$C7 -> 0 | W7: =V7/$C7 -> 0 | Y7: =X7/$C7 -> 0 | Z7: 14 | AA7: =Z7/$C7 -> 0.0010219724 | AB7: 0 | AC7: =AB7/$C7 -> 0 | AE7: =AD7/$C7 -> 0 | AG7: =AF7/$C7 -> 0 | AI7: =AH7/$C$3 -> 0 | AK7: =AJ7/$C7 -> 0 | AL7: 0 | AM7: =AL7/$C7 -> 0 | AN7: 12 | AO7: =AN7/$C7 -> 0.00087597635 | AP7: 0 | AQ7: =AP7/$C7 -> 0 | AR7: 3 | AS7: =AR7/$C7 -> 0.00021899409 | AU7: =AT7/$C7 -> 0
A8: ERIO CALCUTTA SPRINGS LTD. Howrah West Bengal | B8: May 2025 | C8: =D8+F8 -> 15599 | D8: 15520 | E8: =D8/C8 -> 0.99493557 | F8: 79 | G8: =F8/$C8 -> 0.0050644272 | H8: 0 | I8: =H8/$C8 -> 0 | J8: 0 | K8: =J8/$C8 -> 0 | L8: 8 | M8: =L8/$C8 -> 0.00051285339 | N8: 0 | O8: =N8/$C8 -> 0 | P8: 20 | Q8: =P8/$C8 -> 0.0012821335 | R8: 42 | S8: =R8/$C8 -> 0.0026924803 | T8: 0 | U8: =T8/$C8 -> 0 | W8: =V8/$C8 -> 0 | Y8: =X8/$C8 -> 0 | Z8: 0 | AA8: =Z8/$C8 -> 0 | AB8: 0 | AC8: =AB8/$C8 -> 0 | AE8: =AD8/$C8 -> 0 | AG8: =AF8/$C8 -> 0 | AI8: =AH8/$C$3 -> 0 | AK8: =AJ8/$C8 -> 0 | AL8: 9 | AM8: =AL8/$C8 -> 0.00057696006 | AN8: 0 | AO8: =AN8/$C8 -> 0 | AP8: 0 | AQ8: =AP8/$C8 -> 0 | AR8: 0 | AS8: =AR8/$C8 -> 0 | AU8: =AT8/$C8 -> 0
A9: ERIO CALCUTTA SPRINGS LTD. Howrah West Bengal | B9: June 2025 | C9: =D9+F9 -> 85419 | D9: 84700 | E9: =D9/C9 -> 0.99158267 | F9: 719 | G9: =F9/$C9 -> 0.008417331 | H9: 0 | I9: =H9/$C9 -> 0 | J9: 72 | K9: =J9/$C9 -> 0.0008429038 | L9: 110 | M9: =L9/$C9 -> 0.0012877697 | N9: 0 | O9: =N9/$C9 -> 0 | P9: 195 | Q9: =P9/$C9 -> 0.0022828645 | R9: 198 | S9: =R9/$C9 -> 0.0023179855 | T9: 0 | U9: =T9/$C9 -> 0 | W9: =V9/$C9 -> 0 | Y9: =X9/$C9 -> 0 | Z9: 0 | AA9: =Z9/$C9 -> 0 | AB9: 59 | AC9: =AB9/$C9 -> 0.00069071284 | AE9: =AD9/$C9 -> 0 | AG9: =AF9/$C9 -> 0 | AI9: =AH9/$C$3 -> 0 | AK9: =AJ9/$C9 -> 0 | AL9: 17 | AM9: =AL9/$C9 -> 0.00019901895 | AN9: 68 | AO9: =AN9/$C9 -> 0.00079607581 | AP9: 0 | AQ9: =AP9/$C9 -> 0 | AR9: 0 | AS9: =AR9/$C9 -> 0 | AU9: =AT9/$C9 -> 0
A10: ERIO CALCUTTA SPRINGS LTD. Howrah West Bengal | B10: July 2025 | C10: =D10+F10 -> 113463 | D10: 112885 | E10: =D10/C10 -> 0.99490583 | F10: 578 | G10: =F10/$C10 -> 0.0050941717 | H10: 0 | I10: =H10/$C10 -> 0 | J10: 74 | K10: =J10/$C10 -> 0.00065219499 | L10: 101 | M10: =L10/$C10 -> 0.00089015803 | N10: 0 | O10: =N10/$C10 -> 0 | P10: 60 | Q10: =P10/$C10 -> 0.00052880675 | R10: 101 | S10: =R10/$C10 -> 0.00089015803 | T10: 0 | U10: =T10/$C10 -> 0 | W10: =V10/$C10 -> 0 | Y10: =X10/$C10 -> 0 | Z10: 0 | AA10: =Z10/$C10 -> 0 | AB10: 76 | AC10: =AB10/$C10 -> 0.00066982188 | AE10: =AD10/$C10 -> 0 | AG10: =AF10/$C10 -> 0 | AI10: =AH10/$C$3 -> 0 | AK10: =AJ10/$C10 -> 0 | AL10: 40 | AM10: =AL10/$C10 -> 0.00035253783 | AN10: 126 | AO10: =AN10/$C10 -> 0.0011104942 | AP10: 0 | AQ10: =AP10/$C10 -> 0 | AR10: 0 | AS10: =AR10/$C10 -> 0 | AU10: =AT10/$C10 -> 0
A11: ERIO CALCUTTA SPRINGS LTD. Howrah West Bengal | B11: August 2025 | C11: =D11+F11 -> 198328 | D11: 197420 | E11: =D11/C11 -> 0.99542173 | F11: 908 | G11: =F11/$C11 -> 0.0045782744 | H11: 0 | I11: =H11/$C11 -> 0 | J11: 86 | K11: =J11/$C11 -> 0.00043362511 | L11: 173 | M11: =L11/$C11 -> 0.00087229236 | N11: 0 | O11: =N11/$C11 -> 0 | P11: 80 | Q11: =P11/$C11 -> 0.00040337219 | R11: 95 | S11: =R11/$C11 -> 0.00047900448 | T11: 0 | U11: =T11/$C11 -> 0 | W11: =V11/$C11 -> 0 | Y11: =X11/$C11 -> 0 | Z11: 134 | AA11: =Z11/$C11 -> 0.00067564842 | AB11: 0 | AC11: =AB11/$C11 -> 0 | AE11: =AD11/$C11 -> 0 | AG11: =AF11/$C11 -> 0 | AI11: =AH11/$C$3 -> 0 | AK11: =AJ11/$C11 -> 0 | AL11: 35 | AM11: =AL11/$C11 -> 0.00017647533 | AN11: 305 | AO11: =AN11/$C11 -> 0.0015378565 | AP11: 0 | AQ11: =AP11/$C11 -> 0 | AR11: 0 | AS11: =AR11/$C11 -> 0 | AU11: =AT11/$C11 -> 0
A12: ERIO CALCUTTA SPRINGS LTD. Howrah West Bengal | B12: September 2025 | C12: =D12+F12 -> 355915 | D12: 354044 | E12: =D12/C12 -> 0.99474313 | F12: 1871 | G12: =F12/$C12 -> 0.0052568731 | H12: 0 | I12: =H12/$C12 -> 0 | J12: 330 | K12: =J12/$C12 -> 0.00092718767 | L12: 658 | M12: =L12/$C12 -> 0.001848756 | N12: 0 | O12: =N12/$C12 -> 0 | P12: 201 | Q12: =P12/$C12 -> 0.00056474158 | R12: 151 | S12: =R12/$C12 -> 0.0004242586 | T12: 0 | U12: =T12/$C12 -> 0 | W12: =V12/$C12 -> 0 | Y12: =X12/$C12 -> 0 | Z12: 161 | AA12: =Z12/$C12 -> 0.0004523552 | AB12: 0 | AC12: =AB12/$C12 -> 0 | AE12: =AD12/$C12 -> 0 | AG12: =AF12/$C12 -> 0 | AI12: =AH12/$C$3 -> 0 | AK12: =AJ12/$C12 -> 0 | AL12: 12 | AM12: =AL12/$C12 -> 3.3715915e-05 | AN12: 358 | AO12: =AN12/$C12 -> 0.0010058581 | AP12: 0 | AQ12: =AP12/$C12 -> 0 | AR12: 0 | AS12: =AR12/$C12 -> 0 | AU12: =AT12/$C12 -> 0
A13: ERIO CALCUTTA SPRINGS LTD. Howrah West Bengal | B13: October 2025 | C13: =D13+F13 -> 417139 | D13: 414973 | E13: =D13/C13 -> 0.99480749 | F13: 2166 | G13: =F13/$C13 -> 0.0051925138 | H13: 0 | I13: =H13/$C13 -> 0 | J13: 536 | K13: =J13/$C13 -> 0.0012849434 | L13: 423 | M13: =L13/$C13 -> 0.0010140505 | N13: 0 | O13: =N13/$C13 -> 0 | P13: 155 | Q13: =P13/$C13 -> 0.00037157878 | R13: 204 | S13: =R13/$C13 -> 0.00048904562 | T13: 0 | U13: =T13/$C13 -> 0 | W13: =V13/$C13 -> 0 | Y13: =X13/$C13 -> 0 | Z13: 192 | AA13: =Z13/$C13 -> 0.00046027823 | AB13: 10 | AC13: =AB13/$C13 -> 2.3972824e-05 | AE13: =AD13/$C13 -> 0 | AG13: =AF13/$C13 -> 0 | AI13: =AH13/$C$3 -> 0 | AK13: =AJ13/$C13 -> 0 | AL13: 0 | AM13: =AL13/$C13 -> 0 | AN13: 646 | AO13: =AN13/$C13 -> 0.0015486445 | AP13: 0 | AQ13: =AP13/$C13 -> 0 | AR13: 0 | AS13: =AR13/$C13 -> 0 | AU13: =AT13/$C13 -> 0
A14: ERIO CALCUTTA SPRINGS LTD. Howrah West Bengal | B14: Novemeber 2025 | C14: =D14+F14 -> 318458 | D14: 315812 | E14: =D14/C14 -> 0.99169121 | F14: 2646 | G14: =F14/$C14 -> 0.008308788 | H14: 0 | I14: =H14/$C14 -> 0 | J14: 768 | K14: =J14/$C14 -> 0.002411621 | L14: 562 | M14: =L14/$C14 -> 0.0017647539 | N14: 0 | O14: =N14/$C14 -> 0 | P14: 302 | Q14: =P14/$C14 -> 0.00094831972 | R14: 223 | S14: =R14/$C14 -> 0.00070024933 | T14: 0 | U14: =T14/$C14 -> 0 | W14: =V14/$C14 -> 0 | Y14: =X14/$C14 -> 0 | Z14: 107 | AA14: =Z14/$C14 -> 0.00033599407 | AB14: 0 | AC14: =AB14/$C14 -> 0 | AE14: =AD14/$C14 -> 0 | AG14: =AF14/$C14 -> 0 | AI14: =AH14/$C$3 -> 0 | AK14: =AJ14/$C14 -> 0 | AL14: 59 | AM14: =AL14/$C14 -> 0.00018526776 | AN14: 625 | AO14: =AN14/$C14 -> 0.0019625822 | AP14: 0 | AQ14: =AP14/$C14 -> 0 | AR14: 0 | AS14: =AR14/$C14 -> 0 | AU14: =AT14/$C14 -> 0
... A20: ERIO KALIMATA ISPAT (Unit-1) Howrah West Bengal | B20: Novemeber 2025 | C20: =D20+F20 -> 218950 | D20: 216453 | E20: =D20/C20 -> 0.98859557 | F20: 2497 | G20: =F20/$C20 -> 0.01140443 | H20: 568 | I20: =H20/$C20 -> 0.0025941996 | J20: 103 | K20: =J20/$C20 -> 0.00047042704 | L20: 97 | M20: =L20/$C20 -> 0.00044302352 | N20: 0 | O20: =N20/$C20 -> 0 | P20: 483 | Q20: =P20/$C20 -> 0.0022059831 | R20: 250 | S20: =R20/$C20 -> 0.0011418132 | T20: 25 | U20: =T20/$C20 -> 0.00011418132 | W20: =V20/$C20 -> 0 | Y20: =X20/$C20 -> 0 | Z20: 50 | AA20: =Z20/$C20 -> 0.00022836264 | AB20: 0 | AC20: =AB20/$C20 -> 0 | AE20: =AD20/$C20 -> 0 | AG20: =AF20/$C20 -> 0 | AI20: =AH20/$C$3 -> 0 | AK20: =AJ20/$C20 -> 0 | AL20: 0 | AM20: =AL20/$C20 -> 0 | AN20: 715 | AO20: =AN20/$C20 -> 0.0032655858 | AP20: 0 | AQ20: =AP20/$C20 -> 0 | AR20: 206 | AS20: =AR20/$C20 -> 0.00094085408 | AU20: =AT20/$C20 -> 0
A21: ERIO KALIMATA ISPAT (Unit-II) Durgapur West Bengal | B21: September 2025 | C21: =D21+F21 -> 155530 | D21: 153672 | E21: =D21/C21 -> 0.98805375 | F21: 1858 | G21: =F21/$C21 -> 0.011946248 | H21: 0 | I21: =H21/$C21 -> 0 | J21: 54 | K21: =J21/$C21 -> 0.0003471999 | L21: 67 | M21: =L21/$C21 -> 0.00043078506 | N21: 0 | O21: =N21/$C21 -> 0 | P21: 1125 | Q21: =P21/$C21 -> 0.0072333312 | R21: 336 | S21: =R21/$C21 -> 0.0021603549 | T21: 0 | U21: =T21/$C21 -> 0 | W21: =V21/$C21 -> 0 | Y21: =X21/$C21 -> 0 | Z21: 0 | AA21: =Z21/$C21 -> 0 | AB21: 2 | AC21: =AB21/$C21 -> 1.2859255e-05 | AE21: =AD21/$C21 -> 0 | AG21: =AF21/$C21 -> 0 | AI21: =AH21/$C$3 -> 0 | AK21: =AJ21/$C21 -> 0 | AL21: 0 | AM21: =AL21/$C21 -> 0 | AN21: 274 | AO21: =AN21/$C21 -> 0.001761718 | AP21: 0 | AQ21: =AP21/$C21 -> 0 | AR21: 0 | AS21: =AR21/$C21 -> 0 | AT21: 0 | AU21: =AT21/$C21 -> 0
A22: ERIO KALIMATA ISPAT (Unit-II) Durgapur West Bengal | B22: October 2025 | C22: =D22+F22 -> 313842 | D22: 312274 | E22: =D22/C22 -> 0.99500386 | F22: 1568 | G22: =F22/$C22 -> 0.0049961446 | H22: 0 | I22: =H22/$C22 -> 0 | J22: 41 | K22: =J22/$C22 -> 0.00013063898 | L22: 45 | M22: =L22/$C22 -> 0.00014338425 | N22: 0 | O22: =N22/$C22 -> 0 | P22: 740 | Q22: =P22/$C22 -> 0.0023578743 | R22: 541 | S22: =R22/$C22 -> 0.0017237973 | T22: 0 | U22: =T22/$C22 -> 0 | W22: =V22/$C22 -> 0 | Y22: =X22/$C22 -> 0 | Z22: 0 | AA22: =Z22/$C22 -> 0 | AB22: 2 | AC22: =AB22/$C22 -> 6.3726334e-06 | AE22: =AD22/$C22 -> 0 | AG22: =AF22/$C22 -> 0 | AI22: =AH22/$C$3 -> 0 | AK22: =AJ22/$C22 -> 0 | AL22: 0 | AM22: =AL22/$C22 -> 0 | AN22: 195 | AO22: =AN22/$C22 -> 0.00062133175 | AP22: 0 | AQ22: =AP22/$C22 -> 0 | AR22: 0 | AS22: =AR22/$C22 -> 0 | AT22: 4 | AU22: =AT22/$C22 -> 1.2745267e-05
A23: ERIO KALIMATA ISPAT (Unit-II) Durgapur West Bengal | B23: Novemeber 2025 | C23: =D23+F23 -> 356696 | D23: 354982 | E23: =D23/C23 -> 0.99519479 | F23: 1714 | G23: =F23/$C23 -> 0.0048052123 | H23: 0 | I23: =H23/$C23 -> 0 | J23: 4 | K23: =J23/$C23 -> 1.1214031e-05 | L23: 34 | M23: =L23/$C23 -> 9.5319263e-05 | N23: 0 | O23: =N23/$C23 -> 0 | P23: 786 | Q23: =P23/$C23 -> 0.0022035571 | R23: 666 | S23: =R23/$C23 -> 0.0018671362 | T23: 0 | U23: =T23/$C23 -> 0 | W23: =V23/$C23 -> 0 | Y23: =X23/$C23 -> 0 | Z23: 0 | AA23: =Z23/$C23 -> 0 | AB23: 24 | AC23: =AB23/$C23 -> 6.7284186e-05 | AE23: =AD23/$C23 -> 0 | AG23: =AF23/$C23 -> 0 | AI23: =AH23/$C$3 -> 0 | AK23: =AJ23/$C23 -> 0 | AL23: 0 | AM23: =AL23/$C23 -> 0 | AN23: 190 | AO23: =AN23/$C23 -> 0.00053266647 | AP23: 0 | AQ23: =AP23/$C23 -> 0 | AR23: 0 | AS23: =AR23/$C23 -> 0 | AT23: 10 | AU23: =AT23/$C23 -> 2.8035077e-05
A24: ERIO KALIMATA VYAPAAR (Unit-II) Durgapur West Bengal | B24: July 2025 | C24: =D24+F24 -> 257043 | D24: 253874 | E24: =D24/C24 -> 0.98767132 | F24: 3169 | G24: =F24/$C24 -> 0.012328677 | H24: 0 | I24: =H24/$C24 -> 0 | J24: 176 | K24: =J24/$C24 -> 0.00068471034 | L24: 127 | M24: =L24/$C24 -> 0.00049408076 | N24: 0 | O24: =N24/$C24 -> 0 | P24: 1343 | Q24: =P24/$C24 -> 0.0052248067 | R24: 715 | S24: =R24/$C24 -> 0.0027816358 | T24: 0 | U24: =T24/$C24 -> 0 | W24: =V24/$C24 -> 0 | Y24: =X24/$C24 -> 0 | Z24: 360 | AA24: =Z24/$C24 -> 0.0014005439 | AB24: 0 | AC24: =AB24/$C24 -> 0 | AE24: =AD24/$C24 -> 0 | AG24: =AF24/$C24 -> 0 | AI24: =AH24/$C$3 -> 0 | AK24: =AJ24/$C24 -> 0 | AL24: 0 | AM24: =AL24/$C24 -> 0 | AN24: 442 | AO24: =AN24/$C24 -> 0.0017195567 | AP24: 0 | AQ24: =AP24/$C24 -> 0 | AR24: 6 | AS24: =AR24/$C24 -> 2.3342398e-05 | AT24: 0 | AU24: =AT24/$C24 -> 0
A25: ERIO KALIMATA VYAPAAR (Unit-II) Durgapur West Bengal | B25: August 2025 | C25: =D25+F25 -> 500964 | D25: 495090 | E25: =D25/C25 -> 0.98827461 | F25: 5874 | G25: =F25/$C25 -> 0.011725393 | H25: 0 | I25: =H25/$C25 -> 0 | J25: 63 | K25: =J25/$C25 -> 0.00012575754 | L25: 88 | M25: =L25/$C25 -> 0.00017566132 | N25: 0 | O25: =N25/$C25 -> 0 | P25: 2366 | Q25: =P25/$C25 -> 0.0047228943 | R25: 2326 | S25: =R25/$C25 -> 0.0046430482 | T25: 0 | U25: =T25/$C25 -> 0 | W25: =V25/$C25 -> 0 | Y25: =X25/$C25 -> 0 | Z25: 0 | AA25: =Z25/$C25 -> 0 | AB25: 0 | AC25: =AB25/$C25 -> 0 | AE25: =AD25/$C25 -> 0 | AG25: =AF25/$C25 -> 0 | AI25: =AH25/$C$3 -> 0 | AK25: =AJ25/$C25 -> 0 | AL25: 0 | AM25: =AL25/$C25 -> 0 | AN25: 1031 | AO25: =AN25/$C25 -> 0.0020580321 | AP25: 0 | AQ25: =AP25/$C25 -> 0 | AR25: 0 | AS25: =AR25/$C25 -> 0 | AT25: 0 | AU25: =AT25/$C25 -> 0
A26: ERIO KALIMATA VYAPAAR (Unit-II) Durgapur West Bengal | B26: September 2025 | C26: =D26+F26 -> 475451 | D26: 467681 | E26: =D26/C26 -> 0.98365762 | F26: 7770 | G26: =F26/$C26 -> 0.016342378 | H26: 0 | I26: =H26/$C26 -> 0 | J26: 85 | K26: =J26/$C26 -> 0.00017877762 | L26: 106 | M26: =L26/$C26 -> 0.00022294621 | N26: 0 | O26: =N26/$C26 -> 0 | P26: 4909 | Q26: =P26/$C26 -> 0.010324934 | R26: 1256 | S26: =R26/$C26 -> 0.0026417023 | T26: 0 | U26: =T26/$C26 -> 0 | W26: =V26/$C26 -> 0 | Y26: =X26/$C26 -> 0 | Z26: 0 | AA26: =Z26/$C26 -> 0 | AB26: 0 | AC26: =AB26/$C26 -> 0 | AE26: =AD26/$C26 -> 0 | AG26: =AF26/$C26 -> 0 | AI26: =AH26/$C$3 -> 0 | AK26: =AJ26/$C26 -> 0 | AL26: 0 | AM26: =AL26/$C26 -> 0 | AN26: 1414 | AO26: =AN26/$C26 -> 0.0029740184 | AP26: 0 | AQ26: =AP26/$C26 -> 0 | AR26: 0 | AS26: =AR26/$C26 -> 0 | AT26: 0 | AU26: =AT26/$C26 -> 0
A27: ERIO KALIMATA VYAPAAR (Unit-II) Durgapur West Bengal | B27: October 2025 | C27: =D27+F27 -> 376988 | D27: 369610 | E27: =D27/C27 -> 0.98042909 | F27: 7378 | G27: =F27/$C27 -> 0.019570915 | H27: 0 | I27: =H27/$C27 -> 0 | J27: 187 | K27: =J27/$C27 -> 0.00049603701 | L27: 101 | M27: =L27/$C27 -> 0.00026791304 | N27: 0 | O27: =N27/$C27 -> 0 | P27: 3346 | Q27: =P27/$C27 -> 0.0088756141 | R27: 1458 | S27: =R27/$C27 -> 0.0038674971 | T27: 0 | U27: =T27/$C27 -> 0 | W27: =V27/$C27 -> 0 | Y27: =X27/$C27 -> 0 | Z27: 0 | AA27: =Z27/$C27 -> 0 | AB27: 0 | AC27: =AB27/$C27 -> 0 | AE27: =AD27/$C27 -> 0 | AG27: =AF27/$C27 -> 0 | AI27: =AH27/$C$3 -> 0 | AK27: =AJ27/$C27 -> 0 | AL27: 0 | AM27: =AL27/$C27 -> 0 | AN27: 786 | AO27: =AN27/$C27 -> 0.002084947 | AP27: 0 | AQ27: =AP27/$C27 -> 0 | AR27: 1500 | AS27: =AR27/$C27 -> 0.0039789065 | AT27: 0 | AU27: =AT27/$C27 -> 0
A28: ERIO KALIMATA VYAPAAR (Unit-II) Durgapur West Bengal | B28: Novemeber 2025 | C28: =D28+F28 -> 421734 | D28: 416226 | E28: =D28/C28 -> 0.98693963 | F28: 5508 | G28: =F28/$C28 -> 0.013060365 | H28: 0 | I28: =H28/$C28 -> 0 | J28: 71 | K28: =J28/$C28 -> 0.00016835256 | L28: 114 | M28: =L28/$C28 -> 0.00027031257 | N28: 0 | O28: =N28/$C28 -> 0 | P28: 2030 | Q28: =P28/$C28 -> 0.0048134606 | R28: 1817 | S28: =R28/$C28 -> 0.0043084029 | T28: 0 | U28: =T28/$C28 -> 0 | W28: =V28/$C28 -> 0 | Y28: =X28/$C28 -> 0 | Z28: 385 | AA28: =Z28/$C28 -> 0.0009128977 | AB28: 0 | AC28: =AB28/$C28 -> 0 | AE28: =AD28/$C28 -> 0 | AG28: =AF28/$C28 -> 0 | AI28: =AH28/$C$3 -> 0 | AK28: =AJ28/$C28 -> 0 | AL28: 0 | AM28: =AL28/$C28 -> 0 | AN28: 1086 | AO28: =AN28/$C28 -> 0.0025750829 | AP28: 0 | AQ28: =AP28/$C28 -> 0 | AR28: 0 | AS28: =AR28/$C28 -> 0 | AT28: 5 | AU28: =AT28/$C28 -> 1.1855814e-05
A29: ERIO KDS ENGG. PVT. LTD. Howrah West Bengal | B29: June 2025 | C29: =D29+F29 -> 30784 | D29: 30425 | E29: =D29/C29 -> 0.9883381 | F29: 359 | G29: =F29/$C29 -> 0.011661902 | H29: 0 | I29: =H29/$C29 -> 0 | J29: 48 | K29: =J29/$C29 -> 0.0015592516 | L29: 45 | M29: =L29/$C29 -> 0.0014617983 | N29: 0 | O29: =N29/$C29 -> 0 | P29: 43 | Q29: =P29/$C29 -> 0.0013968295 | R29: 197 | S29: =R29/$C29 -> 0.0063994283 | T29: 0 | U29: =T29/$C29 -> 0 | W29: =V29/$C29 -> 0 | Y29: =X29/$C29 -> 0 | Z29: 0 | AA29: =Z29/$C29 -> 0 | AB29: 0 | AC29: =AB29/$C29 -> 0 | AE29: =AD29/$C29 -> 0 | AG29: =AF29/$C29 -> 0 | AI29: =AH29/$C$3 -> 0 | AK29: =AJ29/$C29 -> 0 | AL29: 4 | AM29: =AL29/$C29 -> 0.00012993763 | AN29: 22 | AO29: =AN29/$C29 -> 0.00071465696 | AP29: 0 | AQ29: =AP29/$C29 -> 0 | AR29: 0 | AS29: =AR29/$C29 -> 0 | AU29: =AT29/$C29 -> 0
A30: ERIO KDS ENGG. PVT. LTD. Howrah West Bengal | B30: July 2025 | C30: =D30+F30 -> 49717 | D30: 49025 | E30: =D30/C30 -> 0.98608122 | F30: 692 | G30: =F30/$C30 -> 0.01391878 | H30: 0 | I30: =H30/$C30 -> 0 | J30: 109 | K30: =J30/$C30 -> 0.002192409 | L30: 53 | M30: =L30/$C30 -> 0.0010660338 | N30: 0 | O30: =N30/$C30 -> 0 | P30: 0 | Q30: =P30/$C30 -> 0 | R30: 476 | S30: =R30/$C30 -> 0.0095741899 | T30: 0 | U30: =T30/$C30 -> 0 | W30: =V30/$C30 -> 0 | Y30: =X30/$C30 -> 0 | Z30: 0 | AA30: =Z30/$C30 -> 0 | AB30: 0 | AC30: =AB30/$C30 -> 0 | AE30: =AD30/$C30 -> 0 | AG30: =AF30/$C30 -> 0 | AI30: =AH30/$C$3 -> 0 | AK30: =AJ30/$C30 -> 0 | AL30: 5 | AM30: =AL30/$C30 -> 0.00010056922 | AN30: 49 | AO30: =AN30/$C30 -> 0.00098557837 | AP30: 0 | AQ30: =AP30/$C30 -> 0 | AR30: 0 | AS30: =AR30/$C30 -> 0 | AU30: =AT30/$C30 -> 0
A31: ERIO KDS ENGG. PVT. LTD. Howrah West Bengal | B31: August 2025 | C31: =D31+F31 -> 38729 | D31: 38338 | E31: =D31/C31 -> 0.98990421 | F31: 391 | G31: =F31/$C31 -> 0.010095794 | H31: 0 | I31: =H31/$C31 -> 0 | J31: 83 | K31: =J31/$C31 -> 0.0021430969 | L31: 33 | M31: =L31/$C31 -> 0.00085207467 | N31: 0 | O31: =N31/$C31 -> 0 | P31: 46 | Q31: =P31/$C31 -> 0.0011877405 | R31: 151 | S31: =R31/$C31 -> 0.0038988871 | T31: 0 | U31: =T31/$C31 -> 0 | W31: =V31/$C31 -> 0 | Y31: =X31/$C31 -> 0 | Z31: 0 | AA31: =Z31/$C31 -> 0 | AB31: 0 | AC31: =AB31/$C31 -> 0 | AE31: =AD31/$C31 -> 0 | AG31: =AF31/$C31 -> 0 | AI31: =AH31/$C$3 -> 0 | AK31: =AJ31/$C31 -> 0 | AL31: 0 | AM31: =AL31/$C31 -> 0 | AN31: 78 | AO31: =AN31/$C31 -> 0.0020139947 | AP31: 0 | AQ31: =AP31/$C31 -> 0 | AR31: 0 | AS31: =AR31/$C31 -> 0 | AU31: =AT31/$C31 -> 0
A32: ERIO KRISHNA INFRATECH Jharsuguda Odisha | B32: May 2025 | C32: =D32+F32 -> 101635 | D32: 101200 | E32: =D32/C32 -> 0.99571998 | F32: 435 | G32: =F32/$C32 -> 0.0042800216 | H32: 0 | I32: =H32/$C32 -> 0 | J32: 275 | K32: =J32/$C32 -> 0.0027057608 | L32: 0 | M32: =L32/$C32 -> 0 | N32: 0 | O32: =N32/$C32 -> 0 | P32: 101 | Q32: =P32/$C32 -> 0.00099375215 | R32: 44 | S32: =R32/$C32 -> 0.00043292173 | T32: 0 | U32: =T32/$C32 -> 0 | W32: =V32/$C32 -> 0 | Y32: =X32/$C32 -> 0 | Z32: 0 | AA32: =Z32/$C32 -> 0 | AB32: 0 | AC32: =AB32/$C32 -> 0 | AE32: =AD32/$C32 -> 0 | AG32: =AF32/$C32 -> 0 | AI32: =AH32/$C$3 -> 0 | AK32: =AJ32/$C32 -> 0 | AL32: 15 | AM32: =AL32/$C32 -> 0.00014758695 | AN32: 0 | AO32: =AN32/$C32 -> 0 | AP32: 0 | AQ32: =AP32/$C32 -> 0 | AR32: 0 | AS32: =AR32/$C32 -> 0 | AU32: =AT32/$C32 -> 0
A33: ERIO KRISHNA INFRATECH Jharsuguda Odisha | B33: June 2025 | C33: =D33+F33 -> 142851 | D33: 141702 | E33: =D33/C33 -> 0.99195665 | F33: 1149 | G33: =F33/$C33 -> 0.0080433459 | H33: 0 | I33: =H33/$C33 -> 0 | J33: 757 | K33: =J33/$C33 -> 0.0052992279 | L33: 0 | M33: =L33/$C33 -> 0 | N33: 0 | O33: =N33/$C33 -> 0 | P33: 189 | Q33: =P33/$C33 -> 0.0013230569 | R33: 162 | S33: =R33/$C33 -> 0.0011340488 | T33: 0 | U33: =T33/$C33 -> 0 | W33: =V33/$C33 -> 0 | Y33: =X33/$C33 -> 0 | Z33: 0 | AA33: =Z33/$C33 -> 0 | AB33: 0 | AC33: =AB33/$C33 -> 0 | AE33: =AD33/$C33 -> 0 | AG33: =AF33/$C33 -> 0 | AI33: =AH33/$C$3 -> 0 | AK33: =AJ33/$C33 -> 0 | AL33: 41 | AM33: =AL33/$C33 -> 0.00028701234 | AN33: 0 | AO33: =AN33/$C33 -> 0 | AP33: 0 | AQ33: =AP33/$C33 -> 0 | AR33: 0 | AS33: =AR33/$C33 -> 0 | AU33: =AT33/$C33 -> 0
A34: ERIO KRISHNA INFRATECH Jharsuguda Odisha | B34: July 2025 | C34: =D34+F34 -> 280351 | D34: 277567 | E34: =D34/C34 -> 0.99006959 | F34: 2784 | G34: =F34/$C34 -> 0.0099304087 | H34: 0 | I34: =H34/$C34 -> 0 | J34: 1581 | K34: =J34/$C34 -> 0.0056393592 | L34: 236 | M34: =L34/$C34 -> 0.00084180188 | N34: 0 | O34: =N34/$C34 -> 0 | P34: 425 | Q34: =P34/$C34 -> 0.0015159568 | R34: 321 | S34: =R34/$C34 -> 0.0011449932 | T34: 0 | U34: =T34/$C34 -> 0 | W34: =V34/$C34 -> 0 | Y34: =X34/$C34 -> 0 | Z34: 0 | AA34: =Z34/$C34 -> 0 | AB34: 0 | AC34: =AB34/$C34 -> 0 | AE34: =AD34/$C34 -> 0 | AG34: =AF34/$C34 -> 0 | AI34: =AH34/$C$3 -> 0 | AK34: =AJ34/$C34 -> 0 | AL34: 221 | AM34: =AL34/$C34 -> 0.00078829753 | AN34: 0 | AO34: =AN34/$C34 -> 0 | AP34: 0 | AQ34: =AP34/$C34 -> 0 | AR34: 0 | AS34: =AR34/$C34 -> 0 | AU34: =AT34/$C34 -> 0
A35: ERIO KRISHNA INFRATECH Jharsuguda Odisha | B35: August 2025 | C35: =D35+F35 -> 201251 | D35: 199170 | E35: =D35/C35 -> 0.98965968 | F35: 2081 | G35: =F35/$C35 -> 0.010340321 | H35: 0 | I35: =H35/$C35 -> 0 | J35: 1501 | K35: =J35/$C35 -> 0.007458348 | L35: 184 | M35: =L35/$C35 -> 0.00091428117 | N35: 0 | O35: =N35/$C35 -> 0 | P35: 156 | Q35: =P35/$C35 -> 0.00077515143 | R35: 68 | S35: =R35/$C35 -> 0.00033788652 | T35: 0 | U35: =T35/$C35 -> 0 | W35: =V35/$C35 -> 0 | Y35: =X35/$C35 -> 0 | Z35: 0 | AA35: =Z35/$C35 -> 0 | AB35: 0 | AC35: =AB35/$C35 -> 0 | AE35: =AD35/$C35 -> 0 | AG35: =AF35/$C35 -> 0 | AI35: =AH35/$C$3 -> 0 | AK35: =AJ35/$C35 -> 0 | AL35: 172 | AM35: =AL35/$C35 -> 0.00085465414 | AN35: 0 | AO35: =AN35/$C35 -> 0 | AP35: 0 | AQ35: =AP35/$C35 -> 0 | AR35: 0 | AS35: =AR35/$C35 -> 0 | AU35: =AT35/$C35 -> 0
A36: ERIO KRISHNA INFRATECH Jharsuguda Odisha | B36: September 2025 | C36: =D36+F36 -> 205140 | D36: 203166 | E36: =D36/C36 -> 0.9903773 | F36: 1974 | G36: =F36/$C36 -> 0.0096226967 | H36: 0 | I36: =H36/$C36 -> 0 | J36: 927 | K36: =J36/$C36 -> 0.0045188652 | L36: 271 | M36: =L36/$C36 -> 0.001321049 | N36: 0 | O36: =N36/$C36 -> 0 | P36: 165 | Q36: =P36/$C36 -> 0.00080432875 | R36: 211 | S36: =R36/$C36 -> 0.0010285659 | T36: 0 | U36: =T36/$C36 -> 0 | W36: =V36/$C36 -> 0 | Y36: =X36/$C36 -> 0 | Z36: 0 | AA36: =Z36/$C36 -> 0 | AB36: 0 | AC36: =AB36/$C36 -> 0 | AE36: =AD36/$C36 -> 0 | AG36: =AF36/$C36 -> 0 | AI36: =AH36/$C$3 -> 0 | AK36: =AJ36/$C36 -> 0 | AL36: 90 | AM36: =AL36/$C36 -> 0.00043872477 | AN36: 270 | AO36: =AN36/$C36 -> 0.0013161743 | AP36: 0 | AQ36: =AP36/$C36 -> 0 | AR36: 40 | AS36: =AR36/$C36 -> 0.00019498879 | AU36: =AT36/$C36 -> 0
A37: ERIO KRISHNA INFRATECH Jharsuguda Odisha | B37: October 2025 | C37: =D37+F37 -> 155794 | D37: 154280 | E37: =D37/C37 -> 0.99028204 | F37: 1514 | G37: =F37/$C37 -> 0.0097179609 | H37: 0 | I37: =H37/$C37 -> 0 | J37: 698 | K37: =J37/$C37 -> 0.0044802752 | L37: 272 | M37: =L37/$C37 -> 0.0017458952 | N37: 0 | O37: =N37/$C37 -> 0 | P37: 284 | Q37: =P37/$C37 -> 0.00182292 | R37: 54 | S37: =R37/$C37 -> 0.00034661155 | T37: 0 | U37: =T37/$C37 -> 0 | W37: =V37/$C37 -> 0 | Y37: =X37/$C37 -> 0 | Z37: 0 | AA37: =Z37/$C37 -> 0 | AB37: 0 | AC37: =AB37/$C37 -> 0 | AE37: =AD37/$C37 -> 0 | AG37: =AF37/$C37 -> 0 | AI37: =AH37/$C$3 -> 0 | AK37: =AJ37/$C37 -> 0 | AL37: 41 | AM37: =AL37/$C37 -> 0.00026316803 | AN37: 165 | AO37: =AN37/$C37 -> 0.0010590909 | AP37: 0 | AQ37: =AP37/$C37 -> 0 | AR37: 0 | AS37: =AR37/$C37 -> 0 | AU37: =AT37/$C37 -> 0
A38: ERIO KRISHNA INFRATECH Jharsuguda Odisha | B38: Novemeber 2025 | C38: =D38+F38 -> 175431 | D38: 173590 | E38: =D38/C38 -> 0.98950585 | F38: 1841 | G38: =F38/$C38 -> 0.010494154 | H38: 0 | I38: =H38/$C38 -> 0 | J38: 965 | K38: =J38/$C38 -> 0.0055007382 | L38: 427 | M38: =L38/$C38 -> 0.0024340054 | N38: 0 | O38: =N38/$C38 -> 0 | P38: 146 | Q38: =P38/$C38 -> 0.00083223604 | R38: 96 | S38: =R38/$C38 -> 0.00054722369 | T38: 0 | U38: =T38/$C38 -> 0 | W38: =V38/$C38 -> 0 | Y38: =X38/$C38 -> 0 | Z38: 0 | AA38: =Z38/$C38 -> 0 | AB38: 0 | AC38: =AB38/$C38 -> 0 | AE38: =AD38/$C38 -> 0 | AG38: =AF38/$C38 -> 0 | AI38: =AH38/$C$3 -> 0 | AK38: =AJ38/$C38 -> 0 | AL38: 81 | AM38: =AL38/$C38 -> 0.00046171999 | AN38: 126 | AO38: =AN38/$C38 -> 0.0007182311 | AP38: 0 | AQ38: =AP38/$C38 -> 0 | AR38: 0 | AS38: =AR38/$C38 -> 0 | AU38: =AT38/$C38 -> 0
A39: ERIO KSE ELECTRICALS PVT LTD Howrah West Bengal | B39: May 2025 | C39: =D39+F39 -> 253914 | D39: 253289 | E39: =D39/C39 -> 0.99753854 | F39: 625 | G39: =F39/$C39 -> 0.0024614633 | H39: 58 | I39: =H39/$C39 -> 0.0002284238 | J39: 23 | K39: =J39/$C39 -> 9.0581851e-05 | L39: 39 | M39: =L39/$C39 -> 0.00015359531 | N39: 0 | O39: =N39/$C39 -> 0 | P39: 27 | Q39: =P39/$C39 -> 0.00010633522 | R39: 48 | S39: =R39/$C39 -> 0.00018904038 | T39: 29 | U39: =T39/$C39 -> 0.0001142119 | W39: =V39/$C39 -> 0 | Y39: =X39/$C39 -> 0 | Z39: 66 | AA39: =Z39/$C39 -> 0.00025993053 | AB39: 0 | AC39: =AB39/$C39 -> 0 | AE39: =AD39/$C39 -> 0 | AG39: =AF39/$C39 -> 0 | AI39: =AH39/$C$3 -> 0 | AK39: =AJ39/$C39 -> 0 | AL39: 0 | AM39: =AL39/$C39 -> 0 | AN39: 149 | AO39: =AN39/$C39 -> 0.00058681286 | AP39: 32 | AQ39: =AP39/$C39 -> 0.00012602692 | AR39: 154 | AS39: =AR39/$C39 -> 0.00060650456 | AU39: =AT39/$C39 -> 0
A40: ERIO KSE ELECTRICALS PVT LTD Howrah West Bengal | B40: June 2025 | C40: =D40+F40 -> 276461 | D40: 273897 | E40: =D40/C40 -> 0.99072564 | F40: 2564 | G40: =F40/$C40 -> 0.0092743642 | H40: 288 | I40: =H40/$C40 -> 0.0010417383 | J40: 170 | K40: =J40/$C40 -> 0.00061491494 | L40: 94 | M40: =L40/$C40 -> 0.00034001179 | N40: 0 | O40: =N40/$C40 -> 0 | P40: 426 | Q40: =P40/$C40 -> 0.0015409045 | R40: 582 | S40: =R40/$C40 -> 0.0021051794 | T40: 170 | U40: =T40/$C40 -> 0.00061491494 | W40: =V40/$C40 -> 0 | Y40: =X40/$C40 -> 0 | Z40: 98 | AA40: =Z40/$C40 -> 0.00035448038 | AB40: 0 | AC40: =AB40/$C40 -> 0 | AE40: =AD40/$C40 -> 0 | AG40: =AF40/$C40 -> 0 | AI40: =AH40/$C$3 -> 0 | AK40: =AJ40/$C40 -> 0 | AL40: 0 | AM40: =AL40/$C40 -> 0 | AN40: 166 | AO40: =AN40/$C40 -> 0.00060044636 | AP40: 108 | AQ40: =AP40/$C40 -> 0.00039065185 | AR40: 462 | AS40: =AR40/$C40 -> 0.0016711218 | AU40: =AT40/$C40 -> 0
... A53: ERIO LNVS INFRA PVT. LTD Tatanagar Jharkhand | B53: Novemeber 2025 | C53: =D53+F53 -> 124745 | D53: 123063 | E53: =D53/C53 -> 0.98651649 | F53: 1682 | G53: =F53/$C53 -> 0.013483506 | H53: 385 | I53: =H53/$C53 -> 0.003086296 | J53: 412 | K53: =J53/$C53 -> 0.0033027376 | L53: 251 | M53: =L53/$C53 -> 0.0020121047 | N53: 0 | O53: =N53/$C53 -> 0 | P53: 505 | Q53: =P53/$C53 -> 0.0040482584 | R53: 104 | S53: =R53/$C53 -> 0.00083370075 | T53: 17 | U53: =T53/$C53 -> 0.00013627801 | W53: =V53/$C53 -> 0 | Y53: =X53/$C53 -> 0 | Z53: 0 | AA53: =Z53/$C53 -> 0 | AB53: 0 | AC53: =AB53/$C53 -> 0 | AE53: =AD53/$C53 -> 0 | AG53: =AF53/$C53 -> 0 | AI53: =AH53/$C$3 -> 0 | AK53: =AJ53/$C53 -> 0 | AL53: 0 | AM53: =AL53/$C53 -> 0 | AN53: 0 | AO53: =AN53/$C53 -> 0 | AP53: 0 | AQ53: =AP53/$C53 -> 0 | AR53: 8 | AS53: =AR53/$C53 -> 6.4130827e-05 | AU53: =AT53/$C53 -> 0
A54: ERIO Surya Alloys Industries Limited Durgapur West Bengal | B54: April 2025 | C54: 923540 | D54: 917790 | E54: =D54/C54 -> 0.99377396 | F54: 5750 | G54: =F54/$C54 -> 0.0062260433 | H54: 170 | I54: =H54/$C54 -> 0.00018407432 | J54: 1058 | K54: =J54/$C54 -> 0.001145592 | L54: 499 | M54: =L54/$C54 -> 0.00054031228 | N54: 0 | O54: =N54/$C54 -> 0 | P54: 114 | Q54: =P54/$C54 -> 0.00012343808 | R54: 1548 | S54: =R54/$C54 -> 0.0016761591 | T54: 0 | U54: =T54/$C54 -> 0 | W54: =V54/$C54 -> 0 | Y54: =X54/$C54 -> 0 | Z54: 1920 | AA54: =Z54/$C54 -> 0.0020789571 | AB54: 90 | AC54: =AB54/$C54 -> 9.7451112e-05 | AE54: =AD54/$C54 -> 0 | AG54: =AF54/$C54 -> 0 | AI54: =AH54/$C$3 -> 0 | AK54: =AJ54/$C54 -> 0 | AL54: 83 | AM54: =AL54/$C54 -> 8.9871581e-05 | AN54: 255 | AO54: =AN54/$C54 -> 0.00027611148 | AP54: 13 | AQ54: =AP54/$C54 -> 1.4076272e-05 | AR54: 0 | AS54: =AR54/$C54 -> 0 | AU54: =AT54/$C54 -> 0
A55: ERIO Surya Alloys Industries Limited Durgapur West Bengal | B55: May 2025 | C55: 1220892 | D55: 1216612 | E55: =D55/C55 -> 0.99649437 | F55: 4280 | G55: =F55/$C55 -> 0.0035056336 | H55: 112 | I55: =H55/$C55 -> 9.1736206e-05 | J55: 158 | K55: =J55/$C55 -> 0.00012941358 | L55: 889 | M55: =L55/$C55 -> 0.00072815614 | N55: 0 | O55: =N55/$C55 -> 0 | P55: 440 | Q55: =P55/$C55 -> 0.00036039224 | R55: 897 | S55: =R55/$C55 -> 0.00073470872 | T55: 0 | U55: =T55/$C55 -> 0 | W55: =V55/$C55 -> 0 | Y55: =X55/$C55 -> 0 | Z55: 667 | AA55: =Z55/$C55 -> 0.00054632187 | AB55: 0 | AC55: =AB55/$C55 -> 0 | AE55: =AD55/$C55 -> 0 | AG55: =AF55/$C55 -> 0 | AI55: =AH55/$C$3 -> 0 | AK55: =AJ55/$C55 -> 0 | AL55: 89 | AM55: =AL55/$C55 -> 7.2897521e-05 | AN55: 956 | AO55: =AN55/$C55 -> 0.00078303404 | AP55: 32 | AQ55: =AP55/$C55 -> 2.6210345e-05 | AR55: 40 | AS55: =AR55/$C55 -> 3.2762931e-05 | AU55: =AT55/$C55 -> 0
A56: ERIO Surya Alloys Industries Limited Durgapur West Bengal | B56: June 2025 | C56: =D56+F56 -> 1534702 | D56: 1519600 | E56: =D56/C56 -> 0.99015965 | F56: 15102 | G56: =F56/$C56 -> 0.0098403469 | H56: 265 | I56: =H56/$C56 -> 0.00017267196 | J56: 2660 | K56: =J56/$C56 -> 0.0017332355 | L56: 1162 | M56: =L56/$C56 -> 0.00075715025 | N56: 0 | O56: =N56/$C56 -> 0 | P56: 1828 | Q56: =P56/$C56 -> 0.0011911107 | R56: 4956 | S56: =R56/$C56 -> 0.0032292914 | T56: 0 | U56: =T56/$C56 -> 0 | W56: =V56/$C56 -> 0 | Y56: =X56/$C56 -> 0 | Z56: 976 | AA56: =Z56/$C56 -> 0.00063595408 | AB56: 0 | AC56: =AB56/$C56 -> 0 | AE56: =AD56/$C56 -> 0 | AG56: =AF56/$C56 -> 0 | AI56: =AH56/$C$3 -> 0 | AK56: =AJ56/$C56 -> 0 | AL56: 65 | AM56: =AL56/$C56 -> 4.2353499e-05 | AN56: 3065 | AO56: =AN56/$C56 -> 0.0019971304 | AP56: 66 | AQ56: =AP56/$C56 -> 4.3005092e-05 | AR56: 59 | AS56: =AR56/$C56 -> 3.8443945e-05 | AU56: =AT56/$C56 -> 0
A57: ERIO Surya Alloys Industries Limited Durgapur West Bengal | B57: July 2025 | C57: =D57+F57 -> 2285388 | D57: 2252783 | E57: =D57/C57 -> 0.98573328 | F57: 32605 | G57: =F57/$C57 -> 0.014266724 | H57: 2176 | I57: =H57/$C57 -> 0.00095213592 | J57: 3746 | K57: =J57/$C57 -> 0.001639109 | L57: 2594 | M57: =L57/$C57 -> 0.001135037 | N57: 0 | O57: =N57/$C57 -> 0 | P57: 3505 | Q57: =P57/$C57 -> 0.0015336564 | R57: 9664 | S57: =R57/$C57 -> 0.0042286036 | T57: 0 | U57: =T57/$C57 -> 0 | W57: =V57/$C57 -> 0 | Y57: =X57/$C57 -> 0 | Z57: 865 | AA57: =Z57/$C57 -> 0.00037849153 | AB57: 0 | AC57: =AB57/$C57 -> 0 | AE57: =AD57/$C57 -> 0 | AG57: =AF57/$C57 -> 0 | AI57: =AH57/$C$3 -> 0 | AK57: =AJ57/$C57 -> 0 | AL57: 1059 | AM57: =AL57/$C57 -> 0.00046337865 | AN57: 7205 | AO57: =AN57/$C57 -> 0.0031526375 | AP57: 1245 | AQ57: =AP57/$C57 -> 0.00054476527 | AR57: 546 | AS57: =AR57/$C57 -> 0.0002389091 | AU57: =AT57/$C57 -> 0
A58: ERIO Surya Alloys Industries Limited Durgapur West Bengal | B58: August 2025 | C58: =D58+F58 -> 1925013 | D58: 1892137 | E58: =D58/C58 -> 0.98292167 | F58: 32876 | G58: =F58/$C58 -> 0.017078326 | H58: 599 | I58: =H58/$C58 -> 0.00031116673 | J58: 5316 | K58: =J58/$C58 -> 0.0027615398 | L58: 2898 | M58: =L58/$C58 -> 0.0015054444 | N58: 0 | O58: =N58/$C58 -> 0 | P58: 5097 | Q58: =P58/$C58 -> 0.0026477743 | R58: 8188 | S58: =R58/$C58 -> 0.0042534778 | T58: 0 | U58: =T58/$C58 -> 0 | W58: =V58/$C58 -> 0 | Y58: =X58/$C58 -> 0 | Z58: 754 | AA58: =Z58/$C58 -> 0.00039168567 | AB58: 0 | AC58: =AB58/$C58 -> 0 | AE58: =AD58/$C58 -> 0 | AG58: =AF58/$C58 -> 0 | AI58: =AH58/$C$3 -> 0 | AK58: =AJ58/$C58 -> 0 | AL58: 210 | AM58: =AL58/$C58 -> 0.00010909017 | AN58: 9648 | AO58: =AN58/$C58 -> 0.0050119142 | AP58: 166 | AQ58: =AP58/$C58 -> 8.6233184e-05 | AR58: 0 | AS58: =AR58/$C58 -> 0 | AU58: =AT58/$C58 -> 0
A59: ERIO Surya Alloys Industries Limited Durgapur West Bengal | B59: September 2025 | C59: =D59+F59 -> 2114630 | D59: 2085582 | E59: =D59/C59 -> 0.98626332 | F59: 29048 | G59: =F59/$C59 -> 0.013736682 | H59: 725 | I59: =H59/$C59 -> 0.00034284958 | J59: 3319 | K59: =J59/$C59 -> 0.0015695417 | L59: 1700 | M59: =L59/$C59 -> 0.00080392314 | N59: 0 | O59: =N59/$C59 -> 0 | P59: 4894 | Q59: =P59/$C59 -> 0.0023143529 | R59: 6852 | S59: =R59/$C59 -> 0.0032402832 | T59: 0 | U59: =T59/$C59 -> 0 | W59: =V59/$C59 -> 0 | Y59: =X59/$C59 -> 0 | Z59: 304 | AA59: =Z59/$C59 -> 0.00014376037 | AB59: 0 | AC59: =AB59/$C59 -> 0 | AE59: =AD59/$C59 -> 0 | AG59: =AF59/$C59 -> 0 | AI59: =AH59/$C$3 -> 0 | AK59: =AJ59/$C59 -> 0 | AL59: 171 | AM59: =AL59/$C59 -> 8.086521e-05 | AN59: 10501 | AO59: =AN59/$C59 -> 0.0049658806 | AP59: 582 | AQ59: =AP59/$C59 -> 0.00027522545 | AR59: 0 | AS59: =AR59/$C59 -> 0 | AU59: =AT59/$C59 -> 0
A60: ERIO Surya Alloys Industries Limited Durgapur West Bengal | B60: October 2025 | C60: =D60+F60 -> 1837714 | D60: 1810723 | E60: =D60/C60 -> 0.98531273 | F60: 26991 | G60: =F60/$C60 -> 0.014687269 | H60: 608 | I60: =H60/$C60 -> 0.00033084582 | J60: 3986 | K60: =J60/$C60 -> 0.0021689991 | L60: 1503 | M60: =L60/$C60 -> 0.00081786393 | N60: 0 | O60: =N60/$C60 -> 0 | P60: 3324 | Q60: =P60/$C60 -> 0.0018087689 | R60: 7430 | S60: =R60/$C60 -> 0.0040430665 | T60: 0 | U60: =T60/$C60 -> 0 | W60: =V60/$C60 -> 0 | Y60: =X60/$C60 -> 0 | Z60: 408 | AA60: =Z60/$C60 -> 0.00022201496 | AB60: 0 | AC60: =AB60/$C60 -> 0 | AE60: =AD60/$C60 -> 0 | AG60: =AF60/$C60 -> 0 | AI60: =AH60/$C$3 -> 0 | AK60: =AJ60/$C60 -> 0 | AL60: 459 | AM60: =AL60/$C60 -> 0.00024976683 | AN60: 8275 | AO60: =AN60/$C60 -> 0.0045028769 | AP60: 864 | AQ60: =AP60/$C60 -> 0.00047014933 | AR60: 134 | AS60: =AR60/$C60 -> 7.2916678e-05 | AU60: =AT60/$C60 -> 0
A61: ERIO Surya Alloys Industries Limited Durgapur West Bengal | B61: Novemeber 2025 | C61: =D61+F61 -> 1686431 | D61: 1660652 | E61: =D61/C61 -> 0.98471387 | F61: 25779 | G61: =F61/$C61 -> 0.015286128 | H61: 838 | I61: =H61/$C61 -> 0.00049690737 | J61: 1480 | K61: =J61/$C61 -> 0.00087759298 | L61: 1855 | M61: =L61/$C61 -> 0.0010999561 | N61: 0 | O61: =N61/$C61 -> 0 | P61: 3448 | Q61: =P61/$C61 -> 0.0020445544 | R61: 7563 | S61: =R61/$C61 -> 0.0044846187 | T61: 0 | U61: =T61/$C61 -> 0 | W61: =V61/$C61 -> 0 | Y61: =X61/$C61 -> 0 | Z61: 245 | AA61: =Z61/$C61 -> 0.00014527722 | AB61: 0 | AC61: =AB61/$C61 -> 0 | AE61: =AD61/$C61 -> 0 | AG61: =AF61/$C61 -> 0 | AI61: =AH61/$C$3 -> 0 | AK61: =AJ61/$C61 -> 0 | AL61: 1230 | AM61: =AL61/$C61 -> 0.00072935092 | AN61: 7946 | AO61: =AN61/$C61 -> 0.0047117255 | AP61: 786 | AQ61: =AP61/$C61 -> 0.00046607303 | AR61: 388 | AS61: =AR61/$C61 -> 0.00023007167 | AU61: =AT61/$C61 -> 0
A62: ERIO TECHMA ENGG. Howrah West Bengal | B62: July 2025 | C62: =D62+F62 -> 29666 | D62: 29081 | E62: =D62/C62 -> 0.98028046 | F62: 585 | G62: =F62/$C62 -> 0.019719544 | H62: 0 | I62: =H62/$C62 -> 0 | J62: 66 | K62: =J62/$C62 -> 0.0022247691 | L62: 138 | M62: =L62/$C62 -> 0.0046517899 | N62: 0 | O62: =N62/$C62 -> 0 | P62: 112 | Q62: =P62/$C62 -> 0.0037753657 | R62: 194 | S62: =R62/$C62 -> 0.0065394728 | T62: 0 | U62: =T62/$C62 -> 0 | W62: =V62/$C62 -> 0 | Y62: =X62/$C62 -> 0 | Z62: 0 | AA62: =Z62/$C62 -> 0 | AB62: 0 | AC62: =AB62/$C62 -> 0 | AE62: =AD62/$C62 -> 0 | AG62: =AF62/$C62 -> 0 | AI62: =AH62/$C$3 -> 0 | AK62: =AJ62/$C62 -> 0 | AL62: 43 | AM62: =AL62/$C62 -> 0.0014494708 | AN62: 32 | AO62: =AN62/$C62 -> 0.0010786759 | AP62: 0 | AQ62: =AP62/$C62 -> 0 | AR62: 0 | AS62: =AR62/$C62 -> 0 | AU62: =AT62/$C62 -> 0
A63: ERIO TECHMA ENGG. Howrah West Bengal | B63: August 2025 | C63: =D63+F63 -> 69663 | D63: 68985 | E63: =D63/C63 -> 0.99026743 | F63: 678 | G63: =F63/$C63 -> 0.0097325697 | H63: 0 | I63: =H63/$C63 -> 0 | J63: 120 | K63: =J63/$C63 -> 0.0017225787 | L63: 100 | M63: =L63/$C63 -> 0.0014354823 | N63: 0 | O63: =N63/$C63 -> 0 | P63: 145 | Q63: =P63/$C63 -> 0.0020814493 | R63: 84 | S63: =R63/$C63 -> 0.0012058051 | T63: 0 | U63: =T63/$C63 -> 0 | W63: =V63/$C63 -> 0 | Y63: =X63/$C63 -> 0 | Z63: 0 | AA63: =Z63/$C63 -> 0 | AB63: 0 | AC63: =AB63/$C63 -> 0 | AE63: =AD63/$C63 -> 0 | AG63: =AF63/$C63 -> 0 | AI63: =AH63/$C$3 -> 0 | AK63: =AJ63/$C63 -> 0 | AL63: 51 | AM63: =AL63/$C63 -> 0.00073209595 | AN63: 172 | AO63: =AN63/$C63 -> 0.0024690295 | AP63: 0 | AQ63: =AP63/$C63 -> 0 | AR63: 6 | AS63: =AR63/$C63 -> 8.6128935e-05 | AU63: =AT63/$C63 -> 0
A64: ERIO TECHMA ENGG. Howrah West Bengal | B64: September 2025 | C64: =D64+F64 -> 121732 | D64: 120515 | E64: =D64/C64 -> 0.99000263 | F64: 1217 | G64: =F64/$C64 -> 0.0099973713 | H64: 0 | I64: =H64/$C64 -> 0 | J64: 140 | K64: =J64/$C64 -> 0.0011500674 | L64: 66 | M64: =L64/$C64 -> 0.00054217461 | N64: 0 | O64: =N64/$C64 -> 0 | P64: 94 | Q64: =P64/$C64 -> 0.00077218809 | R64: 127 | S64: =R64/$C64 -> 0.0010432754 | T64: 0 | U64: =T64/$C64 -> 0 | W64: =V64/$C64 -> 0 | Y64: =X64/$C64 -> 0 | Z64: 148 | AA64: =Z64/$C64 -> 0.0012157855 | AB64: 0 | AC64: =AB64/$C64 -> 0 | AE64: =AD64/$C64 -> 0 | AG64: =AF64/$C64 -> 0 | AI64: =AH64/$C$3 -> 0 | AK64: =AJ64/$C64 -> 0 | AL64: 53 | AM64: =AL64/$C64 -> 0.00043538264 | AN64: 484 | AO64: =AN64/$C64 -> 0.0039759472 | AP64: 0 | AQ64: =AP64/$C64 -> 0 | AR64: 105 | AS64: =AR64/$C64 -> 0.00086255052 | AU64: =AT64/$C64 -> 0
A65: ERIO TECHMA ENGG. Howrah West Bengal | B65: October 2025 | C65: =D65+F65 -> 52491 | D65: 51750 | E65: =D65/C65 -> 0.98588329 | F65: 741 | G65: =F65/$C65 -> 0.014116706 | H65: 0 | I65: =H65/$C65 -> 0 | J65: 79 | K65: =J65/$C65 -> 0.0015050199 | L65: 77 | M65: =L65/$C65 -> 0.0014669181 | N65: 0 | O65: =N65/$C65 -> 0 | P65: 129 | Q65: =P65/$C65 -> 0.0024575642 | R65: 155 | S65: =R65/$C65 -> 0.0029528872 | T65: 0 | U65: =T65/$C65 -> 0 | W65: =V65/$C65 -> 0 | Y65: =X65/$C65 -> 0 | Z65: 110 | AA65: =Z65/$C65 -> 0.0020955973 | AB65: 0 | AC65: =AB65/$C65 -> 0 | AE65: =AD65/$C65 -> 0 | AG65: =AF65/$C65 -> 0 | AI65: =AH65/$C$3 -> 0 | AK65: =AJ65/$C65 -> 0 | AL65: 21 | AM65: =AL65/$C65 -> 0.00040006858 | AN65: 152 | AO65: =AN65/$C65 -> 0.0028957345 | AP65: 0 | AQ65: =AP65/$C65 -> 0 | AR65: 18 | AS65: =AR65/$C65 -> 0.00034291593 | AU65: =AT65/$C65 -> 0
A66: ERIO UTKARSH INDIA LIMITED Howrah West Bengal | B66: May 2025 | C66: =D66+F66 -> 16537 | D66: 16500 | E66: =D66/C66 -> 0.99776259 | F66: 37 | G66: =F66/$C66 -> 0.002237407 | H66: 0 | I66: =H66/$C66 -> 0 | J66: 0 | K66: =J66/$C66 -> 0 | L66: 0 | M66: =L66/$C66 -> 0 | N66: 0 | O66: =N66/$C66 -> 0 | P66: 2 | Q66: =P66/$C66 -> 0.00012094092 | R66: 0 | S66: =R66/$C66 -> 0 | T66: 0 | U66: =T66/$C66 -> 0 | W66: =V66/$C66 -> 0 | Y66: =X66/$C66 -> 0 | Z66: 0 | AA66: =Z66/$C66 -> 0 | AB66: 0 | AC66: =AB66/$C66 -> 0 | AE66: =AD66/$C66 -> 0 | AG66: =AF66/$C66 -> 0 | AI66: =AH66/$C$3 -> 0 | AK66: =AJ66/$C66 -> 0 | AL66: 0 | AM66: =AL66/$C66 -> 0 | AN66: 0 | AO66: =AN66/$C66 -> 0 | AP66: 0 | AQ66: =AP66/$C66 -> 0 | AR66: 35 | AS66: =AR66/$C66 -> 0.0021164661 | AU66: =AT66/$C66 -> 0
A67: ERIO UTKARSH INDIA LIMITED Howrah West Bengal | B67: June 2025 | C67: =D67+F67 -> 83437 | D67: 82505 | E67: =D67/C67 -> 0.9888299 | F67: 932 | G67: =F67/$C67 -> 0.011170104 | H67: 166 | I67: =H67/$C67 -> 0.001989525 | J67: 65 | K67: =J67/$C67 -> 0.00077903089 | L67: 12 | M67: =L67/$C67 -> 0.00014382109 | N67: 0 | O67: =N67/$C67 -> 0 | P67: 93 | Q67: =P67/$C67 -> 0.0011146134 | R67: 101 | S67: =R67/$C67 -> 0.0012104941 | T67: 0 | U67: =T67/$C67 -> 0 | W67: =V67/$C67 -> 0 | Y67: =X67/$C67 -> 0 | Z67: 0 | AA67: =Z67/$C67 -> 0 | AB67: 0 | AC67: =AB67/$C67 -> 0 | AE67: =AD67/$C67 -> 0 | AG67: =AF67/$C67 -> 0 | AI67: =AH67/$C$3 -> 0 | AK67: =AJ67/$C67 -> 0 | AL67: 0 | AM67: =AL67/$C67 -> 0 | AN67: 29 | AO67: =AN67/$C67 -> 0.00034756763 | AP67: 0 | AQ67: =AP67/$C67 -> 0 | AR67: 466 | AS67: =AR67/$C67 -> 0.0055850522 | AU67: =AT67/$C67 -> 0
... A72: ERIO UTKARSH INDIA LIMITED Howrah West Bengal | B72: Novemeber 2025 | C72: =D72+F72 -> 122296 | D72: 117164 | E72: =D72/C72 -> 0.95803624 | F72: 5132 | G72: =F72/$C72 -> 0.04196376 | H72: 120 | I72: =H72/$C72 -> 0.00098122588 | J72: 80 | K72: =J72/$C72 -> 0.00065415059 | L72: 64 | M72: =L72/$C72 -> 0.00052332047 | N72: 0 | O72: =N72/$C72 -> 0 | P72: 215 | Q72: =P72/$C72 -> 0.0017580297 | R72: 298 | S72: =R72/$C72 -> 0.0024367109 | T72: 0 | U72: =T72/$C72 -> 0 | W72: =V72/$C72 -> 0 | Y72: =X72/$C72 -> 0 | Z72: 3990 | AA72: =Z72/$C72 -> 0.03262576 | AB72: 0 | AC72: =AB72/$C72 -> 0 | AE72: =AD72/$C72 -> 0 | AG72: =AF72/$C72 -> 0 | AI72: =AH72/$C$3 -> 0 | AK72: =AJ72/$C72 -> 0 | AL72: 0 | AM72: =AL72/$C72 -> 0 | AN72: 312 | AO72: =AN72/$C72 -> 0.0025511873 | AP72: 0 | AQ72: =AP72/$C72 -> 0 | AR72: 53 | AS72: =AR72/$C72 -> 0.00043337476 | AU72: =AT72/$C72 -> 0
A73: NRIO Adinath Industries Bhiwadi Haryana | B73: April 2025 | C73: 122517 | D73: =C73-R73-J73-L73-P73-AB73-AR73-AL73 -> 122421 | E73: =D73/C73 -> 0.99921644 | F73: =C73-D73 -> 96 | G73: =F73/$C73 -> 0.00078356473 | I73: =H73/$C73 -> 0 | J73: 43 | K73: =J73/$C73 -> 0.0003509717 | L73: 5 | M73: =L73/$C73 -> 4.0810663e-05 | N73: 0 | O73: =N73/$C73 -> 0 | P73: 0 | Q73: =P73/$C73 -> 0 | R73: 0 | S73: =R73/$C73 -> 0 | U73: =T73/$C73 -> 0 | W73: =V73/$C73 -> 0 | Y73: =X73/$C73 -> 0 | AA73: =Z73/$C73 -> 0 | AB73: 48 | AC73: =AB73/$C73 -> 0.00039178236 | AE73: =AD73/$C73 -> 0 | AG73: =AF73/$C73 -> 0 | AI73: =AH73/$C$3 -> 0 | AK73: =AJ73/$C73 -> 0 | AL73: 0 | AM73: =AL73/$C73 -> 0 | AO73: =AN73/$C73 -> 0 | AQ73: =AP73/$C73 -> 0 | AR73: 0 | AS73: =AR73/$C73 -> 0 | AU73: =AT73/$C73 -> 0
A74: NRIO Adinath Industries Bhiwadi Haryana | B74: May 2025 | C74: 137207 | D74: =C74-R74-J74-L74-P74-AB74-AR74-AL74 -> 137102 | E74: =D74/C74 -> 0.99923473 | F74: =C74-D74 -> 105 | G74: =F74/$C74 -> 0.00076526708 | I74: =H74/$C74 -> 0 | J74: 48 | K74: =J74/$C74 -> 0.00034983638 | L74: 0 | M74: =L74/$C74 -> 0 | N74: 0 | O74: =N74/$C74 -> 0 | P74: 0 | Q74: =P74/$C74 -> 0 | R74: 0 | S74: =R74/$C74 -> 0 | U74: =T74/$C74 -> 0 | W74: =V74/$C74 -> 0 | Y74: =X74/$C74 -> 0 | AA74: =Z74/$C74 -> 0 | AB74: 57 | AC74: =AB74/$C74 -> 0.0004154307 | AE74: =AD74/$C74 -> 0 | AG74: =AF74/$C74 -> 0 | AI74: =AH74/$C$3 -> 0 | AK74: =AJ74/$C74 -> 0 | AL74: 0 | AM74: =AL74/$C74 -> 0 | AO74: =AN74/$C74 -> 0 | AQ74: =AP74/$C74 -> 0 | AR74: 0 | AS74: =AR74/$C74 -> 0 | AU74: =AT74/$C74 -> 0
A75: NRIO Adinath Industries Bhiwadi Haryana | B75: June 2025 | C75: 165193 | D75: =C75-R75-J75-L75-P75-AB75-AR75-AL75 -> 164635 | E75: =D75/C75 -> 0.99662213 | F75: =C75-D75 -> 558 | G75: =F75/$C75 -> 0.0033778671 | I75: =H75/$C75 -> 0 | J75: 121 | K75: =J75/$C75 -> 0.00073247656 | L75: 107 | M75: =L75/$C75 -> 0.0006477272 | N75: 0 | O75: =N75/$C75 -> 0 | P75: 32 | Q75: =P75/$C75 -> 0.00019371281 | R75: 30 | S75: =R75/$C75 -> 0.00018160576 | U75: =T75/$C75 -> 0 | W75: =V75/$C75 -> 0 | Y75: =X75/$C75 -> 0 | AA75: =Z75/$C75 -> 0 | AB75: 100 | AC75: =AB75/$C75 -> 0.00060535253 | AE75: =AD75/$C75 -> 0 | AG75: =AF75/$C75 -> 0 | AI75: =AH75/$C$3 -> 0 | AK75: =AJ75/$C75 -> 0 | AL75: 0 | AM75: =AL75/$C75 -> 0 | AO75: =AN75/$C75 -> 0 | AQ75: =AP75/$C75 -> 0 | AR75: 168 | AS75: =AR75/$C75 -> 0.0010169922 | AU75: =AT75/$C75 -> 0
A76: NRIO Adinath Industries Bhiwadi Haryana | B76: July 2025 | C76: 155705 | D76: =C76-R76-J76-L76-P76-AB76-AR76-AL76 -> 155046 | E76: =D76/C76 -> 0.99576764 | F76: =C76-D76 -> 659 | G76: =F76/$C76 -> 0.0042323625 | I76: =H76/$C76 -> 0 | J76: 116 | K76: =J76/$C76 -> 0.00074499855 | L76: 142 | M76: =L76/$C76 -> 0.00091198099 | N76: 0 | O76: =N76/$C76 -> 0 | P76: 72 | Q76: =P76/$C76 -> 0.0004624129 | R76: 59 | S76: =R76/$C76 -> 0.00037892168 | U76: =T76/$C76 -> 0 | W76: =V76/$C76 -> 0 | Y76: =X76/$C76 -> 0 | AA76: =Z76/$C76 -> 0 | AB76: 71 | AC76: =AB76/$C76 -> 0.00045599049 | AE76: =AD76/$C76 -> 0 | AG76: =AF76/$C76 -> 0 | AI76: =AH76/$C$3 -> 0 | AK76: =AJ76/$C76 -> 0 | AL76: 0 | AM76: =AL76/$C76 -> 0 | AO76: =AN76/$C76 -> 0 | AQ76: =AP76/$C76 -> 0 | AR76: 199 | AS76: =AR76/$C76 -> 0.0012780579 | AU76: =AT76/$C76 -> 0
A77: NRIO Adinath Industries Bhiwadi Haryana | B77: August 2025 | C77: 170675 | D77: =C77-R77-J77-L77-P77-AB77-AR77-AL77 -> 169978 | E77: =D77/C77 -> 0.99591622 | F77: =C77-D77 -> 697 | G77: =F77/$C77 -> 0.004083785 | I77: =H77/$C77 -> 0 | J77: 127 | K77: =J77/$C77 -> 0.00074410429 | L77: 177 | M77: =L77/$C77 -> 0.0010370587 | N77: 0 | O77: =N77/$C77 -> 0 | P77: 76 | Q77: =P77/$C77 -> 0.00044529076 | R77: 28 | S77: =R77/$C77 -> 0.00016405449 | U77: =T77/$C77 -> 0 | W77: =V77/$C77 -> 0 | Y77: =X77/$C77 -> 0 | AA77: =Z77/$C77 -> 0 | AB77: 86 | AC77: =AB77/$C77 -> 0.00050388165 | AE77: =AD77/$C77 -> 0 | AG77: =AF77/$C77 -> 0 | AI77: =AH77/$C$3 -> 0 | AK77: =AJ77/$C77 -> 0 | AL77: 0 | AM77: =AL77/$C77 -> 0 | AO77: =AN77/$C77 -> 0 | AQ77: =AP77/$C77 -> 0 | AR77: 203 | AS77: =AR77/$C77 -> 0.001189395 | AU77: =AT77/$C77 -> 0
A78: NRIO Adinath Industries Bhiwadi Haryana | B78: September 2025 | C78: 176936 | D78: =C78-R78-J78-L78-P78-AB78-AR78-AL78 -> 176189 | E78: =D78/C78 -> 0.99577813 | F78: =C78-D78 -> 747 | G78: =F78/$C78 -> 0.0042218655 | I78: =H78/$C78 -> 0 | J78: 141 | K78: =J78/$C78 -> 0.00079689831 | L78: 182 | M78: =L78/$C78 -> 0.0010286205 | N78: 0 | O78: =N78/$C78 -> 0 | P78: 135 | Q78: =P78/$C78 -> 0.00076298775 | R78: 0 | S78: =R78/$C78 -> 0 | U78: =T78/$C78 -> 0 | W78: =V78/$C78 -> 0 | Y78: =X78/$C78 -> 0 | AA78: =Z78/$C78 -> 0 | AB78: 95 | AC78: =AB78/$C78 -> 0.0005369173 | AE78: =AD78/$C78 -> 0 | AG78: =AF78/$C78 -> 0 | AI78: =AH78/$C$3 -> 0 | AK78: =AJ78/$C78 -> 0 | AL78: 0 | AM78: =AL78/$C78 -> 0 | AO78: =AN78/$C78 -> 0 | AQ78: =AP78/$C78 -> 0 | AR78: 194 | AS78: =AR78/$C78 -> 0.0010964417 | AU78: =AT78/$C78 -> 0
A79: NRIO Adinath Industries Bhiwadi Haryana | B79: October 2025 | C79: 163413 | D79: =C79-R79-J79-L79-P79-AB79-AR79-AL79 -> 162568 | E79: =D79/C79 -> 0.99482905 | F79: =C79-D79 -> 845 | G79: =F79/$C79 -> 0.0051709472 | I79: =H79/$C79 -> 0 | J79: 150 | K79: =J79/$C79 -> 0.00091791963 | L79: 171 | M79: =L79/$C79 -> 0.0010464284 | N79: 0 | O79: =N79/$C79 -> 0 | P79: 93 | Q79: =P79/$C79 -> 0.00056911017 | R79: 69 | S79: =R79/$C79 -> 0.00042224303 | U79: =T79/$C79 -> 0 | W79: =V79/$C79 -> 0 | Y79: =X79/$C79 -> 0 | AA79: =Z79/$C79 -> 0 | AB79: 98 | AC79: =AB79/$C79 -> 0.00059970749 | AE79: =AD79/$C79 -> 0 | AG79: =AF79/$C79 -> 0 | AI79: =AH79/$C$3 -> 0 | AK79: =AJ79/$C79 -> 0 | AL79: 0 | AM79: =AL79/$C79 -> 0 | AO79: =AN79/$C79 -> 0 | AQ79: =AP79/$C79 -> 0 | AR79: 264 | AS79: =AR79/$C79 -> 0.0016155385 | AU79: =AT79/$C79 -> 0
A80: NRIO Adinath Industries Bhiwadi Haryana | B80: Novemeber 2025 | C80: 242203 | D80: =C80-R80-J80-L80-P80-AB80-AR80-AL80 -> 240479 | E80: =D80/C80 -> 0.992882 | F80: =C80-D80 -> 1724 | G80: =F80/$C80 -> 0.0071179961 | I80: =H80/$C80 -> 0 | J80: 235 | K80: =J80/$C80 -> 0.00097026048 | L80: 247 | M80: =L80/$C80 -> 0.0010198057 | N80: 0 | O80: =N80/$C80 -> 0 | P80: 153 | Q80: =P80/$C80 -> 0.00063170151 | R80: 118 | S80: =R80/$C80 -> 0.00048719463 | U80: =T80/$C80 -> 0 | W80: =V80/$C80 -> 0 | Y80: =X80/$C80 -> 0 | AA80: =Z80/$C80 -> 0 | AB80: 189 | AC80: =AB80/$C80 -> 0.00078033716 | AE80: =AD80/$C80 -> 0 | AG80: =AF80/$C80 -> 0 | AI80: =AH80/$C$3 -> 0 | AK80: =AJ80/$C80 -> 0 | AL80: 0 | AM80: =AL80/$C80 -> 0 | AO80: =AN80/$C80 -> 0 | AQ80: =AP80/$C80 -> 0 | AR80: 782 | AS80: =AR80/$C80 -> 0.0032286966 | AU80: =AT80/$C80 -> 0
A81: NRIO Adinath Industries INC Unit 1 Bhiwadi Haryana | B81: May 2025 | C81: 71594 | D81: =C81-R81-J81-L81-P81-AB81-AR81-AL81 -> 71534 | E81: =D81/C81 -> 0.99916194 | F81: =C81-D81 -> 60 | G81: =F81/$C81 -> 0.00083805906 | I81: =H81/$C81 -> 0 | J81: 33 | K81: =J81/$C81 -> 0.00046093248 | L81: 1 | M81: =L81/$C81 -> 1.3967651e-05 | N81: 0 | O81: =N81/$C81 -> 0 | P81: 0 | Q81: =P81/$C81 -> 0 | R81: 0 | S81: =R81/$C81 -> 0 | U81: =T81/$C81 -> 0 | W81: =V81/$C81 -> 0 | Y81: =X81/$C81 -> 0 | AA81: =Z81/$C81 -> 0 | AB81: 26 | AC81: =AB81/$C81 -> 0.00036315892 | AE81: =AD81/$C81 -> 0 | AG81: =AF81/$C81 -> 0 | AI81: =AH81/$C$3 -> 0 | AK81: =AJ81/$C81 -> 0 | AL81: 0 | AM81: =AL81/$C81 -> 0 | AO81: =AN81/$C81 -> 0 | AQ81: =AP81/$C81 -> 0 | AR81: 0 | AS81: =AR81/$C81 -> 0 | AU81: =AT81/$C81 -> 0
A82: NRIO Adinath Industries INC Unit 1 Bhiwadi Haryana | B82: June 2025 | C82: 117846 | D82: =C82-R82-J82-L82-P82-AB82-AR82-AL82 -> 117505 | E82: =D82/C82 -> 0.99710639 | F82: =C82-D82 -> 341 | G82: =F82/$C82 -> 0.0028936069 | I82: =H82/$C82 -> 0 | J82: 121 | K82: =J82/$C82 -> 0.0010267637 | L82: 66 | M82: =L82/$C82 -> 0.00056005295 | N82: 0 | O82: =N82/$C82 -> 0 | P82: 13 | Q82: =P82/$C82 -> 0.00011031346 | R82: 0 | S82: =R82/$C82 -> 0 | U82: =T82/$C82 -> 0 | W82: =V82/$C82 -> 0 | Y82: =X82/$C82 -> 0 | AA82: =Z82/$C82 -> 0 | AB82: 83 | AC82: =AB82/$C82 -> 0.00070430901 | AE82: =AD82/$C82 -> 0 | AG82: =AF82/$C82 -> 0 | AI82: =AH82/$C$3 -> 0 | AK82: =AJ82/$C82 -> 0 | AL82: 0 | AM82: =AL82/$C82 -> 0 | AO82: =AN82/$C82 -> 0 | AQ82: =AP82/$C82 -> 0 | AR82: 58 | AS82: =AR82/$C82 -> 0.00049216774 | AU82: =AT82/$C82 -> 0
A83: NRIO Adinath Industries INC Unit 1 Bhiwadi Haryana | B83: July 2025 | C83: 160472 | D83: =C83-R83-J83-L83-P83-AB83-AR83-AL83 -> 159848 | E83: =D83/C83 -> 0.99611147 | F83: =C83-D83 -> 624 | G83: =F83/$C83 -> 0.0038885288 | I83: =H83/$C83 -> 0 | J83: 182 | K83: =J83/$C83 -> 0.0011341542 | L83: 101 | M83: =L83/$C83 -> 0.00062939329 | N83: 0 | O83: =N83/$C83 -> 0 | P83: 56 | Q83: =P83/$C83 -> 0.00034897054 | R83: 15 | S83: =R83/$C83 -> 9.3474251e-05 | U83: =T83/$C83 -> 0 | W83: =V83/$C83 -> 0 | Y83: =X83/$C83 -> 0 | AA83: =Z83/$C83 -> 0 | AB83: 141 | AC83: =AB83/$C83 -> 0.00087865796 | AE83: =AD83/$C83 -> 0 | AG83: =AF83/$C83 -> 0 | AI83: =AH83/$C$3 -> 0 | AK83: =AJ83/$C83 -> 0 | AL83: 0 | AM83: =AL83/$C83 -> 0 | AO83: =AN83/$C83 -> 0 | AQ83: =AP83/$C83 -> 0 | AR83: 129 | AS83: =AR83/$C83 -> 0.00080387856 | AU83: =AT83/$C83 -> 0
A84: NRIO Adinath Industries INC Unit 1 Bhiwadi Haryana | B84: August 2025 | C84: 195440 | D84: =C84-R84-J84-L84-P84-AB84-AR84-AL84 -> 194696 | E84: =D84/C84 -> 0.99619321 | F84: =C84-D84 -> 744 | G84: =F84/$C84 -> 0.0038067949 | I84: =H84/$C84 -> 0 | J84: 192 | K84: =J84/$C84 -> 0.00098239869 | L84: 130 | M84: =L84/$C84 -> 0.00066516578 | N84: 0 | O84: =N84/$C84 -> 0 | P84: 67 | Q84: =P84/$C84 -> 0.00034281621 | R84: 21 | S84: =R84/$C84 -> 0.00010744986 | U84: =T84/$C84 -> 0 | W84: =V84/$C84 -> 0 | Y84: =X84/$C84 -> 0 | AA84: =Z84/$C84 -> 0 | AB84: 139 | AC84: =AB84/$C84 -> 0.00071121572 | AE84: =AD84/$C84 -> 0 | AG84: =AF84/$C84 -> 0 | AI84: =AH84/$C$3 -> 0 | AK84: =AJ84/$C84 -> 0 | AL84: 0 | AM84: =AL84/$C84 -> 0 | AO84: =AN84/$C84 -> 0 | AQ84: =AP84/$C84 -> 0 | AR84: 195 | AS84: =AR84/$C84 -> 0.00099774867 | AU84: =AT84/$C84 -> 0
... A93: NRIO Avdesh Tracks(P) Ltd. Mohali Punjab | B93: Novemeber 2025 | C93: 128620 | D93: =C93-R93-J93-L93-P93-AB93-AR93-AL93 -> 127890 | E93: =D93/C93 -> 0.99432437 | F93: =C93-D93 -> 730 | G93: =F93/$C93 -> 0.0056756336 | I93: =H93/$C93 -> 0 | J93: 140 | K93: =J93/$C93 -> 0.0010884777 | L93: 129 | M93: =L93/$C93 -> 0.0010029544 | N93: 0 | O93: =N93/$C93 -> 0 | P93: 71 | Q93: =P93/$C93 -> 0.00055201368 | R93: 41 | S93: =R93/$C93 -> 0.00031876847 | U93: =T93/$C93 -> 0 | W93: =V93/$C93 -> 0 | Y93: =X93/$C93 -> 0 | AA93: =Z93/$C93 -> 0 | AB93: 109 | AC93: =AB93/$C93 -> 0.00084745763 | AE93: =AD93/$C93 -> 0 | AG93: =AF93/$C93 -> 0 | AI93: =AH93/$C$3 -> 0 | AK93: =AJ93/$C93 -> 0 | AL93: 0 | AM93: =AL93/$C93 -> 0 | AO93: =AN93/$C93 -> 0 | AQ93: =AP93/$C93 -> 0 | AR93: 240 | AS93: =AR93/$C93 -> 0.0018659617 | AU93: =AT93/$C93 -> 0
A94: NRIO Bimla Rail Fasteners Karnal Haryana | B94: August 2025 | C94: 6381 | D94: =C94-R94-J94-L94-P94-AB94-AR94-AL94 -> 6376 | E94: =D94/C94 -> 0.99921642 | F94: =C94-D94 -> 5 | G94: =F94/$C94 -> 0.00078357624 | I94: =H94/$C94 -> 0 | J94: 0 | K94: =J94/$C94 -> 0 | L94: 3 | M94: =L94/$C94 -> 0.00047014575 | O94: =N94/$C94 -> 0 | P94: 2 | Q94: =P94/$C94 -> 0.0003134305 | R94: 0 | S94: =R94/$C94 -> 0 | U94: =T94/$C94 -> 0 | W94: =V94/$C94 -> 0 | Y94: =X94/$C94 -> 0 | AA94: =Z94/$C94 -> 0 | AB94: 0 | AC94: =AB94/$C94 -> 0 | AE94: =AD94/$C94 -> 0 | AG94: =AF94/$C94 -> 0 | AI94: =AH94/$C$3 -> 0 | AK94: =AJ94/$C94 -> 0 | AL94: 0 | AM94: =AL94/$C94 -> 0 | AO94: =AN94/$C94 -> 0 | AQ94: =AP94/$C94 -> 0 | AR94: 0 | AS94: =AR94/$C94 -> 0 | AU94: =AT94/$C94 -> 0
A95: NRIO Bimla Rail Fasteners Karnal Haryana | B95: September 2025 | C95: 127933 | D95: =C95-R95-J95-L95-P95-AB95-AR95-AL95 -> 127630 | E95: =D95/C95 -> 0.99763157 | F95: =C95-D95 -> 303 | G95: =F95/$C95 -> 0.0023684272 | I95: =H95/$C95 -> 0 | J95: 62 | K95: =J95/$C95 -> 0.00048462867 | L95: 82 | M95: =L95/$C95 -> 0.0006409605 | O95: =N95/$C95 -> 0 | P95: 47 | Q95: =P95/$C95 -> 0.0003673798 | R95: 8 | S95: =R95/$C95 -> 6.2532732e-05 | U95: =T95/$C95 -> 0 | W95: =V95/$C95 -> 0 | Y95: =X95/$C95 -> 0 | AA95: =Z95/$C95 -> 0 | AB95: 50 | AC95: =AB95/$C95 -> 0.00039082957 | AE95: =AD95/$C95 -> 0 | AG95: =AF95/$C95 -> 0 | AI95: =AH95/$C$3 -> 0 | AK95: =AJ95/$C95 -> 0 | AL95: 0 | AM95: =AL95/$C95 -> 0 | AO95: =AN95/$C95 -> 0 | AQ95: =AP95/$C95 -> 0 | AR95: 54 | AS95: =AR95/$C95 -> 0.00042209594 | AU95: =AT95/$C95 -> 0
A96: NRIO Bimla Rail Fasteners Karnal Haryana | B96: October 2025 | C96: 15550 | D96: =C96-R96-J96-L96-P96-AB96-AR96-AL96 -> 15467 | E96: =D96/C96 -> 0.99466238 | F96: =C96-D96 -> 83 | G96: =F96/$C96 -> 0.0053376206 | I96: =H96/$C96 -> 0 | J96: 12 | K96: =J96/$C96 -> 0.00077170418 | L96: 19 | M96: =L96/$C96 -> 0.001221865 | O96: =N96/$C96 -> 0 | P96: 12 | Q96: =P96/$C96 -> 0.00077170418 | R96: 0 | S96: =R96/$C96 -> 0 | U96: =T96/$C96 -> 0 | W96: =V96/$C96 -> 0 | Y96: =X96/$C96 -> 0 | AA96: =Z96/$C96 -> 0 | AB96: 12 | AC96: =AB96/$C96 -> 0.00077170418 | AE96: =AD96/$C96 -> 0 | AG96: =AF96/$C96 -> 0 | AI96: =AH96/$C$3 -> 0 | AK96: =AJ96/$C96 -> 0 | AL96: 0 | AM96: =AL96/$C96 -> 0 | AO96: =AN96/$C96 -> 0 | AQ96: =AP96/$C96 -> 0 | AR96: 28 | AS96: =AR96/$C96 -> 0.0018006431 | AU96: =AT96/$C96 -> 0
A97: NRIO Bimla Rail Fasteners Karnal Haryana | B97: Novemeber 2025 | C97: 31163 | D97: =C97-R97-J97-L97-P97-AB97-AR97-AL97 -> 30972 | E97: =D97/C97 -> 0.99387094 | F97: =C97-D97 -> 191 | G97: =F97/$C97 -> 0.0061290633 | I97: =H97/$C97 -> 0 | J97: 26 | K97: =J97/$C97 -> 0.00083432275 | L97: 39 | M97: =L97/$C97 -> 0.0012514841 | O97: =N97/$C97 -> 0 | P97: 25 | Q97: =P97/$C97 -> 0.00080223342 | R97: 5 | S97: =R97/$C97 -> 0.00016044668 | U97: =T97/$C97 -> 0 | W97: =V97/$C97 -> 0 | Y97: =X97/$C97 -> 0 | AA97: =Z97/$C97 -> 0 | AB97: 24 | AC97: =AB97/$C97 -> 0.00077014408 | AE97: =AD97/$C97 -> 0 | AG97: =AF97/$C97 -> 0 | AI97: =AH97/$C$3 -> 0 | AK97: =AJ97/$C97 -> 0 | AL97: 0 | AM97: =AL97/$C97 -> 0 | AO97: =AN97/$C97 -> 0 | AQ97: =AP97/$C97 -> 0 | AR97: 72 | AS97: =AR97/$C97 -> 0.0023104322 | AU97: =AT97/$C97 -> 0
A98: NRIO Cemcon Railway Industries Gohana Haryana | B98: July 2025 | C98: 52699 | D98: =C98-R98-J98-L98-P98-AB98-AR98-AL98 -> 52564 | E98: =D98/C98 -> 0.99743828 | F98: =C98-D98 -> 135 | G98: =F98/$C98 -> 0.0025617184 | I98: =H98/$C98 -> 0 | J98: 17 | K98: =J98/$C98 -> 0.00032258677 | L98: 51 | M98: =L98/$C98 -> 0.0009677603 | O98: =N98/$C98 -> 0 | P98: 0 | Q98: =P98/$C98 -> 0 | R98: 0 | S98: =R98/$C98 -> 0 | U98: =T98/$C98 -> 0 | W98: =V98/$C98 -> 0 | Y98: =X98/$C98 -> 0 | AA98: =Z98/$C98 -> 0 | AB98: 56 | AC98: =AB98/$C98 -> 0.0010626388 | AE98: =AD98/$C98 -> 0 | AG98: =AF98/$C98 -> 0 | AI98: =AH98/$C$3 -> 0 | AK98: =AJ98/$C98 -> 0 | AL98: 0 | AM98: =AL98/$C98 -> 0 | AO98: =AN98/$C98 -> 0 | AQ98: =AP98/$C98 -> 0 | AR98: 11 | AS98: =AR98/$C98 -> 0.00020873261 | AU98: =AT98/$C98 -> 0
A99: NRIO Cemcon Railway Industries Gohana Haryana | B99: August 2025 | C99: 46504 | D99: =C99-R99-J99-L99-P99-AB99-AR99-AL99 -> 46328 | E99: =D99/C99 -> 0.99621538 | F99: =C99-D99 -> 176 | G99: =F99/$C99 -> 0.0037846207 | I99: =H99/$C99 -> 0 | J99: 57 | K99: =J99/$C99 -> 0.001225701 | L99: 7 | M99: =L99/$C99 -> 0.00015052469 | O99: =N99/$C99 -> 0 | P99: 0 | Q99: =P99/$C99 -> 0 | R99: 0 | S99: =R99/$C99 -> 0 | U99: =T99/$C99 -> 0 | W99: =V99/$C99 -> 0 | Y99: =X99/$C99 -> 0 | AA99: =Z99/$C99 -> 0 | AB99: 73 | AC99: =AB99/$C99 -> 0.0015697574 | AE99: =AD99/$C99 -> 0 | AG99: =AF99/$C99 -> 0 | AI99: =AH99/$C$3 -> 0 | AK99: =AJ99/$C99 -> 0 | AL99: 0 | AM99: =AL99/$C99 -> 0 | AO99: =AN99/$C99 -> 0 | AQ99: =AP99/$C99 -> 0 | AR99: 39 | AS99: =AR99/$C99 -> 0.00083863754 | AU99: =AT99/$C99 -> 0
A100: NRIO Cemcon Railway Industries Gohana Haryana | B100: September 2025 | C100: 0 | D100: =C100-R100-J100-L100-P100-AB100-AR100-AL100 -> 0 | E100: =D100/C100 -> #DIV/0! | F100: =C100-D100 -> 0 | G100: =F100/$C100 -> #DIV/0! | I100: =H100/$C100 -> #DIV/0! | J100: 0 | K100: =J100/$C100 -> #DIV/0! | L100: 0 | M100: =L100/$C100 -> #DIV/0! | O100: =N100/$C100 -> #DIV/0! | P100: 0 | Q100: =P100/$C100 -> #DIV/0! | R100: 0 | S100: =R100/$C100 -> #DIV/0! | T100: 0 | U100: =T100/$C100 -> #DIV/0! | W100: =V100/$C100 -> #DIV/0! | Y100: =X100/$C100 -> #DIV/0! | AA100: =Z100/$C100 -> #DIV/0! | AB100: 0 | AC100: =AB100/$C100 -> #DIV/0! | AE100: =AD100/$C100 -> #DIV/0! | AG100: =AF100/$C100 -> #DIV/0! | AI100: =AH100/$C$3 -> 0 | AK100: =AJ100/$C100 -> #DIV/0! | AL100: 0 | AM100: =AL100/$C100 -> #DIV/0! | AO100: =AN100/$C100 -> #DIV/0! | AQ100: =AP100/$C100 -> #DIV/0! | AR100: 0 | AS100: =AR100/$C100 -> #DIV/0! | AU100: =AT100/$C100 -> #DIV/0!
A101: NRIO Cemcon Railway Industries Gohana Haryana | B101: October 2025 | C101: 40732 | D101: =C101-R101-J101-L101-P101-AB101-AR101-AL101 -> 40247 | E101: =D101/C101 -> 0.9880929 | F101: =C101-D101 -> 485 | G101: =F101/$C101 -> 0.0119071 | I101: =H101/$C101 -> 0 | J101: 159 | K101: =J101/$C101 -> 0.0039035648 | L101: 140 | M101: =L101/$C101 -> 0.0034371011 | O101: =N101/$C101 -> 0 | P101: 0 | Q101: =P101/$C101 -> 0 | R101: 0 | S101: =R101/$C101 -> 0 | U101: =T101/$C101 -> 0 | W101: =V101/$C101 -> 0 | Y101: =X101/$C101 -> 0 | AA101: =Z101/$C101 -> 0 | AB101: 139 | AC101: =AB101/$C101 -> 0.0034125503 | AE101: =AD101/$C101 -> 0 | AG101: =AF101/$C101 -> 0 | AI101: =AH101/$C$3 -> 0 | AK101: =AJ101/$C101 -> 0 | AL101: 0 | AM101: =AL101/$C101 -> 0 | AO101: =AN101/$C101 -> 0 | AQ101: =AP101/$C101 -> 0 | AR101: 47 | AS101: =AR101/$C101 -> 0.0011538839 | AU101: =AT101/$C101 -> 0
A102: NRIO Cemcon Railway Industries Gohana Haryana | B102: Novemeber 2025 | C102: 50657 | D102: =C102-R102-J102-L102-P102-AB102-AR102-AL102 -> 50006 | E102: =D102/C102 -> 0.98714886 | F102: =C102-D102 -> 651 | G102: =F102/$C102 -> 0.012851136 | I102: =H102/$C102 -> 0 | J102: 193 | K102: =J102/$C102 -> 0.0038099374 | L102: 205 | M102: =L102/$C102 -> 0.0040468247 | O102: =N102/$C102 -> 0 | P102: 0 | Q102: =P102/$C102 -> 0 | R102: 0 | S102: =R102/$C102 -> 0 | U102: =T102/$C102 -> 0 | W102: =V102/$C102 -> 0 | Y102: =X102/$C102 -> 0 | AA102: =Z102/$C102 -> 0 | AB102: 184 | AC102: =AB102/$C102 -> 0.0036322719 | AE102: =AD102/$C102 -> 0 | AG102: =AF102/$C102 -> 0 | AI102: =AH102/$C$3 -> 0 | AK102: =AJ102/$C102 -> 0 | AL102: 0 | AM102: =AL102/$C102 -> 0 | AO102: =AN102/$C102 -> 0 | AQ102: =AP102/$C102 -> 0 | AR102: 69 | AS102: =AR102/$C102 -> 0.001362102 | AU102: =AT102/$C102 -> 0
A103: NRIO Fateh Chand Jain Faridabad Haryana | B103: April 2025 | C103: 157135 | D103: =C103-R103-J103-L103-P103-AB103-AR103-AL103 -> 157010 | E103: =D103/C103 -> 0.99920451 | F103: =C103-D103 -> 125 | G103: =F103/$C103 -> 0.00079549432 | I103: =H103/$C103 -> 0 | J103: 56 | K103: =J103/$C103 -> 0.00035638146 | L103: 8 | M103: =L103/$C103 -> 5.0911636e-05 | O103: =N103/$C103 -> 0 | P103: 0 | Q103: =P103/$C103 -> 0 | R103: 0 | S103: =R103/$C103 -> 0 | U103: =T103/$C103 -> 0 | W103: =V103/$C103 -> 0 | Y103: =X103/$C103 -> 0 | AA103: =Z103/$C103 -> 0 | AB103: 61 | AC103: =AB103/$C103 -> 0.00038820123 | AE103: =AD103/$C103 -> 0 | AG103: =AF103/$C103 -> 0 | AI103: =AH103/$C$3 -> 0 | AK103: =AJ103/$C103 -> 0 | AL103: 0 | AM103: =AL103/$C103 -> 0 | AO103: =AN103/$C103 -> 0 | AQ103: =AP103/$C103 -> 0 | AR103: 0 | AS103: =AR103/$C103 -> 0 | AU103: =AT103/$C103 -> 0
A104: NRIO Fateh Chand Jain Faridabad Haryana | B104: May 2025 | C104: 94593 | D104: =C104-R104-J104-L104-P104-AB104-AR104-AL104 -> 94500 | E104: =D104/C104 -> 0.99901684 | F104: =C104-D104 -> 93 | G104: =F104/$C104 -> 0.00098315943 | I104: =H104/$C104 -> 0 | J104: 44 | K104: =J104/$C104 -> 0.0004651507 | L104: 0 | M104: =L104/$C104 -> 0 | O104: =N104/$C104 -> 0 | P104: 0 | Q104: =P104/$C104 -> 0 | R104: 0 | S104: =R104/$C104 -> 0 | U104: =T104/$C104 -> 0 | W104: =V104/$C104 -> 0 | Y104: =X104/$C104 -> 0 | AA104: =Z104/$C104 -> 0 | AB104: 49 | AC104: =AB104/$C104 -> 0.00051800873 | AE104: =AD104/$C104 -> 0 | AG104: =AF104/$C104 -> 0 | AI104: =AH104/$C$3 -> 0 | AK104: =AJ104/$C104 -> 0 | AL104: 0 | AM104: =AL104/$C104 -> 0 | AO104: =AN104/$C104 -> 0 | AQ104: =AP104/$C104 -> 0 | AR104: 0 | AS104: =AR104/$C104 -> 0 | AU104: =AT104/$C104 -> 0
A105: NRIO Fateh Chand Jain Faridabad Haryana | B105: June 2025 | C105: 99053 | D105: =C105-R105-J105-L105-P105-AB105-AR105-AL105 -> 98777 | E105: =D105/C105 -> 0.99721361 | F105: =C105-D105 -> 276 | G105: =F105/$C105 -> 0.0027863871 | I105: =H105/$C105 -> 0 | J105: 61 | K105: =J105/$C105 -> 0.00061583193 | L105: 2 | M105: =L105/$C105 -> 2.0191211e-05 | O105: =N105/$C105 -> 0 | P105: 1 | Q105: =P105/$C105 -> 1.0095605e-05 | R105: 0 | S105: =R105/$C105 -> 0 | U105: =T105/$C105 -> 0 | W105: =V105/$C105 -> 0 | Y105: =X105/$C105 -> 0 | AA105: =Z105/$C105 -> 0 | AB105: 54 | AC105: =AB105/$C105 -> 0.00054516269 | AE105: =AD105/$C105 -> 0 | AG105: =AF105/$C105 -> 0 | AI105: =AH105/$C$3 -> 0 | AK105: =AJ105/$C105 -> 0 | AL105: 0 | AM105: =AL105/$C105 -> 0 | AO105: =AN105/$C105 -> 0 | AQ105: =AP105/$C105 -> 0 | AR105: 158 | AS105: =AR105/$C105 -> 0.0015951057 | AU105: =AT105/$C105 -> 0
A106: NRIO Fateh Chand Jain Faridabad Haryana | B106: July 2025 | C106: 167505 | D106: =C106-R106-J106-L106-P106-AB106-AR106-AL106 -> 167067 | E106: =D106/C106 -> 0.99738515 | F106: =C106-D106 -> 438 | G106: =F106/$C106 -> 0.0026148473 | I106: =H106/$C106 -> 0 | J106: 99 | K106: =J106/$C106 -> 0.00059102713 | L106: 29 | M106: =L106/$C106 -> 0.00017312916 | O106: =N106/$C106 -> 0 | P106: 6 | Q106: =P106/$C106 -> 3.5819826e-05 | R106: 0 | S106: =R106/$C106 -> 0 | U106: =T106/$C106 -> 0 | W106: =V106/$C106 -> 0 | Y106: =X106/$C106 -> 0 | AA106: =Z106/$C106 -> 0 | AB106: 102 | AC106: =AB106/$C106 -> 0.00060893705 | AE106: =AD106/$C106 -> 0 | AG106: =AF106/$C106 -> 0 | AI106: =AH106/$C$3 -> 0 | AK106: =AJ106/$C106 -> 0 | AL106: 0 | AM106: =AL106/$C106 -> 0 | AO106: =AN106/$C106 -> 0 | AQ106: =AP106/$C106 -> 0 | AR106: 202 | AS106: =AR106/$C106 -> 0.0012059342 | AU106: =AT106/$C106 -> 0
A107: NRIO Fateh Chand Jain Faridabad Haryana | B107: August 2025 | C107: 104777 | D107: =C107-R107-J107-L107-P107-AB107-AR107-AL107 -> 104591 | E107: =D107/C107 -> 0.9982248 | F107: =C107-D107 -> 186 | G107: =F107/$C107 -> 0.0017751988 | I107: =H107/$C107 -> 0 | J107: 71 | K107: =J107/$C107 -> 0.00067762963 | L107: 9 | M107: =L107/$C107 -> 8.5896714e-05 | O107: =N107/$C107 -> 0 | P107: 0 | Q107: =P107/$C107 -> 0 | R107: 0 | S107: =R107/$C107 -> 0 | U107: =T107/$C107 -> 0 | W107: =V107/$C107 -> 0 | Y107: =X107/$C107 -> 0 | AA107: =Z107/$C107 -> 0 | AB107: 63 | AC107: =AB107/$C107 -> 0.000601277 | AE107: =AD107/$C107 -> 0 | AG107: =AF107/$C107 -> 0 | AI107: =AH107/$C$3 -> 0 | AK107: =AJ107/$C107 -> 0 | AL107: 0 | AM107: =AL107/$C107 -> 0 | AO107: =AN107/$C107 -> 0 | AQ107: =AP107/$C107 -> 0 | AR107: 43 | AS107: =AR107/$C107 -> 0.00041039541 | AU107: =AT107/$C107 -> 0
A108: NRIO Fateh Chand Jain Faridabad Haryana | B108: September 2025 | C108: 104320 | D108: =C108-R108-J108-L108-P108-AB108-AR108-AL108 -> 104078 | E108: =D108/C108 -> 0.99768021 | F108: =C108-D108 -> 242 | G108: =F108/$C108 -> 0.0023197853 | I108: =H108/$C108 -> 0 | J108: 77 | K108: =J108/$C108 -> 0.0007381135 | L108: 20 | M108: =L108/$C108 -> 0.00019171779 | O108: =N108/$C108 -> 0 | P108: 0 | Q108: =P108/$C108 -> 0 | R108: 0 | S108: =R108/$C108 -> 0 | U108: =T108/$C108 -> 0 | W108: =V108/$C108 -> 0 | Y108: =X108/$C108 -> 0 | AA108: =Z108/$C108 -> 0 | AB108: 76 | AC108: =AB108/$C108 -> 0.00072852761 | AE108: =AD108/$C108 -> 0 | AG108: =AF108/$C108 -> 0 | AI108: =AH108/$C$3 -> 0 | AK108: =AJ108/$C108 -> 0 | AL108: 0 | AM108: =AL108/$C108 -> 0 | AO108: =AN108/$C108 -> 0 | AQ108: =AP108/$C108 -> 0 | AR108: 69 | AS108: =AR108/$C108 -> 0.00066142638 | AU108: =AT108/$C108 -> 0
A109: NRIO Fateh Chand Jain Faridabad Haryana | B109: October 2025 | C109: 151718 | D109: =C109-R109-J109-L109-P109-AB109-AR109-AL109 -> 150842 | E109: =D109/C109 -> 0.99422613 | F109: =C109-D109 -> 876 | G109: =F109/$C109 -> 0.0057738699 | I109: =H109/$C109 -> 0 | J109: 105 | K109: =J109/$C109 -> 0.00069207345 | L109: 33 | M109: =L109/$C109 -> 0.0002175088 | O109: =N109/$C109 -> 0 | P109: 12 | Q109: =P109/$C109 -> 7.9094109e-05 | R109: 0 | S109: =R109/$C109 -> 0 | U109: =T109/$C109 -> 0 | W109: =V109/$C109 -> 0 | Y109: =X109/$C109 -> 0 | AA109: =Z109/$C109 -> 0 | AB109: 606 | AC109: =AB109/$C109 -> 0.0039942525 | AE109: =AD109/$C109 -> 0 | AG109: =AF109/$C109 -> 0 | AI109: =AH109/$C$3 -> 0 | AK109: =AJ109/$C109 -> 0 | AL109: 0 | AM109: =AL109/$C109 -> 0 | AO109: =AN109/$C109 -> 0 | AQ109: =AP109/$C109 -> 0 | AR109: 120 | AS109: =AR109/$C109 -> 0.00079094109 | AU109: =AT109/$C109 -> 0
A110: NRIO Fateh Chand Jain Faridabad Haryana | B110: Novemeber 2025 | C110: 144113 | D110: =C110-R110-J110-L110-P110-AB110-AR110-AL110 -> 143641 | E110: =D110/C110 -> 0.99672479 | F110: =C110-D110 -> 472 | G110: =F110/$C110 -> 0.0032752076 | I110: =H110/$C110 -> 0 | J110: 105 | K110: =J110/$C110 -> 0.00072859492 | L110: 8 | M110: =L110/$C110 -> 5.5511994e-05 | O110: =N110/$C110 -> 0 | P110: 0 | Q110: =P110/$C110 -> 0 | R110: 0 | S110: =R110/$C110 -> 0 | U110: =T110/$C110 -> 0 | W110: =V110/$C110 -> 0 | Y110: =X110/$C110 -> 0 | AA110: =Z110/$C110 -> 0 | AB110: 100 | AC110: =AB110/$C110 -> 0.00069389993 | AE110: =AD110/$C110 -> 0 | AG110: =AF110/$C110 -> 0 | AI110: =AH110/$C$3 -> 0 | AK110: =AJ110/$C110 -> 0 | AL110: 0 | AM110: =AL110/$C110 -> 0 | AO110: =AN110/$C110 -> 0 | AQ110: =AP110/$C110 -> 0 | AR110: 259 | AS110: =AR110/$C110 -> 0.0017972008 | AU110: =AT110/$C110 -> 0
A111: NRIO Lauls Private Ltd. Faridabad Haryana | B111: April 2025 | C111: 101528 | D111: =C111-R111-J111-L111-P111-AB111-AR111-AL111 -> 101479 | E111: =D111/C111 -> 0.99951737 | F111: =C111-D111 -> 49 | G111: =F111/$C111 -> 0.00048262548 | I111: =H111/$C111 -> 0 | J111: 22 | K111: =J111/$C111 -> 0.00021668899 | L111: 2 | M111: =L111/$C111 -> 1.9698999e-05 | O111: =N111/$C111 -> 0 | P111: 0 | Q111: =P111/$C111 -> 0 | R111: 0 | S111: =R111/$C111 -> 0 | U111: =T111/$C111 -> 0 | W111: =V111/$C111 -> 0 | Y111: =X111/$C111 -> 0 | AA111: =Z111/$C111 -> 0 | AB111: 24 | AC111: =AB111/$C111 -> 0.00023638799 | AE111: =AD111/$C111 -> 0 | AG111: =AF111/$C111 -> 0 | AI111: =AH111/$C$3 -> 0 | AK111: =AJ111/$C111 -> 0 | AL111: 1 | AM111: =AL111/$C111 -> 9.8494996e-06 | AO111: =AN111/$C111 -> 0 | AQ111: =AP111/$C111 -> 0 | AR111: 0 | AS111: =AR111/$C111 -> 0 | AU111: =AT111/$C111 -> 0
A112: NRIO Lauls Private Ltd. Faridabad Haryana | B112: May 2025 | C112: 121436 | D112: =C112-R112-J112-L112-P112-AB112-AR112-AL112 -> 121357 | E112: =D112/C112 -> 0.99934945 | F112: =C112-D112 -> 79 | G112: =F112/$C112 -> 0.00065054844 | I112: =H112/$C112 -> 0 | J112: 40 | K112: =J112/$C112 -> 0.00032939161 | L112: 9 | M112: =L112/$C112 -> 7.4113113e-05 | O112: =N112/$C112 -> 0 | P112: 0 | Q112: =P112/$C112 -> 0 | R112: 0 | S112: =R112/$C112 -> 0 | U112: =T112/$C112 -> 0 | W112: =V112/$C112 -> 0 | Y112: =X112/$C112 -> 0 | AA112: =Z112/$C112 -> 0 | AB112: 30 | AC112: =AB112/$C112 -> 0.00024704371 | AE112: =AD112/$C112 -> 0 | AG112: =AF112/$C112 -> 0 | AI112: =AH112/$C$3 -> 0 | AK112: =AJ112/$C112 -> 0 | AL112: 0 | AM112: =AL112/$C112 -> 0 | AO112: =AN112/$C112 -> 0 | AQ112: =AP112/$C112 -> 0 | AR112: 0 | AS112: =AR112/$C112 -> 0 | AU112: =AT112/$C112 -> 0
... A122: NRIO Panna Lal Kanhiya Lal Bansal LLP Sonipat Haryana | B122: Novemeber 2025 | C122: 107018 | D122: =C122-R122-J122-L122-P122-AB122-AR122-AL122 -> 106380 | E122: =D122/C122 -> 0.99403839 | F122: =C122-D122 -> 638 | G122: =F122/$C122 -> 0.0059616139 | I122: =H122/$C122 -> 0 | J122: 68 | K122: =J122/$C122 -> 0.00063540713 | L122: 33 | M122: =L122/$C122 -> 0.00030835934 | O122: =N122/$C122 -> 0 | P122: 59 | Q122: =P122/$C122 -> 0.00055130913 | R122: 12 | S122: =R122/$C122 -> 0.00011213067 | U122: =T122/$C122 -> 0 | W122: =V122/$C122 -> 0 | Y122: =X122/$C122 -> 0 | AA122: =Z122/$C122 -> 0 | AB122: 50 | AC122: =AB122/$C122 -> 0.00046721112 | AE122: =AD122/$C122 -> 0 | AG122: =AF122/$C122 -> 0 | AI122: =AH122/$C$3 -> 0 | AK122: =AJ122/$C122 -> 0 | AL122: 0 | AM122: =AL122/$C122 -> 0 | AO122: =AN122/$C122 -> 0 | AQ122: =AP122/$C122 -> 0 | AR122: 416 | AS122: =AR122/$C122 -> 0.0038871965 | AU122: =AT122/$C122 -> 0
A123: NRIO Siddartha Metal Fabricators Faridabad Haryana | B123: April 2025 | C123: 60168 | D123: =C123-R123-J123-L123-P123-AB123-AR123-AL123 -> 60128 | E123: =D123/C123 -> 0.99933519 | F123: =C123-D123 -> 40 | G123: =F123/$C123 -> 0.00066480521 | I123: =H123/$C123 -> 0 | J123: 30 | K123: =J123/$C123 -> 0.00049860391 | L123: 1 | M123: =L123/$C123 -> 1.662013e-05 | O123: =N123/$C123 -> 0 | P123: 0 | Q123: =P123/$C123 -> 0 | R123: 0 | S123: =R123/$C123 -> 0 | T123: 0 | U123: =T123/$C123 -> 0 | W123: =V123/$C123 -> 0 | Y123: =X123/$C123 -> 0 | AA123: =Z123/$C123 -> 0 | AB123: 9 | AC123: =AB123/$C123 -> 0.00014958117 | AE123: =AD123/$C123 -> 0 | AG123: =AF123/$C123 -> 0 | AI123: =AH123/$C$3 -> 0 | AK123: =AJ123/$C123 -> 0 | AL123: 0 | AM123: =AL123/$C123 -> 0 | AO123: =AN123/$C123 -> 0 | AQ123: =AP123/$C123 -> 0 | AR123: 0 | AS123: =AR123/$C123 -> 0 | AU123: =AT123/$C123 -> 0
A124: NRIO Siddartha Metal Fabricators Faridabad Haryana | B124: September 2025 | C124: 125428 | D124: =C124-R124-J124-L124-P124-AB124-AR124-AL124 -> 125147 | E124: =D124/C124 -> 0.99775967 | F124: =C124-D124 -> 281 | G124: =F124/$C124 -> 0.0022403291 | I124: =H124/$C124 -> 0 | J124: 115 | K124: =J124/$C124 -> 0.00091686067 | L124: 40 | M124: =L124/$C124 -> 0.00031890806 | O124: =N124/$C124 -> 0 | P124: 0 | Q124: =P124/$C124 -> 0 | R124: 0 | S124: =R124/$C124 -> 0 | T124: 0 | U124: =T124/$C124 -> 0 | W124: =V124/$C124 -> 0 | Y124: =X124/$C124 -> 0 | AA124: =Z124/$C124 -> 0 | AB124: 96 | AC124: =AB124/$C124 -> 0.00076537934 | AE124: =AD124/$C124 -> 0 | AG124: =AF124/$C124 -> 0 | AI124: =AH124/$C$3 -> 0 | AK124: =AJ124/$C124 -> 0 | AL124: 0 | AM124: =AL124/$C124 -> 0 | AO124: =AN124/$C124 -> 0 | AQ124: =AP124/$C124 -> 0 | AR124: 30 | AS124: =AR124/$C124 -> 0.00023918104 | AU124: =AT124/$C124 -> 0
A125: NRIO Siddartha Metal Fabricators Faridabad Haryana | B125: October 2025 | C125: 118323 | D125: =C125-R125-J125-L125-P125-AB125-AR125-AL125 -> 117546 | E125: =D125/C125 -> 0.99343323 | F125: =C125-D125 -> 777 | G125: =F125/$C125 -> 0.0065667706 | I125: =H125/$C125 -> 0 | J125: 586 | K125: =J125/$C125 -> 0.0049525452 | L125: 68 | M125: =L125/$C125 -> 0.00057469807 | O125: =N125/$C125 -> 0 | P125: 0 | Q125: =P125/$C125 -> 0 | R125: 0 | S125: =R125/$C125 -> 0 | T125: 0 | U125: =T125/$C125 -> 0 | W125: =V125/$C125 -> 0 | Y125: =X125/$C125 -> 0 | AA125: =Z125/$C125 -> 0 | AB125: 89 | AC125: =AB125/$C125 -> 0.00075217836 | AE125: =AD125/$C125 -> 0 | AG125: =AF125/$C125 -> 0 | AI125: =AH125/$C$3 -> 0 | AK125: =AJ125/$C125 -> 0 | AL125: 0 | AM125: =AL125/$C125 -> 0 | AO125: =AN125/$C125 -> 0 | AQ125: =AP125/$C125 -> 0 | AR125: 34 | AS125: =AR125/$C125 -> 0.00028734904 | AU125: =AT125/$C125 -> 0
A126: NRIO Siddartha Metal Fabricators Faridabad Haryana | B126: Novemeber 2025 | C126: 77638 | D126: =C126-R126-J126-L126-P126-AB126-AR126-AL126 -> 76995 | E126: =D126/C126 -> 0.99171797 | F126: =C126-D126 -> 643 | G126: =F126/$C126 -> 0.0082820268 | I126: =H126/$C126 -> 0 | J126: 52 | K126: =J126/$C126 -> 0.00066977511 | L126: 32 | M126: =L126/$C126 -> 0.0004121693 | O126: =N126/$C126 -> 0 | P126: 0 | Q126: =P126/$C126 -> 0 | R126: 0 | S126: =R126/$C126 -> 0 | T126: 0 | U126: =T126/$C126 -> 0 | W126: =V126/$C126 -> 0 | Y126: =X126/$C126 -> 0 | AA126: =Z126/$C126 -> 0 | AB126: 51 | AC126: =AB126/$C126 -> 0.00065689482 | AE126: =AD126/$C126 -> 0 | AG126: =AF126/$C126 -> 0 | AI126: =AH126/$C$3 -> 0 | AK126: =AJ126/$C126 -> 0 | AL126: 0 | AM126: =AL126/$C126 -> 0 | AO126: =AN126/$C126 -> 0 | AQ126: =AP126/$C126 -> 0 | AR126: 508 | AS126: =AR126/$C126 -> 0.0065431876 | AU126: =AT126/$C126 -> 0
A127: NRIO Super Steels Mohali Punjab | B127: July 2025 | C127: 22640 | D127: =C127-R127-J127-L127-P127-AB127-AR127-AL127 -> 22618 | E127: =D127/C127 -> 0.99902827 | F127: =C127-D127 -> 22 | G127: =F127/$C127 -> 0.00097173145 | I127: =H127/$C127 -> 0 | J127: 0 | K127: =J127/$C127 -> 0 | L127: 22 | M127: =L127/$C127 -> 0.00097173145 | O127: =N127/$C127 -> 0 | P127: 0 | Q127: =P127/$C127 -> 0 | R127: 0 | S127: =R127/$C127 -> 0 | U127: =T127/$C127 -> 0 | W127: =V127/$C127 -> 0 | Y127: =X127/$C127 -> 0 | AA127: =Z127/$C127 -> 0 | AB127: 0 | AC127: =AB127/$C127 -> 0 | AE127: =AD127/$C127 -> 0 | AG127: =AF127/$C127 -> 0 | AI127: =AH127/$C$3 -> 0 | AK127: =AJ127/$C127 -> 0 | AL127: 0 | AM127: =AL127/$C127 -> 0 | AO127: =AN127/$C127 -> 0 | AQ127: =AP127/$C127 -> 0 | AR127: 0 | AS127: =AR127/$C127 -> 0 | AU127: =AT127/$C127 -> 0
A128: NRIO Super Steels Mohali Punjab | B128: August 2025 | C128: 46850 | D128: =C128-R128-J128-L128-P128-AB128-AR128-AL128 -> 46756 | E128: =D128/C128 -> 0.9979936 | F128: =C128-D128 -> 94 | G128: =F128/$C128 -> 0.0020064034 | I128: =H128/$C128 -> 0 | J128: 26 | K128: =J128/$C128 -> 0.00055496265 | L128: 36 | M128: =L128/$C128 -> 0.00076840982 | O128: =N128/$C128 -> 0 | P128: 0 | Q128: =P128/$C128 -> 0 | R128: 0 | S128: =R128/$C128 -> 0 | U128: =T128/$C128 -> 0 | W128: =V128/$C128 -> 0 | Y128: =X128/$C128 -> 0 | AA128: =Z128/$C128 -> 0 | AB128: 19 | AC128: =AB128/$C128 -> 0.00040554963 | AE128: =AD128/$C128 -> 0 | AG128: =AF128/$C128 -> 0 | AI128: =AH128/$C$3 -> 0 | AK128: =AJ128/$C128 -> 0 | AL128: 0 | AM128: =AL128/$C128 -> 0 | AO128: =AN128/$C128 -> 0 | AQ128: =AP128/$C128 -> 0 | AR128: 13 | AS128: =AR128/$C128 -> 0.00027748132 | AU128: =AT128/$C128 -> 0
A129: NRIO Super Steels Mohali Punjab | B129: September 2025 | C129: 109376 | D129: =C129-R129-J129-L129-P129-AB129-AR129-AL129 -> 109075 | E129: =D129/C129 -> 0.99724803 | F129: =C129-D129 -> 301 | G129: =F129/$C129 -> 0.0027519748 | I129: =H129/$C129 -> 0 | J129: 76 | K129: =J129/$C129 -> 0.00069485079 | L129: 85 | M129: =L129/$C129 -> 0.00077713575 | O129: =N129/$C129 -> 0 | P129: 0 | Q129: =P129/$C129 -> 0 | R129: 0 | S129: =R129/$C129 -> 0 | U129: =T129/$C129 -> 0 | W129: =V129/$C129 -> 0 | Y129: =X129/$C129 -> 0 | AA129: =Z129/$C129 -> 0 | AB129: 75 | AC129: =AB129/$C129 -> 0.00068570802 | AE129: =AD129/$C129 -> 0 | AG129: =AF129/$C129 -> 0 | AI129: =AH129/$C$3 -> 0 | AK129: =AJ129/$C129 -> 0 | AL129: 0 | AM129: =AL129/$C129 -> 0 | AO129: =AN129/$C129 -> 0 | AQ129: =AP129/$C129 -> 0 | AR129: 65 | AS129: =AR129/$C129 -> 0.00059428028 | AU129: =AT129/$C129 -> 0
A130: NRIO Super Steels Mohali Punjab | B130: October 2025 | C130: 60342 | D130: =C130-R130-J130-L130-P130-AB130-AR130-AL130 -> 60125 | E130: =D130/C130 -> 0.99640383 | F130: =C130-D130 -> 217 | G130: =F130/$C130 -> 0.0035961685 | I130: =H130/$C130 -> 0 | J130: 51 | K130: =J130/$C130 -> 0.00084518246 | L130: 47 | M130: =L130/$C130 -> 0.00077889364 | O130: =N130/$C130 -> 0 | P130: 0 | Q130: =P130/$C130 -> 0 | R130: 0 | S130: =R130/$C130 -> 0 | U130: =T130/$C130 -> 0 | W130: =V130/$C130 -> 0 | Y130: =X130/$C130 -> 0 | AA130: =Z130/$C130 -> 0 | AB130: 46 | AC130: =AB130/$C130 -> 0.00076232143 | AE130: =AD130/$C130 -> 0 | AG130: =AF130/$C130 -> 0 | AI130: =AH130/$C$3 -> 0 | AK130: =AJ130/$C130 -> 0 | AL130: 0 | AM130: =AL130/$C130 -> 0 | AO130: =AN130/$C130 -> 0 | AQ130: =AP130/$C130 -> 0 | AR130: 73 | AS130: =AR130/$C130 -> 0.001209771 | AU130: =AT130/$C130 -> 0
A131: NRIO Vedkiran Steel Industries Pvt. Ltd. Batala Punjab | B131: April 2025 | C131: 23654 | D131: =C131-R131-J131-L131-P131-AB131-AR131-AL131 -> 23642 | E131: =D131/C131 -> 0.99949269 | F131: =C131-D131 -> 12 | G131: =F131/$C131 -> 0.00050731377 | I131: =H131/$C131 -> 0 | J131: 4 | K131: =J131/$C131 -> 0.00016910459 | L131: 0 | M131: =L131/$C131 -> 0 | O131: =N131/$C131 -> 0 | P131: 0 | Q131: =P131/$C131 -> 0 | R131: 0 | S131: =R131/$C131 -> 0 | U131: =T131/$C131 -> 0 | W131: =V131/$C131 -> 0 | Y131: =X131/$C131 -> 0 | AA131: =Z131/$C131 -> 0 | AB131: 8 | AC131: =AB131/$C131 -> 0.00033820918 | AE131: =AD131/$C131 -> 0 | AG131: =AF131/$C131 -> 0 | AI131: =AH131/$C$3 -> 0 | AK131: =AJ131/$C131 -> 0 | AL131: 0 | AM131: =AL131/$C131 -> 0 | AO131: =AN131/$C131 -> 0 | AQ131: =AP131/$C131 -> 0 | AR131: 0 | AS131: =AR131/$C131 -> 0 | AU131: =AT131/$C131 -> 0
A132: NRIO Vedkiran Steel Industries Pvt. Ltd. Batala Punjab | B132: May 2025 | C132: 184539 | D132: =C132-R132-J132-L132-P132-AB132-AR132-AL132 -> 184403 | E132: =D132/C132 -> 0.99926303 | F132: =C132-D132 -> 136 | G132: =F132/$C132 -> 0.00073697159 | I132: =H132/$C132 -> 0 | J132: 59 | K132: =J132/$C132 -> 0.00031971562 | L132: 11 | M132: =L132/$C132 -> 5.9607996e-05 | O132: =N132/$C132 -> 0 | P132: 0 | Q132: =P132/$C132 -> 0 | R132: 0 | S132: =R132/$C132 -> 0 | U132: =T132/$C132 -> 0 | W132: =V132/$C132 -> 0 | Y132: =X132/$C132 -> 0 | AA132: =Z132/$C132 -> 0 | AB132: 66 | AC132: =AB132/$C132 -> 0.00035764798 | AE132: =AD132/$C132 -> 0 | AG132: =AF132/$C132 -> 0 | AI132: =AH132/$C$3 -> 0 | AK132: =AJ132/$C132 -> 0 | AL132: 0 | AM132: =AL132/$C132 -> 0 | AO132: =AN132/$C132 -> 0 | AQ132: =AP132/$C132 -> 0 | AR132: 0 | AS132: =AR132/$C132 -> 0 | AU132: =AT132/$C132 -> 0
A133: NRIO Vedkiran Steel Industries Pvt. Ltd. Batala Punjab | B133: June 2025 | C133: 41934 | D133: =C133-R133-J133-L133-P133-AB133-AR133-AL133 -> 41825 | E133: =D133/C133 -> 0.99740068 | F133: =C133-D133 -> 109 | G133: =F133/$C133 -> 0.0025993227 | I133: =H133/$C133 -> 0 | J133: 31 | K133: =J133/$C133 -> 0.00073925693 | L133: 29 | M133: =L133/$C133 -> 0.00069156293 | O133: =N133/$C133 -> 0 | P133: 0 | Q133: =P133/$C133 -> 0 | R133: 0 | S133: =R133/$C133 -> 0 | U133: =T133/$C133 -> 0 | W133: =V133/$C133 -> 0 | Y133: =X133/$C133 -> 0 | AA133: =Z133/$C133 -> 0 | AB133: 28 | AC133: =AB133/$C133 -> 0.00066771593 | AE133: =AD133/$C133 -> 0 | AG133: =AF133/$C133 -> 0 | AI133: =AH133/$C$3 -> 0 | AK133: =AJ133/$C133 -> 0 | AL133: 0 | AM133: =AL133/$C133 -> 0 | AO133: =AN133/$C133 -> 0 | AQ133: =AP133/$C133 -> 0 | AR133: 21 | AS133: =AR133/$C133 -> 0.00050078695 | AU133: =AT133/$C133 -> 0
A134: NRIO Vedkiran Steel Industries Pvt. Ltd. Batala Punjab | B134: July 2025 | C134: 146597 | D134: =C134-R134-J134-L134-P134-AB134-AR134-AL134 -> 146056 | E134: =D134/C134 -> 0.99630961 | F134: =C134-D134 -> 541 | G134: =F134/$C134 -> 0.0036903893 | I134: =H134/$C134 -> 0 | J134: 114 | K134: =J134/$C134 -> 0.00077764211 | L134: 98 | M134: =L134/$C134 -> 0.00066849936 | O134: =N134/$C134 -> 0 | P134: 0 | Q134: =P134/$C134 -> 0 | R134: 0 | S134: =R134/$C134 -> 0 | U134: =T134/$C134 -> 0 | W134: =V134/$C134 -> 0 | Y134: =X134/$C134 -> 0 | AA134: =Z134/$C134 -> 0 | AB134: 92 | AC134: =AB134/$C134 -> 0.00062757082 | AE134: =AD134/$C134 -> 0 | AG134: =AF134/$C134 -> 0 | AI134: =AH134/$C$3 -> 0 | AK134: =AJ134/$C134 -> 0 | AL134: 0 | AM134: =AL134/$C134 -> 0 | AO134: =AN134/$C134 -> 0 | AQ134: =AP134/$C134 -> 0 | AR134: 237 | AS134: =AR134/$C134 -> 0.001616677 | AU134: =AT134/$C134 -> 0
A135: NRIO Vedkiran Steel Industries Pvt. Ltd. Batala Punjab | B135: September 2025 | C135: 168616 | D135: =C135-R135-J135-L135-P135-AB135-AR135-AL135 -> 168024 | E135: =D135/C135 -> 0.99648906 | F135: =C135-D135 -> 592 | G135: =F135/$C135 -> 0.0035109361 | I135: =H135/$C135 -> 0 | J135: 114 | K135: =J135/$C135 -> 0.00067609242 | L135: 83 | M135: =L135/$C135 -> 0.00049224273 | O135: =N135/$C135 -> 0 | P135: 0 | Q135: =P135/$C135 -> 0 | R135: 0 | S135: =R135/$C135 -> 0 | U135: =T135/$C135 -> 0 | W135: =V135/$C135 -> 0 | Y135: =X135/$C135 -> 0 | AA135: =Z135/$C135 -> 0 | AB135: 105 | AC135: =AB135/$C135 -> 0.00062271671 | AE135: =AD135/$C135 -> 0 | AG135: =AF135/$C135 -> 0 | AI135: =AH135/$C$3 -> 0 | AK135: =AJ135/$C135 -> 0 | AL135: 0 | AM135: =AL135/$C135 -> 0 | AO135: =AN135/$C135 -> 0 | AQ135: =AP135/$C135 -> 0 | AR135: 290 | AS135: =AR135/$C135 -> 0.0017198842 | AU135: =AT135/$C135 -> 0
A136: NRIO Vedkiran Steel Industries Pvt. Ltd. Batala Punjab | B136: October 2025 | C136: 131433 | D136: =C136-R136-J136-L136-P136-AB136-AR136-AL136 -> 130878 | E136: =D136/C136 -> 0.99577732 | F136: =C136-D136 -> 555 | G136: =F136/$C136 -> 0.0042226838 | I136: =H136/$C136 -> 0 | J136: 86 | K136: =J136/$C136 -> 0.00065432578 | L136: 66 | M136: =L136/$C136 -> 0.00050215699 | O136: =N136/$C136 -> 0 | P136: 0 | Q136: =P136/$C136 -> 0 | R136: 0 | S136: =R136/$C136 -> 0 | U136: =T136/$C136 -> 0 | W136: =V136/$C136 -> 0 | Y136: =X136/$C136 -> 0 | AA136: =Z136/$C136 -> 0 | AB136: 84 | AC136: =AB136/$C136 -> 0.0006391089 | AE136: =AD136/$C136 -> 0 | AG136: =AF136/$C136 -> 0 | AI136: =AH136/$C$3 -> 0 | AK136: =AJ136/$C136 -> 0 | AL136: 0 | AM136: =AL136/$C136 -> 0 | AO136: =AN136/$C136 -> 0 | AQ136: =AP136/$C136 -> 0 | AR136: 319 | AS136: =AR136/$C136 -> 0.0024270921 | AU136: =AT136/$C136 -> 0
A137: NRIO Vedkiran Steel Industries Pvt. Ltd. Batala Punjab | B137: Novemeber 2025 | C137: 115784 | D137: =C137-R137-J137-L137-P137-AB137-AR137-AL137 -> 115254 | E137: =D137/C137 -> 0.99542251 | F137: =C137-D137 -> 530 | G137: =F137/$C137 -> 0.0045774891 | I137: =H137/$C137 -> 0 | J137: 69 | K137: =J137/$C137 -> 0.00059593726 | L137: 45 | M137: =L137/$C137 -> 0.00038865474 | O137: =N137/$C137 -> 0 | P137: 42 | Q137: =P137/$C137 -> 0.00036274442 | R137: 14 | S137: =R137/$C137 -> 0.00012091481 | U137: =T137/$C137 -> 0 | W137: =V137/$C137 -> 0 | Y137: =X137/$C137 -> 0 | AA137: =Z137/$C137 -> 0 | AB137: 67 | AC137: =AB137/$C137 -> 0.00057866372 | AE137: =AD137/$C137 -> 0 | AG137: =AF137/$C137 -> 0 | AI137: =AH137/$C$3 -> 0 | AK137: =AJ137/$C137 -> 0 | AL137: 0 | AM137: =AL137/$C137 -> 0 | AO137: =AN137/$C137 -> 0 | AQ137: =AP137/$C137 -> 0 | AR137: 293 | AS137: =AR137/$C137 -> 0.0025305742 | AU137: =AT137/$C137 -> 0
A138: SRIO Patil Rail Infrastructure pvt ltd Yellampet, Hyderabad Telangana | B138: April 2025 | C138: 266898 | D138: 266559 | E138: =D138/C138 -> 0.99872985 | F138: 339 | G138: =F138/$C138 -> 0.0012701481 | I138: =H138/$C138 -> 0 | J138: 162 | K138: =J138/$C138 -> 0.00060697345 | L138: 25 | M138: =L138/$C138 -> 9.3668742e-05 | O138: =N138/$C138 -> 0 | P138: 52 | Q138: =P138/$C138 -> 0.00019483098 | R138: 65 | S138: =R138/$C138 -> 0.00024353873 | T138: 10 | U138: =T138/$C138 -> 3.7467497e-05 | W138: =V138/$C138 -> 0 | Y138: =X138/$C138 -> 0 | AA138: =Z138/$C138 -> 0 | AB138: 0 | AC138: =AB138/$C138 -> 0 | AE138: =AD138/$C138 -> 0 | AG138: =AF138/$C138 -> 0 | AI138: =AH138/$C$3 -> 0 | AK138: =AJ138/$C138 -> 0 | AL138: 5 | AM138: =AL138/$C138 -> 1.8733748e-05 | AO138: =AN138/$C138 -> 0 | AQ138: =AP138/$C138 -> 0 | AR138: 40 | AS138: =AR138/$C138 -> 0.00014986999 | AU138: =AT138/$C138 -> 0
A139: SRIO Patil Rail Infrastructure pvt ltd Yellampet, Hyderabad Telangana | B139: May 2025 | C139: 227475 | D139: 227320 | E139: =D139/C139 -> 0.99931861 | F139: 155 | G139: =F139/$C139 -> 0.00068139356 | I139: =H139/$C139 -> 0 | J139: 50 | K139: =J139/$C139 -> 0.00021980437 | L139: 5 | M139: =L139/$C139 -> 2.1980437e-05 | O139: =N139/$C139 -> 0 | P139: 35 | Q139: =P139/$C139 -> 0.00015386306 | R139: 42 | S139: =R139/$C139 -> 0.00018463567 | T139: 3 | U139: =T139/$C139 -> 1.3188262e-05 | W139: =V139/$C139 -> 0 | Y139: =X139/$C139 -> 0 | AA139: =Z139/$C139 -> 0 | AB139: 0 | AC139: =AB139/$C139 -> 0 | AE139: =AD139/$C139 -> 0 | AG139: =AF139/$C139 -> 0 | AI139: =AH139/$C$3 -> 0 | AK139: =AJ139/$C139 -> 0 | AL139: 2 | AM139: =AL139/$C139 -> 8.792175e-06 | AO139: =AN139/$C139 -> 0 | AQ139: =AP139/$C139 -> 0 | AR139: 18 | AS139: =AR139/$C139 -> 7.9129575e-05 | AU139: =AT139/$C139 -> 0
...

Sheet Sheet9
A2: Month | B2: SUM of Inspected (Nos.) | C2: SUM of Rejection (Nos.)
A3: April 2025 | B3: 1506353 | C3: 5457
A4: August 2025 | B4: 668907 | C4: 2157
A5: December 2025 | B5: 5793933 | C5: 68151
A6: December 2025, Jan 2026 | B6: 22694 | C6: 256
A7: Jan 2025 | B7: 43443 | C7: 185
A8: Jan 2026 | B8: 5899133 | C8: 66817
A9: July 2025 | B9: 391590 | C9: 2409
A10: June 2025 | B10: 1521721 | C10: 8166
A11: May 2025 | B11: 511436 | C11: 1914
A12: Novemeber 2025 | B12: 2293294 | C12: 21750
A13: October 2025 | B13: 315652 | C13: 1076
A14: September 2025 | B14: 168616 | C14: 592
A15: Grand Total | B15: 19136772 | C15: 178930

Sheet Detail1-December 2025
A1: Firm Name | B1: Month | C1: PO Number | D1: Zonal Railway | E1: Consignee Details | F1: Inspected (Nos.) | G1: Acceptance (Nos.) | H1: % Acceptance | I1: Rejection (Nos.) | J1: % Rejection | K1: Visual (Sheared Edges, Surface Defects) | L1: %Visual (Sheared Edges, Surface Defects) | M1: Dimensional | N1: %Dimensional | O1: Cut bar length | P1: %Cut bar length | Q1: Cut Bar diameter | R1: %Cut Bar diameter | S1: Turning length | T1: %Turning length | U1: Turning Bar Diameter | V1: %Turning Bar Diameter | W1: Flat Bearing Area | X1: %Flat Bearing Area | Y1: Application & Deflection test | Z1: %Application & Deflection test | AA1: Chemical Composition | AB1: %Chemical Composition | AC1: Toe load | AD1: %Toe load | AE1: Hardness | AF1: %Hardness | AG1: Microstructure | AH1: %Microstructure | AI1: Grain size | AJ1: %Grain size | AK1: Depth of Decarburization | AL1: %Depth of Decarburization | AM1: Inclusion rating | AN1: %Inclusion rating | AO1: MPI | AP1: %MPI | AQ1: Forging defect | AR1: %Forging defect | AS1: Marking | AT1: %Marking | AU1: Embossing Die Impression / Failure | AV1: %Embossing Die Impression / Failure | AW1: Other (less weight) | AX1: %Other (less weight)
A2: ERIO AMBE FASTNERS PVT.LTD. Patna Bihar | B2: December 2025 | F2: 0 | G2: 0 | H2: #DIV/0! | J2: #DIV/0! | L2: 0 | N2: #DIV/0! | P2: 0 | R2: 0 | T2: 0 | V2: 0 | X2: 0 | Z2: 0 | AB2: 0 | AD2: 0 | AF2: 0 | AH2: 0 | AJ2: 0 | AL2: 0 | AN2: 0 | AP2: 0 | AR2: 0 | AT2: 0 | AV2: 0 | AX2: 0
A3: ERIO CALCUTTA SPRINGS LTD. Howrah West Bengal | B3: December 2025 | F3: 375049 | G3: 372076 | H3: 0.99207304 | I3: 2973 | J3: 0.0079269642 | K3: 10 | L3: 4.6218837e-05 | M3: 394 | N3: 0.0010505294 | O3: 458 | P3: 0.0021168227 | R3: 0 | S3: 262 | T3: 0.0012109335 | U3: 49 | V3: 0.0002264723 | W3: 2 | X3: 9.2437674e-06 | Z3: 0 | AB3: 0 | AC3: 105 | AD3: 0.00048529779 | AE3: 118 | AF3: 0.00054538228 | AH3: 0 | AJ3: 0 | AL3: 0 | AN3: 0 | AO3: 56 | AP3: 0.00025882549 | AQ3: 535 | AR3: 0.0024727078 | AT3: 0 | AU3: 705 | AV3: 0.003258428 | AW3: 279 | AX3: 0.0012895056
A4: ERIO KALIMATA ISPAT (Unit-1) Howrah West Bengal | B4: December 2025 | F4: 195702 | G4: 192449 | H4: 0.98337779 | I4: 3253 | J4: 0.016622211 | K4: 145 | L4: 0.00067017314 | M4: 728 | N4: 0.0037199415 | O4: 77 | P4: 0.00035588504 | Q4: 25 | R4: 0.00011554709 | S4: 51 | T4: 0.00023571607 | U4: 755 | V4: 0.0034895222 | W4: 0 | X4: 0 | Z4: 0 | AB4: 0 | AD4: 0 | AE4: 0 | AF4: 0 | AH4: 0 | AJ4: 0 | AL4: 0 | AN4: 0 | AP4: 0 | AQ4: 722 | AR4: 0.003337 | AT4: 0 | AU4: 690 | AV4: 0.0031890997 | AW4: 60 | AX4: 0.00027731302
A5: ERIO KALIMATA ISPAT (Unit-II) Durgapur West Bengal | B5: December 2025 | F5: 423755 | G5: 420203 | H5: 0.9916178 | I5: 3552 | J5: 0.008382202 | K5: 0 | L5: 0 | M5: 44 | N5: 0.00010383358 | O5: 400 | P5: 0.0018487535 | Q5: 0 | R5: 0 | S5: 1420 | T5: 0.0065630748 | U5: 1375 | V5: 0.0063550901 | W5: 0 | X5: 0 | Z5: 0 | AB5: 0 | AD5: 0 | AE5: 22 | AF5: 0.00010168144 | AH5: 0 | AJ5: 0 | AL5: 0 | AN5: 0 | AO5: 3 | AP5: 1.3865651e-05 | AQ5: 258 | AR5: 0.001192446 | AS5: 0 | AT5: 0 | AU5: 0 | AV5: 0 | AW5: 30 | AX5: 0.00013865651
A6: ERIO KALIMATA VYAPAAR (Unit-II) Durgapur West Bengal | B6: December 2025 | F6: 501848 | G6: 495148 | H6: 0.98664934 | I6: 6700 | J6: 0.013350656 | K6: 0 | L6: 0 | M6: 344 | N6: 0.00068546652 | O6: 933 | P6: 0.0043122175 | Q6: 0 | R6: 0 | S6: 2030 | T6: 0.0093824239 | U6: 1877 | V6: 0.0086752757 | W6: 0 | X6: 0 | Z6: 0 | AB6: 0 | AD6: 0 | AE6: 49 | AF6: 0.0002264723 | AH6: 0 | AJ6: 0 | AL6: 0 | AN6: 0 | AO6: 0 | AP6: 0 | AQ6: 1347 | AR6: 0.0062256773 | AS6: 55 | AT6: 0.0002542036 | AU6: 0 | AV6: 0 | AW6: 65 | AX6: 0.00030042244
A7: ERIO KDS ENGG. PVT. LTD. Howrah West Bengal | B7: December 2025 | F7: 0 | G7: 0 | H7: #DIV/0! | I7: 0 | J7: #DIV/0! | L7: 0 | N7: #DIV/0! | P7: 0 | R7: 0 | T7: 0 | V7: 0 | X7: 0 | Z7: 0 | AB7: 0 | AD7: 0 | AF7: 0 | AH7: 0 | AJ7: 0 | AL7: 0 | AN7: 0 | AP7: 0 | AR7: 0 | AT7: 0 | AV7: 0 | AX7: 0
A8: ERIO KRISHNA INFRATECH Jharsuguda Odisha | B8: December 2025 | F8: 228724 | G8: 226410 | H8: 0.989883 | I8: 2314 | J8: 0.010116997 | L8: 0 | M8: 1081 | N8: 0.0047262202 | O8: 466 | P8: 0.0021537978 | R8: 0 | T8: 0 | U8: 431 | V8: 0.0019920319 | X8: 0 | Z8: 0 | AB8: 0 | AD8: 0 | AF8: 0 | AH8: 0 | AJ8: 0 | AL8: 0 | AN8: 0 | AO8: 58 | AP8: 0.00026806925 | AQ8: 236 | AR8: 0.0010907646 | AT8: 0 | AU8: 42 | AV8: 0.00019411912 | AX8: 0
A9: ERIO KSE ELECTRICALS PVT LTD Howrah West Bengal | B9: December 2025 | F9: 641496 | G9: 635630 | H9: 0.99085575 | I9: 5866 | J9: 0.0091442503 | K9: 377 | L9: 0.0017424502 | M9: 671 | N9: 0.0010459925 | O9: 5 | P9: 2.3109418e-05 | Q9: 0 | R9: 0 | S9: 732 | T9: 0.0033832189 | U9: 1566 | V9: 0.0072378699 | W9: 379 | X9: 0.0017516939 | Y9: 0 | Z9: 0 | AA9: 0 | AB9: 0 | AC9: 374 | AD9: 0.0017285845 | AE9: 0 | AF9: 0 | AG9: 0 | AH9: 0 | AI9: 0 | AJ9: 0 | AK9: 0 | AL9: 0 | AM9: 0 | AN9: 0 | AO9: 11 | AP9: 5.0840721e-05 | AQ9: 568 | AR9: 0.0026252299 | AS9: 393 | AT9: 0.0018164003 | AU9: 790 | AV9: 0.0036512881 | AW9: 0 | AX9: 0
A10: ERIO LNVS INFRA PVT. LTD Tatanagar Jharkhand | B10: December 2025 | F10: 140773 | G10: 137864 | H10: 0.97933553 | I10: 2909 | J10: 0.020664474 | K10: 657 | L10: 0.0030365776 | M10: 842 | N10: 0.0059812606 | O10: 61 | P10: 0.00028193491 | R10: 0 | S10: 305 | T10: 0.0014096745 | U10: 19 | V10: 8.781579e-05 | W10: 10 | X10: 4.6218837e-05 | Z10: 0 | AB10: 0 | AD10: 0 | AE10: 765 | AF10: 0.003535741 | AH10: 0 | AJ10: 0 | AL10: 0 | AN10: 0 | AP10: 0 | AQ10: 250 | AR10: 0.0011554709 | AT10: 0 | AV10: 0 | AX10: 0
A11: ERIO Surya Alloys Industries Limited Durgapur West Bengal | B11: December 2025 | F11: 1867938 | G11: 1836599 | H11: 0.98322268 | I11: 31339 | J11: 0.016777323 | K11: 417 | L11: 0.0019273255 | M11: 2211 | N11: 0.0011836581 | O11: 2467 | P11: 0.011402187 | R11: 0 | S11: 5133 | T11: 0.023724129 | U11: 8251 | V11: 0.038135162 | X11: 0 | Z11: 0 | AB11: 0 | AD11: 0 | AE11: 571 | AF11: 0.0026390956 | AH11: 0 | AJ11: 0 | AL11: 0 | AN11: 0 | AO11: 1457 | AP11: 0.0067340845 | AQ11: 10545 | AR11: 0.048737764 | AT11: 0 | AU11: 287 | AV11: 0.0013264806 | AX11: 0
A12: ERIO TECHMA ENGG. Howrah West Bengal | B12: December 2025 | F12: 0 | G12: 0 | H12: #DIV/0! | I12: 0 | J12: #DIV/0! | L12: 0 | N12: #DIV/0! | P12: 0 | R12: 0 | T12: 0 | V12: 0 | X12: 0 | Z12: 0 | AB12: 0 | AD12: 0 | AF12: 0 | AH12: 0 | AJ12: 0 | AL12: 0 | AN12: 0 | AP12: 0 | AR12: 0 | AT12: 0 | AV12: 0 | AX12: 0
A13: ERIO UTKARSH INDIA LIMITED Howrah West Bengal | B13: December 2025 | F13: 0 | G13: 0 | H13: #DIV/0! | J13: #DIV/0! | L13: 0 | N13: #DIV/0! | P13: 0 | R13: 0 | T13: 0 | V13: 0 | X13: 0 | Z13: 0 | AB13: 0 | AD13: 0 | AF13: 0 | AH13: 0 | AJ13: 0 | AL13: 0 | AN13: 0 | AP13: 0 | AR13: 0 | AT13: 0 | AV13: 0 | AX13: 0
A14: NRIO Adinath Industries Bhiwadi Haryana | B14: December 2025 | C14: 63245440202943 | D14: North Central | F14: 61300 | G14: 60847 | H14: 0.99261011 | I14: 453 | J14: 0.0073898858 | K14: 0 | L14: 0 | M14: 59 | N14: 0.00096247961 | O14: 54 | P14: 0.00024958172 | Q14: 0 | R14: 0 | S14: 49 | T14: 0.0002264723 | V14: 0 | W14: 68 | X14: 0.00031428809 | Z14: 0 | AB14: 0 | AD14: 0 | AE14: 44 | AF14: 0.00020336288 | AH14: 0 | AJ14: 0 | AL14: 0 | AN14: 0 | AO14: 0 | AP14: 0 | AR14: 0 | AT14: 0 | AU14: 179 | AV14: 0.00082731718 | AW14: 0 | AX14: 0
A15: NRIO Adinath Industries Bhiwadi Haryana | B15: December 2025 | C15: 63255372202188 | D15: North Western | F15: 223258 | G15: 221479 | H15: 0.99203164 | I15: 1779 | J15: 0.0079683595 | K15: 0 | L15: 0 | M15: 222 | N15: 0.00099436526 | O15: 214 | P15: 0.00098908311 | Q15: 0 | R15: 0 | S15: 201 | T15: 0.00092899862 | V15: 0 | W15: 202 | X15: 0.00093362051 | Z15: 0 | AB15: 0 | AD15: 0 | AE15: 189 | AF15: 0.00087353602 | AH15: 0 | AJ15: 0 | AL15: 0 | AN15: 0 | AO15: 0 | AP15: 0 | AR15: 0 | AT15: 0 | AU15: 751 | AV15: 0.0034710347 | AW15: 0 | AX15: 0
A16: NRIO Adinath Industries INC Bhiwadi Haryana | B16: December 2025 | C16: 63255372202187 | D16: North Western | F16: 304516 | G16: 302789 | H16: 0.99432871 | I16: 1727 | J16: 0.0056712948 | K16: 0 | L16: 0 | M16: 213 | N16: 0.00069947064 | O16: 197 | P16: 0.00091051109 | Q16: 0 | R16: 0 | S16: 151 | T16: 0.00069790444 | U16: 67 | V16: 0.00030966621 | X16: 0 | Z16: 0 | AB16: 0 | AD16: 0 | AE16: 198 | AF16: 0.00091513297 | AH16: 0 | AJ16: 0 | AL16: 0 | AN16: 0 | AO16: 0 | AP16: 0 | AR16: 0 | AT16: 0 | AU16: 901 | AV16: 0.0041643172 | AW16: 0 | AX16: 0
A17: NRIO Avdesh Tracks(P) Ltd. Mohali Punjab | B17: December 2025 | C17: 7254988202253 | D17: East Central | F17: 172153 | G17: 171235 | H17: 0.99466753 | I17: 918 | J17: 0.0053324659 | K17: 0 | L17: 0 | M17: 151 | N17: 0.00087712674 | O17: 155 | P17: 0.00071639197 | Q17: 0 | R17: 0 | S17: 113 | T17: 0.00052227286 | U17: 53 | V17: 0.00024495984 | X17: 0 | Z17: 0 | AB17: 0 | AD17: 0 | AE17: 114 | AF17: 0.00052689474 | AH17: 0 | AJ17: 0 | AL17: 0 | AN17: 0 | AO17: 0 | AP17: 0 | AR17: 0 | AT17: 0 | AU17: 332 | AV17: 0.0015344654 | AW17: 0 | AX17: 0
A18: NRIO Avdesh Tracks(P) Ltd. Mohali Punjab | B18: December 2025 | C18: 81246420101886 | D18: West Central | F18: 5600 | G18: 5569 | H18: 0.99446429 | I18: 31 | J18: 0.0055357143 | K18: 0 | L18: 0 | M18: 6 | N18: 0.0010714286 | O18: 5 | P18: 2.3109418e-05 | Q18: 0 | R18: 0 | T18: 0 | V18: 0 | X18: 0 | Z18: 0 | AB18: 0 | AD18: 0 | AE18: 5 | AF18: 2.3109418e-05 | AH18: 0 | AJ18: 0 | AL18: 0 | AN18: 0 | AO18: 0 | AP18: 0 | AR18: 0 | AT18: 0 | AU18: 15 | AV18: 6.9328255e-05 | AW18: 0 | AX18: 0
A19: NRIO Bimla Rail Fasteners Karnal Haryana | B19: December 2025 | C19: 77255086207678 | D19: Northern | F19: 45220 | G19: 45040 | H19: 0.99601946 | I19: 180 | J19: 0.0039805396 | K19: 0 | L19: 0 | M19: 26 | N19: 0.00057496683 | O19: 40 | P19: 0.00018487535 | Q19: 0 | R19: 0 | S19: 23 | T19: 0.00010630332 | U19: 8 | V19: 3.697507e-05 | X19: 0 | Z19: 0 | AB19: 0 | AD19: 0 | AE19: 27 | AF19: 0.00012479086 | AH19: 0 | AJ19: 0 | AL19: 0 | AN19: 0 | AO19: 0 | AP19: 0 | AR19: 0 | AT19: 0 | AU19: 56 | AV19: 0.00025882549 | AW19: 0 | AX19: 0
A20: NRIO Bimla Rail Fasteners Karnal Haryana | B20: December 2025 | C20: 77255086207679 | D20: Northern | F20: 36436 | G20: 36270 | H20: 0.99544407 | I20: 166 | J20: 0.0045559337 | K20: 0 | L20: 0 | M20: 23 | N20: 0.00063124382 | O20: 35 | P20: 0.00016176593 | Q20: 0 | R20: 0 | S20: 28 | T20: 0.00012941274 | V20: 0 | X20: 0 | Z20: 0 | AB20: 0 | AD20: 0 | AE20: 20 | AF20: 9.2437674e-05 | AH20: 0 | AJ20: 0 | AL20: 0 | AN20: 0 | AO20: 0 | AP20: 0 | AR20: 0 | AT20: 0 | AU20: 60 | AV20: 0.00027731302 | AW20: 0 | AX20: 0
A21: NRIO Bimla Rail Fasteners Karnal Haryana | B21: December 2025 | C21: 77255086207680 | D21: Northern | F21: 29237 | G21: 29109 | H21: 0.99562199 | I21: 128 | J21: 0.0043780142 | K21: 0 | L21: 0 | M21: 15 | N21: 0.00051304853 | O21: 27 | P21: 0.00012479086 | Q21: 0 | R21: 0 | S21: 20 | T21: 9.2437674e-05 | V21: 0 | X21: 0 | Z21: 0 | AB21: 0 | AD21: 0 | AE21: 15 | AF21: 6.9328255e-05 | AH21: 0 | AJ21: 0 | AL21: 0 | AN21: 0 | AO21: 0 | AP21: 0 | AR21: 0 | AT21: 0 | AU21: 51 | AV21: 0.00023571607 | AW21: 0 | AX21: 0
A22: NRIO Fateh Chand Jain Faridabad Haryana | B22: December 2025 | C22: 51245071203888 | D22: Central | F22: 54772 | G22: 53974 | H22: 0.98543051 | I22: 798 | J22: 0.014569488 | K22: 0 | L22: 0 | M22: 641 | N22: 0.01170306 | O22: 0 | P22: 0 | Q22: 0 | R22: 0 | S22: 0 | T22: 0 | U22: 0 | V22: 0 | X22: 0 | Z22: 0 | AB22: 0 | AD22: 0 | AE22: 28 | AF22: 0.00012941274 | AH22: 0 | AJ22: 0 | AL22: 0 | AN22: 0 | AO22: 0 | AP22: 0 | AR22: 0 | AT22: 0 | AU22: 129 | AV22: 0.000596223 | AW22: 0 | AX22: 0
A23: NRIO Panna Lal Kanhiya Lal Bansal LLP Sonipat Haryana | B23: December 2025 | C23: 60250003103020 | D23: South Eastern | F23: 194320 | G23: 192985 | H23: 0.99312989 | I23: 1335 | J23: 0.0068701112 | K23: 0 | L23: 0 | M23: 103 | N23: 0.00053005352 | O23: 74 | P23: 0.00034201939 | Q23: 0 | R23: 0 | S23: 159 | T23: 0.00073487951 | V23: 0 | X23: 0 | Z23: 0 | AB23: 0 | AD23: 0 | AE23: 68 | AF23: 0.00031428809 | AH23: 0 | AJ23: 0 | AL23: 0 | AN23: 0 | AO23: 0 | AP23: 0 | AR23: 0 | AT23: 0 | AU23: 543 | AV23: 0.0025096828 | AW23: 0 | AX23: 0
A24: NRIO Qualite Steels Sirsa | B24: December 2025 | C24: 77255086207683 | D24: Northern | F24: 51550 | G24: 51443 | H24: 0.99792435 | I24: 107 | J24: 0.0020756547 | K24: 0 | L24: 0 | M24: 25 | N24: 0.00048496605 | O24: 27 | P24: 0.00012479086 | Q24: 0 | R24: 0 | S24: 26 | T24: 0.00012016898 | V24: 0 | X24: 0 | Z24: 0 | AB24: 0 | AD24: 0 | AE24: 17 | AF24: 7.8572023e-05 | AH24: 0 | AJ24: 0 | AL24: 0 | AN24: 0 | AO24: 0 | AP24: 0 | AR24: 0 | AT24: 0 | AU24: 12 | AV24: 5.5462604e-05 | AW24: 0 | AX24: 0
A25: NRIO Siddartha Metal Fabricators Faridabad Haryana | B25: December 2025 | C25: 6250113101698 | D25: South East Central | F25: 99046 | G25: 98177 | H25: 0.9912263 | I25: 869 | J25: 0.0087737011 | K25: 0 | L25: 0 | M25: 69 | N25: 0.000696646 | O25: 38 | P25: 0.00017563158 | Q25: 0 | R25: 0 | T25: 0 | V25: 0 | X25: 0 | Z25: 0 | AB25: 0 | AD25: 0 | AE25: 57 | AF25: 0.00026344737 | AH25: 0 | AJ25: 0 | AL25: 0 | AN25: 0 | AO25: 0 | AP25: 0 | AR25: 0 | AT25: 0 | AU25: 705 | AV25: 0.003258428 | AW25: 0 | AX25: 0
A26: NRIO Siddartha Metal Fabricators Faridabad Haryana | B26: December 2025 | C26: 26245057101751 | D26: North Eastern | F26: 22694 | G26: 22438 | H26: 0.98871949 | I26: 256 | J26: 0.011280515 | K26: 0 | L26: 0 | M26: 18 | N26: 0.00079316119 | O26: 14 | P26: 6.4706372e-05 | Q26: 0 | R26: 0 | T26: 0 | V26: 0 | X26: 0 | Z26: 0 | AB26: 0 | AD26: 0 | AE26: 13 | AF26: 6.0084488e-05 | AH26: 0 | AJ26: 0 | AL26: 0 | AN26: 0 | AO26: 0 | AP26: 0 | AR26: 0 | AT26: 0 | AU26: 211 | AV26: 0.00097521746 | AW26: 0 | AX26: 0
A27: NRIO Siddartha Metal Fabricators Faridabad Haryana | B27: December 2025 | C27: 60250004103382 | D27: South Eastern | F27: 26469 | G27: 26263 | H27: 0.99221731 | I27: 206 | J27: 0.0077826892 | K27: 0 | L27: 0 | M27: 17 | N27: 0.00064226076 | O27: 10 | P27: 4.6218837e-05 | Q27: 0 | R27: 0 | T27: 0 | V27: 0 | X27: 0 | Z27: 0 | AB27: 0 | AD27: 0 | AE27: 15 | AF27: 6.9328255e-05 | AH27: 0 | AJ27: 0 | AL27: 0 | AN27: 0 | AO27: 0 | AP27: 0 | AR27: 0 | AT27: 0 | AU27: 164 | AV27: 0.00075798893 | AW27: 0 | AX27: 0
A28: NRIO Vedkiran Steel Industries Pvt. Ltd. Batala Punjab | B28: December 2025 | C28: 77245102206898 | D28: Northern | F28: 71971 | G28: 71589 | H28: 0.99469231 | I28: 382 | J28: 0.0053076934 | K28: 0 | L28: 0 | M28: 50 | N28: 0.00069472426 | O28: 39 | P28: 0.00018025346 | Q28: 0 | R28: 0 | T28: 0 | V28: 0 | W28: 0 | X28: 0 | Z28: 0 | AB28: 0 | AD28: 0 | AE28: 53 | AF28: 0.00024495984 | AH28: 0 | AJ28: 0 | AL28: 0 | AN28: 0 | AO28: 0 | AP28: 0 | AR28: 0 | AT28: 0 | AU28: 240 | AV28: 0.0011092521 | AW28: 0 | AX28: 0
A29: NRIO Vedkiran Steel Industries Pvt. Ltd. Batala Punjab | B29: December 2025 | C29: 77255086207681 | D29: Northern | F29: 78532 | G29: 78083 | H29: 0.99428259 | I29: 449 | J29: 0.0057174146 | K29: 0 | L29: 0 | M29: 53 | N29: 0.00067488412 | O29: 25 | P29: 0.00011554709 | Q29: 0 | R29: 0 | S29: 47 | T29: 0.00021722853 | U29: 0 | V29: 0 | W29: 0 | X29: 0 | Z29: 0 | AB29: 0 | AD29: 0 | AE29: 49 | AF29: 0.0002264723 | AH29: 0 | AJ29: 0 | AL29: 0 | AN29: 0 | AO29: 0 | AP29: 0 | AR29: 0 | AT29: 0 | AU29: 275 | AV29: 0.001271018 | AW29: 0 | AX29: 0
A30: SRIO Patil Rail Infrastructure pvt ltd Yellampet, Hyderabad Telangana | B30: December 2025 | C30: 60257500205475 | D30: South Central | F30: 304352 | G30: 302822 | H30: 0.99308464 | I30: 1530 | J30: 0.0069153551 | K30: 0 | L30: 0 | M30: 10 | N30: 0.0016111042 | O30: 16 | P30: 3.697507e-05 | Q30: 0 | R30: 0 | S30: 496 | T30: 0.00041596953 | U30: 578 | V30: 0.00034664128 | W30: 0 | X30: 0 | Z30: 0 | AB30: 0 | AD30: 0 | AE30: 5 | AF30: 0 | AH30: 0 | AJ30: 0 | AL30: 0 | AN30: 0 | AO30: 10 | AP30: 2.7731302e-05 | AR30: 0 | AT30: 0 | AU30: 415 | AV30: 0.00016176593 | AW30: 0 | AX30: 0
A31: WRIO Bridge Track & Tower Pvt Ltd Raipur Chhatishgarh | B31: December 2025 | C31: 60250003104660 | D31: West Central | F31: 548699 | G31: 541466 | H31: 0.98681791 | I31: 7233 | J31: 0.013182091 | K31: 103 | L31: 0.00047605402 | M31: 250 | N31: 0.00045562321 | O31: 821 | P31: 0.0037945665 | R31: 0 | T31: 0 | U31: 1471 | V31: 0.0067987909 | X31: 0 | Z31: 0 | AB31: 0 | AD31: 0 | AE31: 93 | AF31: 0.00042983518 | AH31: 0 | AJ31: 0 | AL31: 0 | AN31: 0 | AO31: 93 | AP31: 0.00042983518 | AR31: 0 | AT31: 0 | AU31: 4402 | AV31: 0.020345532 | AX31: 0
A32: WRIO Cosmo Enterprise Raipur Chhatishgarh | B32: December 2025 | D32: West Central | H32: 0 | J32: #DIV/0! | K32: 0 | L32: 0 | M32: 0 | N32: #DIV/0! | O32: 0 | P32: 0 | R32: 0 | T32: 0 | U32: 0 | V32: 0 | X32: 0 | Z32: 0 | AB32: 0 | AD32: 0 | AE32: 0 | AF32: 0 | AH32: 0 | AJ32: 0 | AL32: 0 | AN32: 0 | AO32: 0 | AP32: 0 | AR32: 0 | AT32: 0 | AU32: 0 | AV32: 0 | AX32: 0
A33: WRIO Pathik Engineering Works Rajnandgaon Chhatishgarh | B33: December 2025 | C33: 6250091201415 | D33: West Central | F33: 165540 | G33: 164426 | H33: 0.99327051 | I33: 1114 | J33: 0.0067294914 | K33: 0 | L33: 0 | M33: 71 | N33: 0.00042889936 | O33: 67 | P33: 0.00030966621 | R33: 0 | T33: 0 | U33: 367 | V33: 0.0016962313 | X33: 0 | Z33: 0 | AB33: 0 | AD33: 0 | AE33: 9 | AF33: 4.1596953e-05 | AH33: 0 | AJ33: 0 | AL33: 0 | AN33: 0 | AO33: 321 | AP33: 0.0014836247 | AR33: 0 | AT33: 0 | AU33: 291 | AV33: 0.0013449682 | AX33: 0
A34: WRIO Prakash Metallics Pvt Ltd Raipur Chhatishgarh | B34: December 2025 | C34: 26255259205058 | D34: West Central | F34: 348192 | G34: 342585 | H34: 0.98389682 | I34: 5607 | J34: 0.016103184 | K34: 1368 | L34: 0.0063227369 | M34: 183 | N34: 0.0005255721 | O34: 1036 | P34: 0.0047882715 | R34: 0 | T34: 0 | U34: 1045 | V34: 0.0048298685 | X34: 0 | Z34: 0 | AB34: 0 | AD34: 0 | AE34: 110 | AF34: 0.00050840721 | AH34: 0 | AJ34: 0 | AL34: 0 | AN34: 0 | AO34: 984 | AP34: 0.0045479336 | AR34: 0 | AT34: 0 | AU34: 728 | AV34: 0.0033647313 | AX34: 0
A35: WRIO Prakash Monomers Pvt Ltd Raipur Chhatishgarh | B35: December 2025 | H35: 0 | J35: #DIV/0! | K35: 0 | L35: 0 | M35: 0 | N35: #DIV/0! | O35: 0 | P35: 0 | R35: 0 | T35: 0 | U35: 0 | V35: 0 | X35: 0 | Z35: 0 | AB35: 0 | AD35: 0 | AE35: 0 | AF35: 0 | AH35: 0 | AJ35: 0 | AL35: 0 | AN35: 0 | AO35: 0 | AP35: 0 | AR35: 0 | AT35: 0 | AU35: 0 | AV35: 0 | AX35: 0
A36: WRIO Royal fasteners Raipur Chhatishgarh | B36: December 2025 | C36: 81255001102837 | D36: West Central | F36: 137066 | G36: 135434 | H36: 0.98809333 | I36: 1632 | J36: 0.011906673 | K36: 105 | L36: 0.00048529779 | M36: 67 | N36: 0.00048881561 | O36: 358 | P36: 0.0016546344 | R36: 0 | T36: 0 | U36: 613 | V36: 0.0028332147 | X36: 0 | Z36: 0 | AB36: 0 | AD36: 0 | AE36: 2 | AF36: 9.2437674e-06 | AH36: 0 | AJ36: 0 | AL36: 0 | AN36: 0 | AO36: 52 | AP36: 0.00024033795 | AR36: 0 | AT36: 0 | AU36: 437 | AV36: 0.0020197632 | AX36: 0
A37: WRIO Royal Infraconstru Raipur Chhatishgarh | B37: December 2025 | C37: 60257500205473 | D37: West Central | F37: 692025 | G37: 685418 | H37: 0.99045266 | I37: 6607 | J37: 0.0095473429 | K37: 146 | L37: 0.00067479502 | M37: 17 | N37: 2.4565587e-05 | O37: 2087 | P37: 0.0096458713 | R37: 0 | T37: 0 | U37: 2140 | V37: 0.0098908311 | X37: 0 | Z37: 0 | AB37: 0 | AD37: 0 | AE37: 1 | AF37: 4.6218837e-06 | AH37: 0 | AJ37: 0 | AL37: 0 | AN37: 0 | AO37: 158 | AP37: 0.00073025762 | AR37: 0 | AT37: 0 | AU37: 2058 | AV37: 0.0095118366 | AX37: 0
A38: WRIO Sai Kripa Industries Durg Chhatishgarh | B38: December 2025 | C38: 77255086207666 | D38: West Central | F38: 104520 | G38: 102105 | H38: 0.97689437 | I38: 2415 | J38: 0.023105626 | K38: 5 | L38: 2.3109418e-05 | M38: 75 | N38: 0.00071756602 | O38: 445 | P38: 0.0020567382 | R38: 0 | T38: 0 | U38: 373 | V38: 0.0017239626 | X38: 0 | Z38: 0 | AB38: 0 | AD38: 0 | AE38: 6 | AF38: 2.7731302e-05 | AH38: 0 | AJ38: 0 | AL38: 0 | AN38: 0 | AO38: 391 | AP38: 0.0018071565 | AR38: 0 | AT38: 0 | AU38: 1113 | AV38: 0.0051441566 | AX38: 0
A39: WRIO Sheth & Co. | B39: December 2025 | C39: 81255499104483 | D39: West Central | F39: 48289 | G39: 47859 | H39: 0.99109528 | I39: 430 | J39: 0.0089047195 | K39: 0 | L39: 0 | M39: 24 | N39: 0.0004970076 | O39: 5 | P39: 2.3109418e-05 | R39: 0 | T39: 0 | U39: 216 | V39: 0.00099832688 | X39: 0 | Z39: 0 | AB39: 0 | AD39: 0 | AE39: 17 | AF39: 7.8572023e-05 | AH39: 0 | AJ39: 0 | AL39: 0 | AN39: 0 | AO39: 16 | AP39: 7.3950139e-05 | AR39: 0 | AT39: 0 | AU39: 152 | AV39: 0.00070252632 | AX39: 0
A40: WRIO Technosteel Infraprojects Nagpur Maharastra | B40: December 2025 | D40: West Central | F40: 0 | G40: 0 | H40: #DIV/0! | I40: 0 | J40: #DIV/0! | K40: 0 | L40: 0 | M40: 0 | N40: #DIV/0! | O40: 0 | P40: 0 | R40: 0 | T40: 0 | U40: 0 | V40: 0 | X40: 0 | Z40: 0 | AB40: 0 | AD40: 0 | AE40: 0 | AF40: 0 | AH40: 0 | AJ40: 0 | AL40: 0 | AN40: 0 | AO40: 0 | AP40: 0 | AR40: 0 | AT40: 0 | AU40: 0 | AV40: 0 | AX40: 0
A41: WRIO Veera Track Fasteners Rajnandgaon Chhatishgarh | B41: December 2025 | C41: 3245217206100 | D41: West Central | F41: 15416 | G41: 15215 | H41: 0.9869616 | I41: 201 | J41: 0.013038402 | K41: 13 | L41: 6.0084488e-05 | M41: 2 | N41: 0.00012973534 | O41: 39 | P41: 0.00018025346 | R41: 0 | T41: 0 | U41: 0 | V41: 0 | X41: 0 | Z41: 0 | AB41: 0 | AD41: 0 | AE41: 0 | AF41: 0 | AH41: 0 | AJ41: 0 | AL41: 0 | AN41: 0 | AO41: 116 | AP41: 0.00053613851 | AR41: 0 | AT41: 0 | AU41: 31 | AV41: 0.00014327839 | AX41: 0
A42: SRIO Patil Rail Infrastructure pvt ltd Yellampet, Hyderabad Telangana | B42: 45992 | C42: 60257500205475 | D42: Southern | F42: 304352 | G42: 302822 | H42: =G42/F42 -> 0.99497293 | I42: 1530 | J42: 0 .051 | K42: 0 | L42: 0 | M42: 10 | N42: 0.00012973534 | O42: 16 | P42: 0.00018025346 | Q42: 0 | R42: 0 | S42: 496 | U42: 578 | W42: 0 | X42: 0 | AE42: 5 | AF42: 0 | AO42: 10 | AU42: 415 | AX42: 0
A43: SRIO Patil Rail Infrastructure pvt ltd Yellampet, Hyderabad Telangana | B43: 46023 | C43: 60257500205475 | D43: Southern Central | F43: 235206 | G43: 234269 | H43: =G43/F43 -> 0.99601626 | I43: 937 | K43: 0 | L43: 0 | M43: 20 | O43: 10 | Q43: 0 | S43: 432 | U43: 459 | W43: 0 | X43: 0 | AE43: 4 | AF43: 0 | AO43: 5 | AU43: 7 | AW43: 0 | AX43: 0
A44: SRIO Patil Rail Infrastructure pvt ltd Yellampet, Hyderabad Telangana | B44: Febraury 2026 | C44: 60257500205475 | D44: Southern Central | F44: 264246 | G44: 262745 | I44: 1501 | K44: 0 | L44: 0 | M44: 20 | O44: 43 | Q44: 0 | S44: 473 | U44: 568 | W44: 0 | X44: 0 | AE44: 5 | AF44: 0 | AO44: 35 | AU44: 55 | AW44: 0 | AX44: 0
A45: SRIO Patil Rail Infrastructure pvt ltd Yellampet, Hyderabad Telangana | B45: 46082 | C45: 60257500205475 | D45: Southern Central | F45: 322033 | G45: 319920 | H45: 0.9934 | I45: 2113 | J45: =I45/F45 -> 0.0065614394 | K45: 92 | L45: =K45/F45 -> 0.00028568501 | M45: 7 | N45: =M45/F45 -> 2.1736903e-05 | O45: 4 | P45: =O45/F45 -> 1.2421087e-05 | Q45: 0 | R45: =Q45/F45 -> 0 | S45: 285 | T45: =S45/F45 -> 0.00088500247 | U45: 1098 | V45: =U45/F45 -> 0.0034095885 | W45: 0 | X45: =W45/F45 -> 0 | Y45: 0 | Z45: =Y45/F45 -> 0 | AA45: 0 | AB45: =AA45/F45 -> 0 | AC45: 0 | AD45: =AC45/F45 -> 0 | AE45: 0 | AF45: =AE45/F45 -> 0 | AG45: 0 | AH45: =AG45/F45 -> 0 | AI45: 0 | AJ45: =AI45/F45 -> 0 | AK45: 0 | AL45: =AK45/F45 -> 0 | AM45: 0 | AN45: =AM45/F45 -> 0 | AO45: 42 | AP45: =AO45/F45 -> 0.00013042142 | AQ45: 585 | AR45: =AQ45/F45 -> 0.001816584 | AS45: 0 | AT45: =AS45/F45 -> 0 | AU45: 0 | AV45: =AU45/F45 -> 0 | AW45: 0 | AX45: =AW45/F45 -> 0
A46: SRIO Patil Rail Infrastructure pvt ltd Yellampet, Hyderabad Telangana | B46: 46113 | C46: 60257500205475 | D46: Southern Central | F46: 142298 | G46: 141315 | H46: =G46/F46 -> 0.99309196 | I46: 983 | J46: =I46/F46 -> 0.0069080381 | K46: 18 | L46: =K46/F46 -> 0.0001264951 | M46: 284 | N46: =M46/F46 -> 0.0019958116 | O46: 24 | P46: =O46/F46 -> 0.00016866014 | Q46: 0 | R46: =Q46/F46 -> 0 | S46: 322 | T46: =S46/F46 -> 0.0022628568 | U46: 318 | V46: =U46/F46 -> 0.0022347468 | W46: 0 | X46: =W46/F46 -> 0 | Y46: 0 | Z46: =Y46/F46 -> 0 | AA46: 0 | AB46: =AA46/F46 -> 0 | AC46: 0 | AD46: =AC46/F46 -> 0 | AE46: 0 | AF46: =AE46/F46 -> 0 | AG46: 0 | AH46: =AG46/F46 -> 0 | AI46: 0 | AJ46: =AI46/F46 -> 0 | AK46: 0 | AL46: =AK46/F46 -> 0 | AM46: 0 | AN46: =AM46/F46 -> 0 | AO46: 17 | AP46: =AO46/F46 -> 0.0001194676 | AQ46: 0 | AR46: =AQ46/F46 -> 0 | AS46: 0 | AT46: =AS46/F46 -> 0 | AU46: 0 | AV46: =AU46/F46 -> 0 | AW46: 0 | AX46: =AW46/F46 -> 0

Sheet Plant & Month Wise Defect Analy
B1: ERC Inspection Details
A2: Firm Name | B2: Month | C2: Inspected (Nos.) | D2: Acceptance (Nos.) | E2: % Acceptance | F2: Rejection (Nos.) | G2: % Rejection | H2: Visual (Sheared Edges, Surface Defects) | I2: ="%"&H2 -> %Visual (Sheared Edges, Surface Defects) | J2: Dimensional | K2: ="%"&J2 -> %Dimensional | L2: Cut bar length | M2: ="%"&L2 -> %Cut bar length | N2: Cut Bar diameter | O2: ="%"&N2 -> %Cut Bar diameter | P2: Turning length | Q2: ="%"&P2 -> %Turning length | R2: Turning Bar Diameter | S2: ="%"&R2 -> %Turning Bar Diameter | T2: Flat Bearing Area | U2: ="%"&T2 -> %Flat Bearing Area | V2: Application & Deflection test | W2: ="%"&V2 -> %Application & Deflection test | X2: Chemical Composition | Y2: ="%"&X2 -> %Chemical Composition | Z2: Toe load | AA2: ="%"&Z2 -> %Toe load | AB2: Hardness | AC2: ="%"&AB2 -> %Hardness | AD2: Microstructure | AE2: ="%"&AD2 -> %Microstructure | AF2: Grain size | AG2: ="%"&AF2 -> %Grain size | AH2: Depth of Decarburization | AI2: ="%"&AH2 -> %Depth of Decarburization | AJ2: Inclusion rating | AK2: ="%"&AJ2 -> %Inclusion rating | AL2: MPI | AM2: ="%"&AL2 -> %MPI | AN2: Forging defect | AO2: ="%"&AN2 -> %Forging defect | AP2: Marking | AQ2: ="%"&AP2 -> %Marking | AR2: Embossing Die Impression / Failure | AS2: ="%"&AR2 -> %Embossing Die Impression / Failure | AT2: Other (less weight) | AU2: ="%"&AT2 -> %Other (less weight)
A3: NRIO Adinath Industries Bhiwadi Haryana | B3: April 2025 | C3: 122517 | D3: =C3-R3-J3-L3-P3-AB3-AR3-AL3 -> 122421 | E3: =D3/C3 -> 0.99921644 | F3: =C3-D3 -> 96 | G3: =F3/C3 -> 0.00078356473 | I3: =H3/$C$3 -> 0 | J3: 43 | K3: =J3/C3 -> 0.0003509717 | L3: 5 | M3: =L3/$C$3 -> 4.0810663e-05 | N3: 0 | O3: =N3/$C$3 -> 0 | P3: 0 | Q3: =P3/$C$3 -> 0 | R3: 0 | S3: =R3/$C$3 -> 0 | U3: =T3/$C$3 -> 0 | W3: =V3/$C$3 -> 0 | Y3: =X3/$C$3 -> 0 | AA3: =Z3/$C$3 -> 0 | AB3: 48 | AC3: =AB3/$C$3 -> 0.00039178236 | AE3: =AD3/$C$3 -> 0 | AG3: =AF3/$C$3 -> 0 | AI3: =AH3/$C$3 -> 0 | AK3: =AJ3/$C$3 -> 0 | AL3: 0 | AM3: =AL3/$C$3 -> 0 | AO3: =AN3/$C$3 -> 0 | AQ3: =AP3/$C$3 -> 0 | AR3: 0 | AS3: =AR3/$C$3 -> 0 | AU3: =AT3/$C$3 -> 0 | AV3: =AR3+AL3+AB3+T3+R3+P3+L3+J3-F3+AT3+N3+H3+AP3+AN3+AJ3+AH3+AF3+AD3+Z3+X3+V3 -> 0
A4: NRIO Adinath Industries Bhiwadi Haryana | B4: May 2025 | C4: 137207 | D4: =C4-R4-J4-L4-P4-AB4-AR4-AL4 -> 137102 | E4: =D4/C4 -> 0.99923473 | F4: =C4-D4 -> 105 | G4: =F4/C4 -> 0.00076526708 | I4: =H4/$C$3 -> 0 | J4: 48 | K4: =J4/C4 -> 0.00034983638 | L4: 0 | M4: =L4/$C$3 -> 0 | N4: 0 | O4: =N4/$C$3 -> 0 | P4: 0 | Q4: =P4/$C$3 -> 0 | R4: 0 | S4: =R4/$C$3 -> 0 | U4: =T4/$C$3 -> 0 | W4: =V4/$C$3 -> 0 | Y4: =X4/$C$3 -> 0 | AA4: =Z4/$C$3 -> 0 | AB4: 57 | AC4: =AB4/$C$3 -> 0.00046524156 | AE4: =AD4/$C$3 -> 0 | AG4: =AF4/$C$3 -> 0 | AI4: =AH4/$C$3 -> 0 | AK4: =AJ4/$C$3 -> 0 | AL4: 0 | AM4: =AL4/$C$3 -> 0 | AO4: =AN4/$C$3 -> 0 | AQ4: =AP4/$C$3 -> 0 | AR4: 0 | AS4: =AR4/$C$3 -> 0 | AU4: =AT4/$C$3 -> 0 | AV4: =AR4+AL4+AB4+T4+R4+P4+L4+J4-F4+AT4+N4+H4+AP4+AN4+AJ4+AH4+AF4+AD4+Z4+X4+V4 -> 0
A5: NRIO Adinath Industries Bhiwadi Haryana | B5: June 2025 | C5: 165193 | D5: =C5-R5-J5-L5-P5-AB5-AR5-AL5 -> 164635 | E5: =D5/C5 -> 0.99662213 | F5: =C5-D5 -> 558 | G5: =F5/C5 -> 0.0033778671 | I5: =H5/$C$3 -> 0 | J5: 121 | K5: =J5/C5 -> 0.00073247656 | L5: 107 | M5: =L5/$C$3 -> 0.00087334819 | N5: 0 | O5: =N5/$C$3 -> 0 | P5: 32 | Q5: =P5/$C$3 -> 0.00026118824 | R5: 30 | S5: =R5/$C$3 -> 0.00024486398 | U5: =T5/$C$3 -> 0 | W5: =V5/$C$3 -> 0 | Y5: =X5/$C$3 -> 0 | AA5: =Z5/$C$3 -> 0 | AB5: 100 | AC5: =AB5/$C$3 -> 0.00081621326 | AE5: =AD5/$C$3 -> 0 | AG5: =AF5/$C$3 -> 0 | AI5: =AH5/$C$3 -> 0 | AK5: =AJ5/$C$3 -> 0 | AL5: 0 | AM5: =AL5/$C$3 -> 0 | AO5: =AN5/$C$3 -> 0 | AQ5: =AP5/$C$3 -> 0 | AR5: 168 | AS5: =AR5/$C$3 -> 0.0013712383 | AU5: =AT5/$C$3 -> 0 | AV5: =AR5+AL5+AB5+T5+R5+P5+L5+J5-F5+AT5+N5+H5+AP5+AN5+AJ5+AH5+AF5+AD5+Z5+X5+V5 -> 0
A6: NRIO Adinath Industries Bhiwadi Haryana | B6: July 2025 | C6: 155705 | D6: =C6-R6-J6-L6-P6-AB6-AR6-AL6 -> 155046 | E6: =D6/C6 -> 0.99576764 | F6: =C6-D6 -> 659 | G6: =F6/C6 -> 0.0042323625 | I6: =H6/$C$3 -> 0 | J6: 116 | K6: =J6/C6 -> 0.00074499855 | L6: 142 | M6: =L6/$C$3 -> 0.0011590228 | N6: 0 | O6: =N6/$C$3 -> 0 | P6: 72 | Q6: =P6/$C$3 -> 0.00058767355 | R6: 59 | S6: =R6/$C$3 -> 0.00048156582 | U6: =T6/$C$3 -> 0 | W6: =V6/$C$3 -> 0 | Y6: =X6/$C$3 -> 0 | AA6: =Z6/$C$3 -> 0 | AB6: 71 | AC6: =AB6/$C$3 -> 0.00057951141 | AE6: =AD6/$C$3 -> 0 | AG6: =AF6/$C$3 -> 0 | AI6: =AH6/$C$3 -> 0 | AK6: =AJ6/$C$3 -> 0 | AL6: 0 | AM6: =AL6/$C$3 -> 0 | AO6: =AN6/$C$3 -> 0 | AQ6: =AP6/$C$3 -> 0 | AR6: 199 | AS6: =AR6/$C$3 -> 0.0016242644 | AU6: =AT6/$C$3 -> 0 | AV6: =AR6+AL6+AB6+T6+R6+P6+L6+J6-F6+AT6+N6+H6+AP6+AN6+AJ6+AH6+AF6+AD6+Z6+X6+V6 -> 0
A7: NRIO Adinath Industries Bhiwadi Haryana | B7: August 2025 | C7: 170675 | D7: =C7-R7-J7-L7-P7-AB7-AR7-AL7 -> 169978 | E7: =D7/C7 -> 0.99591622 | F7: =C7-D7 -> 697 | G7: =F7/C7 -> 0.004083785 | I7: =H7/$C$3 -> 0 | J7: 127 | K7: =J7/C7 -> 0.00074410429 | L7: 177 | M7: =L7/$C$3 -> 0.0014446975 | N7: 0 | O7: =N7/$C$3 -> 0 | P7: 76 | Q7: =P7/$C$3 -> 0.00062032208 | R7: 28 | S7: =R7/$C$3 -> 0.00022853971 | U7: =T7/$C$3 -> 0 | W7: =V7/$C$3 -> 0 | Y7: =X7/$C$3 -> 0 | AA7: =Z7/$C$3 -> 0 | AB7: 86 | AC7: =AB7/$C$3 -> 0.0007019434 | AE7: =AD7/$C$3 -> 0 | AG7: =AF7/$C$3 -> 0 | AI7: =AH7/$C$3 -> 0 | AK7: =AJ7/$C$3 -> 0 | AL7: 0 | AM7: =AL7/$C$3 -> 0 | AO7: =AN7/$C$3 -> 0 | AQ7: =AP7/$C$3 -> 0 | AR7: 203 | AS7: =AR7/$C$3 -> 0.0016569129 | AU7: =AT7/$C$3 -> 0 | AV7: =AR7+AL7+AB7+T7+R7+P7+L7+J7-F7+AT7+N7+H7+AP7+AN7+AJ7+AH7+AF7+AD7+Z7+X7+V7 -> 0
